Workbook
Name C_to_CO2: Conversions!$B$5
Name kg_to_m3: Conversions!$B$3
Name t_to_m3: Conversions!$B$2
Name tC_to_m3: Conversions!$B$4

Sheet Sheet1
A1: Metadata | B1: Metadata | C1: Metadata | D1: Metadata | E1: Metadata | F1: Metadata | G1: Metadata | H1: Metadata | I1: Metadata | J1: Metadata | K1: Metadata | L1: Metadata | M1: Metadata | N1: Metadata | O1: Protocol | P1: Protocol | S1: Drivers | T1: Drivers | U1: Drivers | X1: Drivers | Y1: Drivers | Z1: Drivers | AA1: Drivers | AB1: Drivers | AC1: Drivers | AD1: Drivers | AE1: Drivers | AF1: Drivers | AG1: Drivers | AH1: Drivers | AI1: Drivers | AJ1: Drivers | AK1: Drivers | AL1: Drivers | AM1: Drivers | AN1: Drivers | AO1: Drivers | AP1: Drivers | AQ1: Drivers | AR1: Drivers | AS1: Drivers | AT1: Drivers | AU1: Drivers | AV1: Drivers | AW1: Drivers | AX1: Drivers | AY1: Drivers | AZ1: Protocol | BA1: Protocol | BE1: Protocol | BF1: Protocol | BG1: Drivers | BH1: Drivers | BI1: Outcomes | BJ1: Outcomes | BL1: Outcomes | BM1: Outcomes | BN1: Outcomes | BO1: Outcomes | BP1: Outcomes | BQ1: Outcomes | BR1: Outcomes | BT1: Outcomes | BU1: Outcomes | BV1: Outcomes | BW1: Outcomes | BX1: Outcomes | BZ1: Outcomes | CA1: Outcomes | CB1: Outcomes | CC1: Outcomes | CD1: Outcomes | CE1: Outcomes | CF1: Outcomes | CG1: Outcomes | CH1: Outcomes | CI1: Outcomes | CJ1: Outcomes | CK1: Outcomes | CL1: Outcomes | CM1: Outcomes | CN1: Outcomes | CO1: Outcomes | CP1: Outcomes | CQ1: Outcomes | CR1: Outcomes | CS1: Outcomes | CU1: Outcomes | CV1: Outcomes | CW1: Outcomes | CY1: Outcomes | DA1: Outcomes | DB1: Model | DC1: Model | DD1: Model | DE1: Model | DF1: Model | DG1: Model | DH1: Model | DI1: Model | DJ1: Model | DK1: Model | DL1: Model | DM1: Model | DN1: Model | DO1: Model | DP1: Model | DQ1: Model | DR1: Model | DS1: Model | DT1: Model | DU1: Model | DV1: Model | DW1: Model | DX1: Model | DY1: Model | DZ1: Model | EA1: Model | EB1: Model | EC1: Model | ED1: Model | EE1: Model | EF1: Model | EG1: Model | EH1: Model | EI1: Model | EJ1: Model | EK1: Model | EL1: Model | EM1: Model | EN1: Model | EW1: Protocol | EX1: Protocol | EY1: Protocol | EZ1: Protocol | FB1: Protocol | FC1: Protocol
A2: Paper description | B2: Paper description | C2: Paper description | D2: Paper description | E2: Paper description | F2: Paper description | G2: Paper description | H2: Paper description | I2: Paper description | J2: Paper description | K2: Paper description | L2: Paper description | M2: Paper description | N2: Protocol | O2: Extraction | P2: Post-extraction | Q2: Extraction round | S2: Driver | T2: Driver | U2: Driver | X2: Change in practices | Y2: Change in practices | Z2: Change in practices | AA2: Change in practices | AB2: Change in practices | AC2: Change in practices | AD2: Change in practices | AE2: Change in practices | AF2: Change in practices | AG2: Change in practices | AH2: Change in practices | AI2: Change in practices | AJ2: Change in practices | AK2: Change in practices | AL2: Change in practices | AM2: Change in practices | AN2: Change in practices | AO2: Environmental change | AP2: Environmental change | AQ2: Environmental change | AR2: Environmental change | AS2: Environmental change | AT2: Environmental change | AU2: Environmental change | AV2: Environmental change | AW2: Environmental change | AX2: Environmental change | AY2: Environmental change | AZ2: Post-extraction | BA2: QC | BE2: QC | BF2: QC | BG2: DataCorrection | BH2: DataCorrection | BI2: Carbon_outcome | BJ2: Carbon_outcome | BL2: Carbon_outcome | BM2: Carbon_outcome | BN2: Carbon_outcome | BO2: Carbon_outcome | BP2: Carbon_outcome | BQ2: Carbon_outcome | BR2: Carbon_outcome | BT2: Carbon_outcome | BU2: Carbon_outcome | BV2: Carbon_outcome | BW2: Carbon_outcome | BX2: Carbon_outcome | BZ2: Carbon_outcome | CB2: Non_c_outcomes | CC2: Non_c_outcomes | CD2: Non_c_outcomes | CE2: Non_c_outcomes | CF2: Non_c_outcomes | CG2: Non_c_outcomes | CH2: Non_c_outcomes | CI2: Non_c_outcomes | CJ2: Non_c_outcomes | CK2: Non_c_outcomes | CL2: Non_c_outcomes | CM2: Non_c_outcomes | CN2: Non_c_outcomes | CO2: Non_c_outcomes | CP2: DataCorrection | CQ2: DataCorrection | CR2: DataCorrection | CS2: DataCorrection | CU2: DataCorrection | CV2: DataCorrection | CW2: DataCorrection | CY2: DataCorrection | DA2: DataCorrection | DB2: Context definition | DC2: DataCorrection | DD2: DataCorrection | DE2: Context definition | DF2: Context definition | DG2: Context definition | DH2: DataCorrection | DI2: Context definition | DJ2: Context definition | DK2: Context definition | DL2: Context definition | DM2: Context definition | DN2: QC | DO2: DataCorrection | DP2: Context definition | DQ2: Context definition | DR2: Context definition | DS2: Context definition | DT2: Processes | DU2: Processes | DV2: ProcessesDetails | DW2: ProcessesDetails | DX2: ProcessesDetails | DY2: QC | DZ2: Post-extraction | EA2: Processes | EB2: Processes | EC2: Processes | ED2: Processes | EE2: Processes | EF2: Processes | EG2: Processes | EH2: Processes | EI2: Processes | EJ2: Processes | EK2: Processes | EL2: Processes | EM2: Processes | EN2: Processes | EW2: Post-extraction | EX2: Post-extraction | EY2: Post-extraction | EZ2: Post-extraction | FB2: Post-extraction | FC2: QC
X3: #CAACCB | Y3: #CAACCB | Z3: #CAACCB | AA3: #CAACCB | AB3: #CAACCB | AC3: #CAACCB | AD3: #CAACCB | AE3: #CAACCB | AF3: #CAACCB | AG3: #CAACCB | AH3: #CAACCB | AI3: #CAACCB | AJ3: #CAACCB | AK3: #CAACCB | AL3: #CAACCB | AM3: #CAACCB | AN3: #CAACCB | AO3: #994F93 | AP3: #994F93 | AQ3: #994F93 | AR3: #994F93 | AS3: #994F93 | AT3: #994F93 | AU3: #994F93 | AV3: #994F93 | AW3: #994F93 | AX3: #994F93 | AY3: #994F93 | DN3: #77777 | DT3: #90C987 | DU3: #90C987 | DV3: #90C987 | DW3: #90C987 | DX3: #90C987 | DY3: #77777 | EA3: #90C987 | EB3: #90C987 | EC3: #90C987 | ED3: #90C987 | EE3: #90C987 | EF3: #90C987 | EG3: #90C987 | EH3: #90C987 | EI3: #90C987 | EJ3: #90C987 | EK3: #90C988 | EL3: #90C989 | EM3: #90C990 | EN3: #90C991
A4: Publication | B4: Topic | C4: Topic | D4: Authors | E4: Topic | F4: Topic | G4: Journal | H4: Publication | I4: Publication | J4: Publication | K4: Publication | L4: Publication | M4: Authors | N4: Exclusion | O4: Full revision | P4: Revision | S4: driver description | T4: driver description | U4: driver description | V4: Silviculture for removals | X4: Silviculture for removals | Y4: Silviculture for removals | Z4: Silviculture for removals | AA4: Silviculture for removals | AB4: Silviculture for productivity | AC4: Silviculture for productivity | AD4: Silviculture for productivity | AE4: Silviculture for productivity | AF4: Supply chain | AG4: Supply chain | AH4: Supply chain | AI4: Supply chain | AJ4: Supply chain | AK4: Supply chain | AL4: Technology | AM4: Technology | AN4: Technology | AO4: Environmental change | AP4: Environmental change | AQ4: Environmental change | AR4: Environmental change | AS4: Environmental change | AT4: Environmental change | AU4: Demand | AV4: Demand | AW4: Demand | AX4: Demand | AY4: Demand | AZ4: QC | BA4: All | BE4: AllEnvir | BF4: AllEnvir | BG4: MainDriver | BH4: MainDriver | BI4: Wood amount | BJ4: Wood amount | BL4: Wood amount | BM4: Wood amount | BN4: Wood amount | BO4: Wood amount | BP4: Wood amount | BQ4: Wood amount | BR4: Cumulated C balance | BS4: Cumulated C balance | BT4: Cumulated C balance | BU4: Cumulated C balance | BV4: Cumulated C balance | BW4: Cumulated C balance | BX4: Cumulated C balance | BZ4: Cumulated C balance | CA4: Substitution coefficient | CB4: LCAOutcomes | CC4: biogeochemicalOutcomes | CD4: biogeochemicalOutcomes | CE4: biogeochemicalOutcomes | CF4: biogeochemicalOutcomes | CG4: biogeochemicalOutcomes | CH4: biogeochemicalOutcomes | CI4: biophysicalOutcomes | CJ4: biophysicalOutcomes | CK4: biophysicalOutcomes | CL4: biophysicalOutcomes | CM4: biophysicalOutcomes | CN4: ecologicalOutcomes | CO4: economicalOutcomes | CP4: driver description | CQ4: Wood amount | CR4: Carbon_outcome | CS4: Carbon_outcome | CU4: Carbon_outcome | CV4: Carbon_outcome | CW4: Carbon_outcome | CY4: Carbon_outcome | DA4: Carbon_outcome | DB4: Location | DC4: Location | DD4: Location | DE4: Time period | DF4: Time period | DG4: Time period | DI4: Wood affected by driver change | DJ4: Wood affected by driver change | DK4: Wood affected by driver change | DL4: Wood affected by driver change | DM4: Sector scale | DN4: QC | DO4: Wood affected by driver change | DP4: Wood affected by driver change | DQ4: Wood affected by driver change | DR4: Wood affected by driver change | DS4: Wood affected by driver change | DT4: SubstitutionShortcut | DU4: SubstitutionShortcut | DV4: SubstitutionShortcut | DW4: SubstitutionShortcut | DX4: SubstitutionShortcut | DY4: QC | DZ4: SubstitutionShortcut | EA4: C fluxes | EB4: C fluxes | EC4: C fluxes | ED4: C fluxes | EE4: C fluxes | EF4: C fluxes | EG4: C fluxes | EH4: C fluxes | EI4: C fluxes | EJ4: C fluxes | EK4: Dynamics | EL4: Dynamics | EM4: Dynamics | EN4: Dynamics | EW4: QC | EX4: QC | EY4: QC | EZ4: QC | FB4: QC | FC4: DriverCheck
V5: #D9CCE3 | W5: #D9CCE3 | X5: #D9CCE3 | Y5: #D9CCE3 | Z5: #D9CCE3 | AA5: #D9CCE3 | AB5: #D9CCE3 | AC5: #D9CCE3 | AD5: #D9CCE3 | AE5: #D9CCE3 | AF5: #CAACCB | AG5: #CAACCB | AH5: #CAACCB | AI5: #CAACCB | AJ5: #CAACCB | AK5: #CAACCB | AL5: #BA8DB4 | AM5: #BA8DB4 | AN5: #BA8DB4 | AO5: #994F88 | AP5: #994F88 | AQ5: #994F88 | AR5: #994F88 | AS5: #994F88 | AT5: #994F88 | AU5: #882E72 | AV5: #882E72 | AW5: #882E72 | AX5: #882E72 | AY5: #882E72 | DN5: #77777 | DT5: #CAE0AB | DU5: #CAE0AB | DV5: #CAE0AB | DW5: #CAE0AB | DX5: #CAE0AB | DY5: #77777 | EA5: #90C987 | EB5: #90C987 | EC5: #90C987 | ED5: #90C987 | EE5: #90C987 | EF5: #90C987 | EG5: #90C987 | EH5: #90C987 | EI5: #90C987 | EJ5: #90C987 | EK5: #4EB265 | EL5: #4EB265 | EM5: #4EB265 | EN5: #4EB265
A6: Publication | B6: Topic | C6: Topic | D6: Authors | E6: Topic | F6: Topic | G6: Journal | H6: Publication | I6: Publication | J6: Publication | K6: Publication | L6: Publication | M6: Authors | N6: Exclusion | O6: Full revision | P6: Revision | R6: QC | S6: driver description | T6: driver description | U6: driver description | V6: Silviculture for removals | W6: Silviculture for removals | X6: Silviculture for removals | Y6: Silviculture for removals | Z6: Silviculture for removals | AA6: Silviculture for removals | AB6: Silviculture for productivity | AC6: Silviculture for productivity | AD6: Silviculture for productivity | AE6: Silviculture for productivity | AF6: Supply chain | AG6: Supply chain | AH6: Supply chain | AI6: Supply chain | AJ6: Supply chain | AK6: Supply chain | AL6: Technology | AM6: Technology | AN6: Technology | AO6: Environmental change | AP6: Environmental change | AQ6: Environmental change | AR6: Environmental change | AS6: Environmental change | AT6: Environmental change | AU6: Demand | AV6: Demand | AW6: Demand | AX6: Demand | AY6: Demand | AZ6: QC | BA6: All | BE6: AllEnvir | BF6: AllEnvir | BG6: MainDriver | BH6: MainDriver | BI6: Wood amount | BJ6: Wood amount | BL6: Wood amount | BM6: Wood amount | BN6: Wood amount | BO6: Wood amount | BP6: Wood amount | BQ6: Wood amount | BR6: Cumulated C balance | BS6: Cumulated C balance | BT6: Cumulated C balance | BU6: Cumulated C balance | BV6: Cumulated C balance | BW6: Cumulated C balance | BX6: Cumulated C balance | BZ6: Cumulated C balance | CA6: Substitution coefficient | CB6: LCAOutcomes | CC6: biogeochemicalOutcomes | CD6: biogeochemicalOutcomes | CE6: biogeochemicalOutcomes | CF6: biogeochemicalOutcomes | CG6: biogeochemicalOutcomes | CH6: biogeochemicalOutcomes | CI6: biophysicalOutcomes | CJ6: biophysicalOutcomes | CK6: biophysicalOutcomes | CL6: biophysicalOutcomes | CM6: biophysicalOutcomes | CN6: ecologicalOutcomes | CO6: economicalOutcomes | CP6: driver description | CQ6: Wood amount | CR6: Carbon_outcome | CS6: Carbon_outcome | CU6: Carbon_outcome | CV6: Carbon_outcome | CW6: Carbon_outcome | CY6: Carbon_outcome | DA6: Carbon_outcome | DB6: Location | DC6: Location | DD6: Location | DE6: Time period | DF6: Time period | DG6: Time period | DI6: Wood affected by driver change | DJ6: Wood affected by driver change | DK6: Wood affected by driver change | DL6: Wood affected by driver change | DM6: Sector scale | DN6: QC | DO6: Wood affected by driver change | DP6: Wood affected by driver change | DQ6: Wood affected by driver change | DR6: Wood affected by driver change | DS6: Wood affected by driver change | DT6: SubstitutionShortcut | DU6: SubstitutionShortcut | DV6: SubstitutionShortcut | DW6: SubstitutionShortcut | DX6: SubstitutionShortcut | DY6: QC | DZ6: SubstitutionShortcut | EA6: Biogenic in-situ C | EB6: Biogenic in-situ C | EC6: Biogenic in-situ C | ED6: Biogenic ex-situ C | EE6: Biogenic ex-situ C | EF6: Biogenic ex-situ C | EG6: Fossil in-situ | EH6: Fossil ex-situ | EI6: Fossil ex-situ | EJ6: Fossil ex-situ | EK6: C dynamics | EL6: C dynamics | EM6: Market-based feedbacks | EN6: Market-based feedbacks | EP6: =COUNTIF($EP8:$EP1666,"Whole sector") -> 0 | EQ6: =COUNTIF($EQ8:$EQ1666,"Ecosystem approach") -> 236 | ER6: =COUNTIF($ER8:$ER1666,"Technology approach") -> 355 | EW6: QC | EX6: QC | EY6: QC | EZ6: QC | FB6: QC | FC6: DriverCheck | FD6: QCv7 | FE6: QC8_AV
A7: Source Title | B7: Author Keywords | C7: Keywords Plus | D7: Authors | E7: Article_Title | F7: Abstract | G7: Journal_ISO_Abbreviation | H7: Document type | I7: Publication_Year | J7: Times_cited | K7: DOI | L7: multipaper_index | M7: PaperID | N7: Exclusion | O7: Reviewer | P7: Reviewer2 | Q7: Extraction round | R7: ReviewerQCv7 | S7: driver definition | T7: name_ref | U7: name_alternative | V7: unmanaged forest to managed forest | W7: afforestation | X7: area subject to harvest | Y7: unspecified harvest increase | Z7: rotation length | AA7: cutting intensity | AB7: species | AC7: plantation density | AD7: fertilisation | AE7: site fertility | AF7: harvesting system | AG7: location of industry | AH7: supply chain organization | AI7: recycling | AJ7: end of life disposal | AK7: products lifespan | AL7: efficiency improvement | AM7: technologies/design switch | AN7: CCS | AO7: Water table | AP7: Temperature | AQ7: rainfall | AR7: CO2 fertilization | AS7: disturbance | AT7: N deposition | AU7: Unspecified policy | AV7: gdp, population | AW7: Exogenous wood price | AX7: Exogenous C price | AY7: exogenous land use change | AZ7: driverCheck | BA7: PracticesCheck | BB7: Nsilvicuture | BC7: Nsupplychain | BD7: Ntechnology | BE7: Ndemand | BF7: Nenvir | BG7: driver1 | BH7: driver1Cat | BI7: Qwood_stageInput | BJ7: Qwood_varInput | BK7: QwoodInPublication | BL7: Qwood_unitInput | BM7: Qwood_refInput | BN7: Qwood_alternativeInput | BO7: Qwood_ratioInput | BP7: Qwood_deltaInput | BQ7: Qwood_delta_m3woodInput | BR7: C_signInput | BS7: CInPublication | BT7: C_unitInput | BU7: C_refInput | BV7: C_alternativeInput | BW7: CratioInput | BX7: CdeltaInput | BZ7: Cdelta_tCO2Input | CA7: substitutionInput | CB7: LCA scores | CC7: CH4 | CD7: CO | CE7: N2O | CF7: Nox | CG7: Sox | CH7: VOC | CI7: Climate | CJ7: albedo | CK7: water quantity | CL7: water quality | CM7: erosion | CN7: biodiversity | CO7: price/economic welfare/social cost | CP7: Ref_check | CQ7: Qwood_ref | CR7: Qwood_alternative | CS7: Qwood_delta_m3wood | CT7: Qwood_delta_m3wood_HWP | CU7: C_ref | CV7: C_alternative | CW7: Cdelta_tCO2 | CX7: subsitution_init | CY7: substitution | CZ7: substitution_HWP | DA7: Cratio | DB7: scale | DC7: scaleAgg | DD7: country | DE7: time_start | DF7: time_end | DG7: time_length | DH7: time_horizon | DI7: UpstreamInput | DJ7: EnergyInput | DK7: PulpPaperInput | DL7: TimberInput | DM7: economy_sector | DN7: productsCheck | DO7: singleProduct | DP7: Upstream | DQ7: Energy | DR7: Pulp/Paper | DS7: Timber | DT7: self-calculated DF | DU7: displacement factor used | DV7: energy DF origin | DW7: material DF origin | DX7: overall DF origin | DY7: substitutionDFCheck | DZ7: substitution_shortcut | EA7: soilC | EB7: harv_residues | EC7: live_biomass_C | ED7: products_storage_C | EE7: eol_biogenic | EF7: off_product_biogenic | EG7: forestry_emiss | EH7: manufacturing_emiss | EI7: maintenance_emiss | EJ7: eol_fossil_emiss | EK7: biogenic_dyn | EL7: fossil_dyn | EM7: LUC_dyn | EN7: rebound_dyn | EO7: Publication quality | EP7: modelApproach | EQ7: ecosystem aproach | ER7: technology approach | ES7: C neutral forest and HWP assumption | ET7: All C | EU7: In-situ only assumption | EV7: Searchinger's assumption | EW7: Comment | EX7: Check exclusion | EY7: Outlier? | EZ7: Check outlier | FA7: Check_paradox | FB7: Check_AV | FC7: CheckSL
A8: ENVIRONMENTAL RESEARCH LETTERS | B8: forests; climate; environment; policy; bioenergy | C8: HARVEST RESIDUES; CARBON; LAND | D8: Birdsey, R; Duffy, P; Smyth, C; Akurz, W; Dugan, AJ; Houghton, R | E8: Climate, economic, and environmental impacts of producing wood for bioenergy | F8: Increasing combustion of woody biomass for electricity has raised concerns and produced conflicting statements about impacts on atmospheric greenhouse gas (GHG) concentrations, climate, and other forest values such as timber supply and biodiversity. The purposes of this concise review of current literature are to (1) examine impacts on net GHG emissions and climate from increasing bioenergy production from forests and exporting wood pellets to Europe from North America, (2) develop a set of science-based recommendations about the circumstances that would result in GHG reductions or increases in the atmosphere, and (3) identify economic and environmental impacts of increasing bioenergy use of forests. We find that increasing bioenergy production and pellet exports often increase net emissions of GHGs for decades or longer, depending on source of feedstock and its alternate fate, time horizon of analysis, energy emissions associated with the supply chain and fuel substitution, and impacts on carbon cycling of forest ecosystems. Alternative uses of roundwood often offer larger reductions in GHGs, in particular long-lived wood products that store carbon for longer periods of time and can achieve greater substitution benefits than bioenergy. Other effects of using wood for bioenergy may be considerable including induced land-use change, changes in supplies of wood and other materials for construction, albedo and non-radiative effects of land-cover change on climate, and long-term impacts on soil productivity. Changes in biodiversity and other ecosystem attributes may be strongly affected by increasing biofuel production, depending on source of material and the projected scale of biofuel production increases. | G8: Environ. Res. Lett. | I8: 2018 | K8: 10.1088/1748-9326/aab9d5 | M8: =LEFT($D8,FIND(",",$D8)-1)&"_"&I8&L8 -> Birdsey_2018 | N8: review | O8: SL | Q8: v4 | CA8: =IFERROR(BZ8/BQ8,"") | CT8: =IF(BI8="Roundwood",$CS8/2,$CS8) -> 0 | CX8: =IFERROR($CW8/$CS8,"") | CZ8: =IFERROR($CW8/$CT8,"") | EP8: =IF(AND(AND(AND(OR($EC8=1,$EB8=1),OR($EH8=1,$EF8=1)),SUM($EA8:$EE8,$EK8)>=3),SUM($EF8:$EJ8)>=2),"Whole sector approach","") | EQ8: =IF(AND(AND(OR($EC8=1,$EB8=1),AND($EH8=0,$EF8=0)),SUM($EA8:$EE8,$EK8)>=3),"Ecosystem approach","") | ER8: =IF(AND(AND(AND($EC8=0,$EB8=0),OR($EH8=1,$EF8=1)),SUM($EG8:$EJ8)>=2),"Technology approach","") | ES8: =IF(AND($EC8+$EB8+$EE8+$EA8+$EF8+$EG8=0,$N8="included"),"C neutral forest and HWP assumption","") | ET8: =IF(AND(AND(AND($EC8+$EB8+$EA8+$EG8>=2,$EF8+$EH8+$EI8>=1),$ED8+$EE8>=1),$N8="included"),"All C pools assumption","") | EU8: =IF(AND($ED8+$EE8+$EI8+$EH8+$EF8=0,$N8="included"),"In-situ only assumption","") | EX8: okVB | EY8: =IF(ISNUMBER(BW8),IF(ABS(BW8-[1]QC_indicators!$B$2)>3*[1]QC_indicators!$C$2,"C ratio",IF(ISNUMBER(CA8),IF(ABS(CA8-[1]QC_indicators!$B$1)>3*[1]QC_indicators!$C$1,"DF","no"))),IF(ISNUMBER(CA8),IF(ABS(CA8-[1]QC_indicators!$B$1)>3*[1]QC_indicators!$C$1,"DF","no"))) -> FALSE | FA8: =IF(LEN($CY8)=0,"",IF(AND($CY8<(-0.05),$ES8="C neutral forest and HWP assumption"),"Cneutral paradox",IF(AND($CY8>0.05,$EU8="In-situ only assumption"),"In-situ only paradox","")))
A9: GLOBAL CHANGE BIOLOGY | B9: carbon retention curve; carbon sequestration; cascading; climate change; first-order decay; half-life; low-carbon economy; mitigation; wood industry | C9: FOREST MANAGEMENT-PRACTICES; LIFE-CYCLE ASSESSMENT; GREENHOUSE-GAS; CLIMATE-CHANGE; ROTATION LENGTH; SEQUESTRATION; STORAGE; IMPACTS; DECOMPOSITION; DYNAMICS | D9: Brunet-Navarro, P; Jochheim, H; Muys, B | E9: Modelling carbon stocks and fluxes in the wood product sector: a comparative review | F9: In addition to forest ecosystems, wood products are carbon pools that can be strategically managed to mitigate climate change. Wood product models (WPMs) simulating the carbon balance of wood production, use and end of life can complement forest growth models to evaluate the mitigation potential of the forest sector as a whole. WPMs can be used to compare scenarios of product use and explore mitigation strategies. A considerable number of WPMs have been developed in the last three decades, but there is no review available analysing their functionality and performance. This study analyses and compares 41 WPMs. One surprising initial result was that we discovered the erroneous implementation of a few concepts and assumptions in some of the models. We further described and compared the models using six model characteristics (bucking allocation, industrial processes, carbon pools, product removal, recycling and substitution effects) and three model-use characteristics (system boundaries, model initialization and evaluation of results). Using a set of indicators based on the model characteristics, we classified models using a hierarchical clustering technique and differentiated them according to their increasing degrees of complexity and varying levels of user support. For purposes of simulating carbon stock in wood products, models with a simple structure may be sufficient, but to compare climate change mitigation options, complex models are needed. The number of models has increased substantially over the last ten years, introducing more diversity and accuracy. Calculation of substitution effects and recycling has also become more prominent. However, the lack of data is still an important constraint for a more realistic estimation of carbon stocks and fluxes. Therefore, if the sector wants to demonstrate the environmental quality of its products, it should make it a priority to provide reliable life cycle inventory data, particularly regarding aspects of time and location. | G9: Glob. Change Biol. | H9: Review | I9: 2016 | J9: 34 | K9: 10.1111/gcb.13235 | M9: =LEFT($D9,FIND(",",$D9)-1)&"_"&I9&L9 -> Brunet-Navarro_2016 | N9: review | O9: AV | Q9: v6 | CA9: =IFERROR(BZ9/BQ9,"") | CT9: =IF(BI9="Roundwood",$CS9/2,$CS9) -> 0 | CX9: =IFERROR($CW9/$CS9,"") | CZ9: =IFERROR($CW9/$CT9,"") | EP9: =IF(AND(AND(AND(OR($EC9=1,$EB9=1),OR($EH9=1,$EF9=1)),SUM($EA9:$EE9,$EK9)>=3),SUM($EF9:$EJ9)>=2),"Whole sector approach","") | EQ9: =IF(AND(AND(OR($EC9=1,$EB9=1),AND($EH9=0,$EF9=0)),SUM($EA9:$EE9,$EK9)>=3),"Ecosystem approach","") | ER9: =IF(AND(AND(AND($EC9=0,$EB9=0),OR($EH9=1,$EF9=1)),SUM($EG9:$EJ9)>=2),"Technology approach","") | ES9: =IF(AND($EC9+$EB9+$EE9+$EA9+$EF9+$EG9=0,$N9="included"),"C neutral forest and HWP assumption","") | ET9: =IF(AND(AND(AND($EC9+$EB9+$EA9+$EG9>=2,$EF9+$EH9+$EI9>=1),$ED9+$EE9>=1),$N9="included"),"All C pools assumption","") | EU9: =IF(AND($ED9+$EE9+$EI9+$EH9+$EF9=0,$N9="included"),"In-situ only assumption","") | EV9: C neutral | EY9: =IF(ISNUMBER(BW9),IF(ABS(BW9-[1]QC_indicators!$B$2)>3*[1]QC_indicators!$C$2,"C ratio",IF(ISNUMBER(CA9),IF(ABS(CA9-[1]QC_indicators!$B$1)>3*[1]QC_indicators!$C$1,"DF","no"))),IF(ISNUMBER(CA9),IF(ABS(CA9-[1]QC_indicators!$B$1)>3*[1]QC_indicators!$C$1,"DF","no"))) -> FALSE | FA9: =IF(LEN($CY9)=0,"",IF(AND($CY9<(-0.05),$ES9="C neutral forest and HWP assumption"),"Cneutral paradox",IF(AND($CY9>0.05,$EU9="In-situ only assumption"),"In-situ only paradox","")))
A10: REVISTA BRASILEIRA DE ZOOTECNIA-BRAZILIAN JOURNAL OF ANIMAL SCIENCE | B10: biological N-2 fixation; ecosystem services; grassland; nutrient cycling; tropical | C10: LEUCAENA-LEUCOCEPHALA; GLIRICIDIA-SEPIUM; ECOSYSTEM SERVICES; CONDENSED TANNINS; TROPICAL TREE; NUTRITION SECURITY; BIOMASS PRODUCTION; NITROGEN-FIXATION; FODDER TREES; N-2 FIXATION | D10: Dubeux, JCB; Muir, JP; Apolinario, VXD; Nair, PKR; Lira, MD; Sollenberger, LE | E10: Tree legumes: an underexploited resource in warm-climate silvopastures | F10: Tree legumes are an underexploited resource in warm-climate silvopastures. Perceived benefits of tree legumes include provisioning (browse/mast, timber, fuel, human food, natural medicines, and ornamentals), regulating (C sequestration, greenhouse gas mitigation, soil erosion control and riparian buffers, shade, windbreaks, and habitat for pollinators), supporting (biological N-2-fixation, nutrient cycling, soil fertility and soil health, photosynthesis, and primary productivity), and cultural ecosystem services. Tree legumes, however, have not been assessed to the same extent as herbaceous legumes. Once tree legumes are established, they are often more persistent than most herbaceous legumes. There are limitations for extended research with tree legume silvopastures, but extensive research has been done in Africa and Australia and recent efforts have been reported in South America. Economic benefits must be demonstrated to land managers to increase adoption. These benefits are apparent in the research and successes already available, but more long-term research, including the livestock component is necessary. Other factors that reduce adoption include paucity of domesticated germplasm, lag in research/technology, challenges of multipurpose trees and management complexity, challenges to mechanization, dangers of invasive weeds, and social and cultural barriers. In the current scenario of climate change and the need to increase food security, tree legumes are a key component for the sustainable intensification of livestock systems in warm-climate regions. | G10: Rev. Bras. Zootecn. | H10: Review | I10: 2017 | J10: 18 | K10: 10.1590/S1806-92902017000800010 | M10: =LEFT($D10,FIND(",",$D10)-1)&"_"&I10&L10 -> Dubeux_2017 | N10: review | O10: KN | Q10: v5 | CA10: =IFERROR(BZ10/BQ10,"") | CT10: =IF(BI10="Roundwood",$CS10/2,$CS10) -> 0 | CX10: =IFERROR($CW10/$CS10,"") | CZ10: =IFERROR($CW10/$CT10,"") | EP10: =IF(AND(AND(AND(OR($EC10=1,$EB10=1),OR($EH10=1,$EF10=1)),SUM($EA10:$EE10,$EK10)>=3),SUM($EF10:$EJ10)>=2),"Whole sector approach","") | EQ10: =IF(AND(AND(OR($EC10=1,$EB10=1),AND($EH10=0,$EF10=0)),SUM($EA10:$EE10,$EK10)>=3),"Ecosystem approach","") | ER10: =IF(AND(AND(AND($EC10=0,$EB10=0),OR($EH10=1,$EF10=1)),SUM($EG10:$EJ10)>=2),"Technology approach","") | ES10: =IF(AND($EC10+$EB10+$EE10+$EA10+$EF10+$EG10=0,$N10="included"),"C neutral forest and HWP assumption","") | ET10: =IF(AND(AND(AND($EC10+$EB10+$EA10+$EG10>=2,$EF10+$EH10+$EI10>=1),$ED10+$EE10>=1),$N10="included"),"All C pools assumption","") | EU10: =IF(AND($ED10+$EE10+$EI10+$EH10+$EF10=0,$N10="included"),"In-situ only assumption","") | EX10: okVB | EY10: =IF(ISNUMBER(BW10),IF(ABS(BW10-[1]QC_indicators!$B$2)>3*[1]QC_indicators!$C$2,"C ratio",IF(ISNUMBER(CA10),IF(ABS(CA10-[1]QC_indicators!$B$1)>3*[1]QC_indicators!$C$1,"DF","no"))),IF(ISNUMBER(CA10),IF(ABS(CA10-[1]QC_indicators!$B$1)>3*[1]QC_indicators!$C$1,"DF","no"))) -> FALSE | FA10: =IF(LEN($CY10)=0,"",IF(AND($CY10<(-0.05),$ES10="C neutral forest and HWP assumption"),"Cneutral paradox",IF(AND($CY10>0.05,$EU10="In-situ only assumption"),"In-situ only paradox","")))
A11: INTERNATIONAL JOURNAL OF LIFE CYCLE ASSESSMENT | B11: Ghanaian timber sector; Environmental performance indicators; Functional units; Life cycle impact assessment (LCIA); Tropical wood | C11: LAND-USE IMPACT; ENVIRONMENTAL-IMPACT; WOOD WASTES; INVENTORY; BIODIVERSITY; METHODOLOGY; PRODUCTS | D11: Eshun, JF; Potting, J; Leemans, R | E11: LCA of the timber sector in Ghana: preliminary life cycle impact assessment (LCIA) | F11: Purpose Most life cycle impact assessment (LCIA) approaches in life cycle assessment (LCA) are developed for western countries. Their LCIA approaches and characterization methodologies for different impact categories may not be necessarily relevant to African environmental conditions and particularly not for the timber sector in Ghana. This study reviews the relevance of existing impact categories and LCIA approaches, and uses the most relevant for the timber sector of Ghana. Materials and methods The study reviewed 23 life cycle inventories (LCIs) and LCAs on forestry, timber, and wood products for relevant impact categories and LCIA approaches for their relevance to the specific conditions in Ghana. This study uses an earlier LCI study of the timber industry as a starting point for an additional LCIA. We next performed a correlation and regression analysis to learn whether wood wastes may function as a reasonable single indicator for land use as proxy for biodiversity loss and the other impact categories. Results and discussion The literature review shows that no LCI or LCA studies were developed for Africa or the tropics. The LCIA approaches in the reviewed LCAs are indeed shown to take their basis in the environmental problems in western countries and characterization methodologies relating to how these problems manifest themselves in the western world. Characterization methodologies for different impact categories in CML-2000 and other LCIA approaches may not be necessarily relevant to African tropical environmental conditions and particularly not for the timber sector in Ghana. This situation hampers the reliability of our LCIA and points to a serious research gap in LCIA development in general. We applied the scientifically well-recognized CML 2000 to the earlier LCI results and characterized the preliminary selected impact categories of global warming, acidification, eutrophication, photochemical oxidant formation, and human toxicity. The correlation analysis indicated that wood waste is indeed strongly correlated with land use as proxy for biodiversity loss and also positively correlated with the other five potential impact results. It can be concluded that wood waste production is a major driving force for biodiversity loss and a sufficiently good single indicator for all other environmental performance indicators in the timber sector of Ghana. Conclusions This study and the previous LCI paper are pioneering a field not yet explored, since the correct environmental performance indicators are not yet developed or adapted to tropical conditions. The development of LCIA approaches in the tropics may be the start of a never-ending journey in LCA research in Africa, particularly Ghana. | G11: Int. J. Life Cycle Assess. | H11: Article | I11: 2011 | J11: 15 | K11: 10.1007/s11367-011-0307-5 | M11: =LEFT($D11,FIND(",",$D11)-1)&"_"&I11&L11 -> Eshun_2011 | N11: review | O11: SC | P11: AV | Q11: v6 | CA11: =IFERROR(BZ11/BQ11,"") | CT11: =IF(BI11="Roundwood",$CS11/2,$CS11) -> 0 | CX11: =IFERROR($CW11/$CS11,"") | CZ11: =IFERROR($CW11/$CT11,"") | EP11: =IF(AND(AND(AND(OR($EC11=1,$EB11=1),OR($EH11=1,$EF11=1)),SUM($EA11:$EE11,$EK11)>=3),SUM($EF11:$EJ11)>=2),"Whole sector approach","") | EQ11: =IF(AND(AND(OR($EC11=1,$EB11=1),AND($EH11=0,$EF11=0)),SUM($EA11:$EE11,$EK11)>=3),"Ecosystem approach","") | ER11: =IF(AND(AND(AND($EC11=0,$EB11=0),OR($EH11=1,$EF11=1)),SUM($EG11:$EJ11)>=2),"Technology approach","") | ES11: =IF(AND($EC11+$EB11+$EE11+$EA11+$EF11+$EG11=0,$N11="included"),"C neutral forest and HWP assumption","") | ET11: =IF(AND(AND(AND($EC11+$EB11+$EA11+$EG11>=2,$EF11+$EH11+$EI11>=1),$ED11+$EE11>=1),$N11="included"),"All C pools assumption","") | EU11: =IF(AND($ED11+$EE11+$EI11+$EH11+$EF11=0,$N11="included"),"In-situ only assumption","") | EW11: not a review per se but duplicates results from Eshun 2010 | EY11: =IF(ISNUMBER(BW11),IF(ABS(BW11-[1]QC_indicators!$B$2)>3*[1]QC_indicators!$C$2,"C ratio",IF(ISNUMBER(CA11),IF(ABS(CA11-[1]QC_indicators!$B$1)>3*[1]QC_indicators!$C$1,"DF","no"))),IF(ISNUMBER(CA11),IF(ABS(CA11-[1]QC_indicators!$B$1)>3*[1]QC_indicators!$C$1,"DF","no"))) -> FALSE | FA11: =IF(LEN($CY11)=0,"",IF(AND($CY11<(-0.05),$ES11="C neutral forest and HWP assumption"),"Cneutral paradox",IF(AND($CY11>0.05,$EU11="In-situ only assumption"),"In-situ only paradox","")))
A12: FOREST POLICY AND ECONOMICS | B12: Climate change; Harvested wood products; Carbon stocks and emissions; Wood substitute | C12: FOREST BIOENERGY; LIFE-CYCLE; ENERGY USE; EMISSIONS; SEQUESTRATION; CONSTRUCTION; MANAGEMENT; IMPACTS; CLIMATE; BUDGET | D12: Geng, AX; Yang, HQ; Chen, JX; Hong, YX | E12: Review of carbon storage function of harvested wood products and the potential of wood substitution in greenhouse gas mitigation | F12: Global forests have the potential to significantly increase or reduce atmospheric greenhouse gas (GHG) concentration. Harvested wood products (HWP) are an important part of the forest-atmosphere carbon cycle. On the one hand, HWP can retain the carbon for various periods of time, depending on the end uses. On the other hand, using HWP in place of more GHG-intensive materials and using wood bioenergy to substitute for fossil fuels result in reduced fossil fuel emissions. However, critical methodological differences exist in existing literature in assessing the GHG effects of HWP and wood bioenergy substitution, and large diversity in system boundary, substitution scenario, study period, and reference baseline results in large difference in reported GHG effects of wood substitution. In the present study, we conducted a comprehensive literature review to (a) clarify the methodological issues in GHG effects assessments of HWP and wood bioenergy substitution, (b) summarize and compare the reported GHG effects, and (c) identify knowledge gaps to inform future research. We support the conclusion that to accurately assess the GHG effects, HWP and wood bioenergy life-cycle carbon analysis needs to be integrated with forest carbon balance analysis. Substituting HWP for non-wood materials appears to be more effective in reducing GHG emissions than substituting wood for fossil fuels. The time required to obtain net emission reduction for wood bioenergy in place of fossil fuels can be 0 years, decades or more than a century, depending on forest biomass sources (e.g., harvest residue, standing live trees) and fossil fuels displaced. For HWP used to replace non-wood material, however, the time required to obtain net emission reduction largely remains a future research need. Overall, HWP and wood bioenergy originated from sustainably managed forests can significantly contribute to GHG emissions reduction in the long term. | G12: Forest Policy Econ. | H12: Article | I12: 2017 | J12: 50 | K12: 10.1016/j.forpol.2017.08.007 | M12: =LEFT($D12,FIND(",",$D12)-1)&"_"&I12&L12 -> Geng_2017 | N12: review | O12: SL | Q12: v5 | CA12: =IFERROR(BZ12/BQ12,"") | CT12: =IF(BI12="Roundwood",$CS12/2,$CS12) -> 0 | CX12: =IFERROR($CW12/$CS12,"") | CZ12: =IFERROR($CW12/$CT12,"") | EP12: =IF(AND(AND(AND(OR($EC12=1,$EB12=1),OR($EH12=1,$EF12=1)),SUM($EA12:$EE12,$EK12)>=3),SUM($EF12:$EJ12)>=2),"Whole sector approach","") | EQ12: =IF(AND(AND(OR($EC12=1,$EB12=1),AND($EH12=0,$EF12=0)),SUM($EA12:$EE12,$EK12)>=3),"Ecosystem approach","") | ER12: =IF(AND(AND(AND($EC12=0,$EB12=0),OR($EH12=1,$EF12=1)),SUM($EG12:$EJ12)>=2),"Technology approach","") | ES12: =IF(AND($EC12+$EB12+$EE12+$EA12+$EF12+$EG12=0,$N12="included"),"C neutral forest and HWP assumption","") | ET12: =IF(AND(AND(AND($EC12+$EB12+$EA12+$EG12>=2,$EF12+$EH12+$EI12>=1),$ED12+$EE12>=1),$N12="included"),"All C pools assumption","") | EU12: =IF(AND($ED12+$EE12+$EI12+$EH12+$EF12=0,$N12="included"),"In-situ only assumption","") | EX12: disagree: it is an original LCA paper. It combines existing LCAs on raw materials to compare a baseline with a "high HWP" scenario | EY12: =IF(ISNUMBER(BW12),IF(ABS(BW12-[1]QC_indicators!$B$2)>3*[1]QC_indicators!$C$2,"C ratio",IF(ISNUMBER(CA12),IF(ABS(CA12-[1]QC_indicators!$B$1)>3*[1]QC_indicators!$C$1,"DF","no"))),IF(ISNUMBER(CA12),IF(ABS(CA12-[1]QC_indicators!$B$1)>3*[1]QC_indicators!$C$1,"DF","no"))) -> FALSE | FA12: =IF(LEN($CY12)=0,"",IF(AND($CY12<(-0.05),$ES12="C neutral forest and HWP assumption"),"Cneutral paradox",IF(AND($CY12>0.05,$EU12="In-situ only assumption"),"In-situ only paradox","")))
A13: FOREST POLICY AND ECONOMICS | B13: Climate change; Harvested wood products; Carbon stocks and emissions; Wood substitute | C13: FOREST BIOENERGY; LIFE-CYCLE; ENERGY USE; EMISSIONS; SEQUESTRATION; CONSTRUCTION; MANAGEMENT; IMPACTS; CLIMATE; BUDGET | D13: Geng, AX; Yang, HQ; Chen, JX; Hong, YX | E13: Review of carbon storage function of harvested wood products and the potential of wood substitution in greenhouse gas mitigation | F13: Global forests have the potential to significantly increase or reduce atmospheric greenhouse gas (GHG) concentration. Harvested wood products (HWP) are an important part of the forest-atmosphere carbon cycle. On the one hand, HWP can retain the carbon for various periods of time, depending on the end uses. On the other hand, using HWP in place of more GHG-intensive materials and using wood bioenergy to substitute for fossil fuels result in reduced fossil fuel emissions. However, critical methodological differences exist in existing literature in assessing the GHG effects of HWP and wood bioenergy substitution, and large diversity in system boundary, substitution scenario, study period, and reference baseline results in large difference in reported GHG effects of wood substitution. In the present study, we conducted a comprehensive literature review to (a) clarify the methodological issues in GHG effects assessments of HWP and wood bioenergy substitution, (b) summarize and compare the reported GHG effects, and (c) identify knowledge gaps to inform future research. We support the conclusion that to accurately assess the GHG effects, HWP and wood bioenergy life-cycle carbon analysis needs to be integrated with forest carbon balance analysis. Substituting HWP for non-wood materials appears to be more effective in reducing GHG emissions than substituting wood for fossil fuels. The time required to obtain net emission reduction for wood bioenergy in place of fossil fuels can be 0 years, decades or more than a century, depending on forest biomass sources (e.g., harvest residue, standing live trees) and fossil fuels displaced. For HWP used to replace non-wood material, however, the time required to obtain net emission reduction largely remains a future research need. Overall, HWP and wood bioenergy originated from sustainably managed forests can significantly contribute to GHG emissions reduction in the long term. | G13: Forest Policy Econ. | H13: Article | I13: 2017 | J13: 50 | K13: 10.1016/j.forpol.2017.08.007 | M13: =LEFT($D13,FIND(",",$D13)-1)&"_"&I13&L13 -> Geng_2017 | N13: review | O13: SL | P13: AV | Q13: v6 | CA13: =IFERROR(BZ13/BQ13,"") | CT13: =IF(BI13="Roundwood",$CS13/2,$CS13) -> 0 | CX13: =IFERROR($CW13/$CS13,"") | CZ13: =IFERROR($CW13/$CT13,"") | EP13: =IF(AND(AND(AND(OR($EC13=1,$EB13=1),OR($EH13=1,$EF13=1)),SUM($EA13:$EE13,$EK13)>=3),SUM($EF13:$EJ13)>=2),"Whole sector approach","") | EQ13: =IF(AND(AND(OR($EC13=1,$EB13=1),AND($EH13=0,$EF13=0)),SUM($EA13:$EE13,$EK13)>=3),"Ecosystem approach","") | ER13: =IF(AND(AND(AND($EC13=0,$EB13=0),OR($EH13=1,$EF13=1)),SUM($EG13:$EJ13)>=2),"Technology approach","") | ES13: =IF(AND($EC13+$EB13+$EE13+$EA13+$EF13+$EG13=0,$N13="included"),"C neutral forest and HWP assumption","") | ET13: =IF(AND(AND(AND($EC13+$EB13+$EA13+$EG13>=2,$EF13+$EH13+$EI13>=1),$ED13+$EE13>=1),$N13="included"),"All C pools assumption","") | EU13: =IF(AND($ED13+$EE13+$EI13+$EH13+$EF13=0,$N13="included"),"In-situ only assumption","") | EY13: =IF(ISNUMBER(BW13),IF(ABS(BW13-[1]QC_indicators!$B$2)>3*[1]QC_indicators!$C$2,"C ratio",IF(ISNUMBER(CA13),IF(ABS(CA13-[1]QC_indicators!$B$1)>3*[1]QC_indicators!$C$1,"DF","no"))),IF(ISNUMBER(CA13),IF(ABS(CA13-[1]QC_indicators!$B$1)>3*[1]QC_indicators!$C$1,"DF","no"))) -> FALSE | FA13: =IF(LEN($CY13)=0,"",IF(AND($CY13<(-0.05),$ES13="C neutral forest and HWP assumption"),"Cneutral paradox",IF(AND($CY13>0.05,$EU13="In-situ only assumption"),"In-situ only paradox","")))
A14: SUSTAINABILITY | B14: cross-laminated timber; life-cycle assessment; mass timber building; whole-building LCA methodology | D14: Gu, HM; Liang, SB; Pierobon, F; Puettmann, M; Ganguly, I; Chen, CY; Pasternack, R; Wishnie, M; Jones, S; Maples, I | E14: Mass Timber Building Life Cycle Assessment Methodology for the US Regional Case Studies | F14: The building industry currently consumes over a third of energy produced and emits 39% of greenhouse gases globally produced by human activities. The manufacturing of building materials and the construction of buildings make up 11% of those emissions within the sector. Whole-building life-cycle assessment is a holistic and scientific tool to assess multiple environmental impacts with internationally accepted inventory databases. A comparison of the building life-cycle assessment results would help to select materials and designs to reduce total environmental impacts at the early planning stage for architects and developers, and to revise the building code to improve environmental performance. The Nature Conservancy convened a group of researchers and policymakers from governments and non-profit organizations with expertise across wood product life-cycle assessment, forest carbon, and forest products market analysis to address emissions and energy consumption associated with mass timber building solutions. The study disclosed a series of detailed, comparative life-cycle assessments of pairs of buildings using both mass timber and conventional materials. The methodologies used in this study are clearly laid out in this paper for transparency and accountability. A plethora of data exists on the favorable environmental performance of wood as a building material and energy source, and many opportunities appear for research to improve on current practices. | G14: Sustainability | H14: Article | I14: 2021 | J14: 0 | K14: 10.3390/su132414034 | M14: =LEFT($D14,FIND(",",$D14)-1)&"_"&I14&L14 -> Gu_2021 | N14: review | O14: TH | Q14: v5 | CA14: =IFERROR(BZ14/BQ14,"") | CT14: =IF(BI14="Roundwood",$CS14/2,$CS14) -> 0 | CX14: =IFERROR($CW14/$CS14,"") | CZ14: =IFERROR($CW14/$CT14,"") | EP14: =IF(AND(AND(AND(OR($EC14=1,$EB14=1),OR($EH14=1,$EF14=1)),SUM($EA14:$EE14,$EK14)>=3),SUM($EF14:$EJ14)>=2),"Whole sector approach","") | EQ14: =IF(AND(AND(OR($EC14=1,$EB14=1),AND($EH14=0,$EF14=0)),SUM($EA14:$EE14,$EK14)>=3),"Ecosystem approach","") | ER14: =IF(AND(AND(AND($EC14=0,$EB14=0),OR($EH14=1,$EF14=1)),SUM($EG14:$EJ14)>=2),"Technology approach","") | ES14: =IF(AND($EC14+$EB14+$EE14+$EA14+$EF14+$EG14=0,$N14="included"),"C neutral forest and HWP assumption","") | ET14: =IF(AND(AND(AND($EC14+$EB14+$EA14+$EG14>=2,$EF14+$EH14+$EI14>=1),$ED14+$EE14>=1),$N14="included"),"All C pools assumption","") | EU14: =IF(AND($ED14+$EE14+$EI14+$EH14+$EF14=0,$N14="included"),"In-situ only assumption","") | EX14: okVB | EY14: =IF(ISNUMBER(BW14),IF(ABS(BW14-[1]QC_indicators!$B$2)>3*[1]QC_indicators!$C$2,"C ratio",IF(ISNUMBER(CA14),IF(ABS(CA14-[1]QC_indicators!$B$1)>3*[1]QC_indicators!$C$1,"DF","no"))),IF(ISNUMBER(CA14),IF(ABS(CA14-[1]QC_indicators!$B$1)>3*[1]QC_indicators!$C$1,"DF","no"))) -> FALSE | FA14: =IF(LEN($CY14)=0,"",IF(AND($CY14<(-0.05),$ES14="C neutral forest and HWP assumption"),"Cneutral paradox",IF(AND($CY14>0.05,$EU14="In-situ only assumption"),"In-situ only paradox","")))
A15: SUSTAINABILITY | B15: structural and engineered timber; life cycle assessment; harvested wood products; carbon storage; built environment; climate change mitigation | C15: LIFE-CYCLE ASSESSMENT; CLIMATE-CHANGE; CARBON MITIGATION; BUILT ENVIRONMENT; EMBODIED CARBON; BIOGENIC CARBON; COMPARATIVE LCA; WOOD PRODUCTS; LAND-USE; IMPACT | D15: Hart, J; Pomponi, F | E15: More Timber in Construction: Unanswered Questions and Future Challenges | F15: The built environment is one of the greatest contributors to carbon emissions, climate change, and to the unsustainable pressure on the natural environment and its ecosystems. The use of more timber in construction is one possible response, and an authoritative contribution to this growing movement comes from the UK's Committee on Climate Change, which identifies a substantial increase in the use of wood in the construction of buildings as a top priority. However, a global encouragement of such a strategy raises some difficult questions. Given the urgency of effective solutions for low-carbon built environments, and the likely continued growth in demand for timber in construction, this article reviews its sustainability and identifies future challenges and unanswered questions. Existing evidence points indeed towards timber as the lower carbon option when modelled through life cycle assessment without having to draw on arguments around carbon storage. Issues however remain on the timing of carbon emissions, land allocation, and the environmental loads and benefits associated with the end-of-life options: analysis of environmental product declarations for engineered timber suggests that landfill might either be the best or the worst option from a climate change perspective, depending on assumptions. | G15: Sustainability | H15: Article | I15: 2020 | J15: 11 | K15: 10.3390/su12083473 | M15: =LEFT($D15,FIND(",",$D15)-1)&"_"&I15&L15 -> Hart_2020 | N15: review | O15: TH | Q15: v5 | CA15: =IFERROR(BZ15/BQ15,"") | CT15: =IF(BI15="Roundwood",$CS15/2,$CS15) -> 0 | CX15: =IFERROR($CW15/$CS15,"") | CZ15: =IFERROR($CW15/$CT15,"") | EP15: =IF(AND(AND(AND(OR($EC15=1,$EB15=1),OR($EH15=1,$EF15=1)),SUM($EA15:$EE15,$EK15)>=3),SUM($EF15:$EJ15)>=2),"Whole sector approach","") | EQ15: =IF(AND(AND(OR($EC15=1,$EB15=1),AND($EH15=0,$EF15=0)),SUM($EA15:$EE15,$EK15)>=3),"Ecosystem approach","") | ER15: =IF(AND(AND(AND($EC15=0,$EB15=0),OR($EH15=1,$EF15=1)),SUM($EG15:$EJ15)>=2),"Technology approach","") | ES15: =IF(AND($EC15+$EB15+$EE15+$EA15+$EF15+$EG15=0,$N15="included"),"C neutral forest and HWP assumption","") | ET15: =IF(AND(AND(AND($EC15+$EB15+$EA15+$EG15>=2,$EF15+$EH15+$EI15>=1),$ED15+$EE15>=1),$N15="included"),"All C pools assumption","") | EU15: =IF(AND($ED15+$EE15+$EI15+$EH15+$EF15=0,$N15="included"),"In-situ only assumption","") | EX15: okVB | EY15: =IF(ISNUMBER(BW15),IF(ABS(BW15-[1]QC_indicators!$B$2)>3*[1]QC_indicators!$C$2,"C ratio",IF(ISNUMBER(CA15),IF(ABS(CA15-[1]QC_indicators!$B$1)>3*[1]QC_indicators!$C$1,"DF","no"))),IF(ISNUMBER(CA15),IF(ABS(CA15-[1]QC_indicators!$B$1)>3*[1]QC_indicators!$C$1,"DF","no"))) -> FALSE | FA15: =IF(LEN($CY15)=0,"",IF(AND($CY15<(-0.05),$ES15="C neutral forest and HWP assumption"),"Cneutral paradox",IF(AND($CY15>0.05,$EU15="In-situ only assumption"),"In-situ only paradox","")))
A16: LAND | B16: wood-based products; circular bioeconomy; market development; climate change impacts; environmental sustainability | C16: LIFE-CYCLE ASSESSMENT; KRAFT PULP-MILL; CRUDE TALL OIL; GREENHOUSE-GAS; GLOBAL PAPER; MARKET; BIODIVERSITY; CHEMICALS; INDUSTRY; IMPACTS | D16: Hassegawa, M; Van Brusselen, J; Cramm, M; Verkerk, PJ | E16: Wood-Based Products in the Circular Bioeconomy: Status and Opportunities towards Environmental Sustainability | F16: The circular bioeconomy offers solutions to curb the effects of climate change by focusing on the use of renewable, biological resources to produce food, energy, materials, and services. The substitution of fossil products by wood-based products can help avoid or reduce greenhouse gas emissions over the life cycle of products. However, it is important to understand the potential impacts of large-scale material substitution at the market level. This study aimed to assess the role of selected wood-based products in the circular bioeconomy, the possible changes in their markets, and investigate which elements could ensure the environmental sustainability of these products. The demand for graphic paper has declined over the last 15 years, while the demand for packaging has increased. Cross-laminated timber and man-made cellulosic fibres have seen their global consumption increase over the last decade. While there are benefits associated with the substitution of non-renewable materials by wood-based products, there is still limited understanding of the substitution effects at market-, country- and global level. Some factors enabling the further uptake of wood-based products include initiatives that stimulate technological change, incentives to produce or consume less fossil-based and more bio-based alternatives, and the promotion and marketing of wood-based products as viable alternatives to non-renewable materials. | G16: Land | H16: Article | I16: 2022 | J16: 1 | K16: 10.3390/land11122131 | M16: =LEFT($D16,FIND(",",$D16)-1)&"_"&I16&L16 -> Hassegawa_2022 | N16: review | O16: AV | Q16: v6 | AZ16: =COUNTIF(X16:AY16,"<>0") -> 28 | BA16: =COUNTIF(X16:AN16,"<>0") -> 17 | CA16: =IFERROR(BZ16/BQ16,"") | CT16: =IF(BI16="Roundwood",$CS16/2,$CS16) -> 0 | CX16: =IFERROR($CW16/$CS16,"") | CZ16: =IFERROR($CW16/$CT16,"") | EP16: =IF(AND(AND(AND(OR($EC16=1,$EB16=1),OR($EH16=1,$EF16=1)),SUM($EA16:$EE16,$EK16)>=3),SUM($EF16:$EJ16)>=2),"Whole sector approach","") | EQ16: =IF(AND(AND(OR($EC16=1,$EB16=1),AND($EH16=0,$EF16=0)),SUM($EA16:$EE16,$EK16)>=3),"Ecosystem approach","") | ER16: =IF(AND(AND(AND($EC16=0,$EB16=0),OR($EH16=1,$EF16=1)),SUM($EG16:$EJ16)>=2),"Technology approach","") | ES16: =IF(AND($EC16+$EB16+$EE16+$EA16+$EF16+$EG16=0,$N16="included"),"C neutral forest and HWP assumption","") | ET16: =IF(AND(AND(AND($EC16+$EB16+$EA16+$EG16>=2,$EF16+$EH16+$EI16>=1),$ED16+$EE16>=1),$N16="included"),"All C pools assumption","") | EU16: =IF(AND($ED16+$EE16+$EI16+$EH16+$EF16=0,$N16="included"),"In-situ only assumption","") | EY16: =IF(ISNUMBER(BW16),IF(ABS(BW16-[1]QC_indicators!$B$2)>3*[1]QC_indicators!$C$2,"C ratio",IF(ISNUMBER(CA16),IF(ABS(CA16-[1]QC_indicators!$B$1)>3*[1]QC_indicators!$C$1,"DF","no"))),IF(ISNUMBER(CA16),IF(ABS(CA16-[1]QC_indicators!$B$1)>3*[1]QC_indicators!$C$1,"DF","no"))) -> FALSE | FA16: =IF(LEN($CY16)=0,"",IF(AND($CY16<(-0.05),$ES16="C neutral forest and HWP assumption"),"Cneutral paradox",IF(AND($CY16>0.05,$EU16="In-situ only assumption"),"In-situ only paradox","")))
A17: ENVIRONMENTAL RESEARCH LETTERS | B17: circular economy; climate change mitigation; life cycle assessment; industrial policy; resource efficiency; cement; iron and steel | C17: LIFE-CYCLE ASSESSMENT; COMPARING ENVIRONMENTAL IMPACTS; PRINTED-CIRCUIT BOARDS; MATERIAL FLOW-ANALYSIS; DEMOLITION WASTE; ENERGY DEMAND; STEEL REUSE; RESIDENTIAL BUILDINGS; BUILT ENVIRONMENT; EMBODIED ENERGY | D17: Hertwich, EG; Ali, S; Ciacci, L; Fishman, T; Heeren, N; Masanet, E; Asghari, FN; Olivetti, E; Pauliuk, S; Tu, QS; Wolfram, P | E17: Material efficiency strategies to reducing greenhouse gas emissions associated with buildings, vehicles, and electronics-a review | F17: As one quarter of global energy use serves the production of materials, the more efficient use of these materials presents a significant opportunity for the mitigation of greenhouse gas (GHG) emissions. With the renewed interest of policy makers in the circular economy, material efficiency (ME) strategies such as light-weighting and downsizing of and lifetime extension for products, reuse and recycling of materials, and appropriate material choice are being promoted. Yet, the emissions savings from ME remain poorly understood, owing in part to the multitude of material uses and diversity of circumstances and in part to a lack of analytical effort. We have reviewed emissions reductions from ME strategies applied to buildings, cars, and electronics. We find that there can be a systematic trade-off between material use in the production of buildings, vehicles, and appliances and energy use in their operation, requiring a careful life cycle assessment of ME strategies. We find that the largest potential emission reductions quantified in the literature result from more intensive use of and lifetime extension for buildings and the light-weighting and reduced size of vehicles. Replacing metals and concrete with timber in construction can result in significant GHG benefits, but trade-offs and limitations to the potential supply of timber need to be recognized. Repair and remanufacturing of products can also result in emission reductions, which have been quantified only on a case-by-case basis and are difficult to generalize. The recovery of steel, aluminum, and copper from building demolition waste and the end-of-life vehicles and appliances already results in the recycling of base metals, which achieves significant emission reductions. Higher collection rates, sorting efficiencies, and the alloy-specific sorting of metals to preserve the function of alloying elements while avoiding the contamination of base metals are important steps to further reduce emissions. | G17: Environ. Res. Lett. | H17: Review | I17: 2019 | J17: 79 | K17: 10.1088/1748-9326/ab0fe3 | M17: =LEFT($D17,FIND(",",$D17)-1)&"_"&I17&L17 -> Hertwich_2019 | N17: review | O17: SC | Q17: v5 | CA17: =IFERROR(BZ17/BQ17,"") | CT17: =IF(BI17="Roundwood",$CS17/2,$CS17) -> 0 | CX17: =IFERROR($CW17/$CS17,"") | CZ17: =IFERROR($CW17/$CT17,"") | EP17: =IF(AND(AND(AND(OR($EC17=1,$EB17=1),OR($EH17=1,$EF17=1)),SUM($EA17:$EE17,$EK17)>=3),SUM($EF17:$EJ17)>=2),"Whole sector approach","") | EQ17: =IF(AND(AND(OR($EC17=1,$EB17=1),AND($EH17=0,$EF17=0)),SUM($EA17:$EE17,$EK17)>=3),"Ecosystem approach","") | ER17: =IF(AND(AND(AND($EC17=0,$EB17=0),OR($EH17=1,$EF17=1)),SUM($EG17:$EJ17)>=2),"Technology approach","") | ES17: =IF(AND($EC17+$EB17+$EE17+$EA17+$EF17+$EG17=0,$N17="included"),"C neutral forest and HWP assumption","") | ET17: =IF(AND(AND(AND($EC17+$EB17+$EA17+$EG17>=2,$EF17+$EH17+$EI17>=1),$ED17+$EE17>=1),$N17="included"),"All C pools assumption","") | EU17: =IF(AND($ED17+$EE17+$EI17+$EH17+$EF17=0,$N17="included"),"In-situ only assumption","") | EX17: okVB | EY17: =IF(ISNUMBER(BW17),IF(ABS(BW17-[1]QC_indicators!$B$2)>3*[1]QC_indicators!$C$2,"C ratio",IF(ISNUMBER(CA17),IF(ABS(CA17-[1]QC_indicators!$B$1)>3*[1]QC_indicators!$C$1,"DF","no"))),IF(ISNUMBER(CA17),IF(ABS(CA17-[1]QC_indicators!$B$1)>3*[1]QC_indicators!$C$1,"DF","no"))) -> FALSE | FA17: =IF(LEN($CY17)=0,"",IF(AND($CY17<(-0.05),$ES17="C neutral forest and HWP assumption"),"Cneutral paradox",IF(AND($CY17>0.05,$EU17="In-situ only assumption"),"In-situ only paradox","")))
D18: Hurmekoski, E., Smyth, C., Stern, T., Verkerk, P. J., & Asada, R. | E18: Substitution impacts of wood use at the market level: a systematic review | G18: Environmental Research Letters | I18: 2021 | K18: 10.1088/1748-9326/ac386f | M18: =LEFT($D18,FIND(",",$D18)-1)&"_"&I18&L18 -> Hurmekoski_2021 | N18: review | O18: AV | Q18: v5 | CA18: =IFERROR(BZ18/BQ18,"") | CT18: =IF(BI18="Roundwood",$CS18/2,$CS18) -> 0 | CX18: =IFERROR($CW18/$CS18,"") | CZ18: =IFERROR($CW18/$CT18,"") | EP18: =IF(AND(AND(AND(OR($EC18=1,$EB18=1),OR($EH18=1,$EF18=1)),SUM($EA18:$EE18,$EK18)>=3),SUM($EF18:$EJ18)>=2),"Whole sector approach","") | EQ18: =IF(AND(AND(OR($EC18=1,$EB18=1),AND($EH18=0,$EF18=0)),SUM($EA18:$EE18,$EK18)>=3),"Ecosystem approach","") | ER18: =IF(AND(AND(AND($EC18=0,$EB18=0),OR($EH18=1,$EF18=1)),SUM($EG18:$EJ18)>=2),"Technology approach","") | ES18: =IF(AND($EC18+$EB18+$EE18+$EA18+$EF18+$EG18=0,$N18="included"),"C neutral forest and HWP assumption","") | ET18: =IF(AND(AND(AND($EC18+$EB18+$EA18+$EG18>=2,$EF18+$EH18+$EI18>=1),$ED18+$EE18>=1),$N18="included"),"All C pools assumption","") | EU18: =IF(AND($ED18+$EE18+$EI18+$EH18+$EF18=0,$N18="included"),"In-situ only assumption","") | EY18: =IF(ISNUMBER(BW18),IF(ABS(BW18-[1]QC_indicators!$B$2)>3*[1]QC_indicators!$C$2,"C ratio",IF(ISNUMBER(CA18),IF(ABS(CA18-[1]QC_indicators!$B$1)>3*[1]QC_indicators!$C$1,"DF","no"))),IF(ISNUMBER(CA18),IF(ABS(CA18-[1]QC_indicators!$B$1)>3*[1]QC_indicators!$C$1,"DF","no"))) -> FALSE | FA18: =IF(LEN($CY18)=0,"",IF(AND($CY18<(-0.05),$ES18="C neutral forest and HWP assumption"),"Cneutral paradox",IF(AND($CY18>0.05,$EU18="In-situ only assumption"),"In-situ only paradox","")))
A19: ENVIRONMENTAL REVIEWS | B19: boreal forest; Canada; carbon; climate change; mitigation | C19: LAND-USE CHANGE; GREENHOUSE-GAS-MITIGATION; GROWING POPLAR PLANTATIONS; MOUNTAIN PINE-BEETLE; LIFE-CYCLE ANALYSIS; OLD-GROWTH FORESTS; CARBON SEQUESTRATION; WOOD PRODUCTS; AGRICULTURAL LAND; BLACK SPRUCE | D19: Lempriere, TC; Kurz, WA; Hogg, EH; Schmoll, C; Rampley, GJ; Yemshanov, D; McKenney, DW; Gilsenan, R; Beatch, A; Blain, D; Bhatti, JS; Krcmar, E | E19: Canadian boreal forests and climate change mitigation | F19: Quantitative assessment of Canada&apos;s boreal forest mitigation potential is not yet possible, though the range of mitigation activities is known, requirements for sound analyses of options are increasingly understood, and there is emerging recognition that biogeophysical effects need greater attention. Use of a systems perspective highlights trade-offs between activities aimed at increasing carbon storage in the ecosystem, increasing carbon storage in harvested wood products (HWPs), or increasing the substitution benefits of using wood in place of fossil fuels or more emissions-intensive products. A systems perspective also suggests that erroneous conclusions about mitigation potential could result if analyses assume that HWP carbon is emitted at harvest, or bioenergy is carbon neutral. The greatest short-run boreal mitigation benefit generally would be achieved by avoiding greenhouse gas emissions; but over the longer run, there could be significant potential in activities that increase carbon removals. Mitigation activities could maximize landscape carbon uptake or maximize landscape carbon density, but not both simultaneously. The difference between the two is the rate at which HWPs are produced to meet society&apos;s demands, and mitigation activities could seek to delay or reduce HWP emissions and increase substitution benefits. Use of forest biomass for bioenergy could also contribute though the point in time at which this produces a net mitigation benefit relative to a fossil fuel alternative will be situation-specific. Key knowledge gaps exist in understanding boreal mitigation strategies that are robust to climate change and how mitigation could be integrated with adaptation to climate change. | G19: Environ. Rev. | H19: Review | I19: 2013 | J19: 89 | K19: 10.1139/er-2013-0039 | M19: =LEFT($D19,FIND(",",$D19)-1)&"_"&I19&L19 -> Lempriere_2013 | N19: review | O19: SL | Q19: v5 | CA19: =IFERROR(BZ19/BQ19,"") | CT19: =IF(BI19="Roundwood",$CS19/2,$CS19) -> 0 | CX19: =IFERROR($CW19/$CS19,"") | CZ19: =IFERROR($CW19/$CT19,"") | EP19: =IF(AND(AND(AND(OR($EC19=1,$EB19=1),OR($EH19=1,$EF19=1)),SUM($EA19:$EE19,$EK19)>=3),SUM($EF19:$EJ19)>=2),"Whole sector approach","") | EQ19: =IF(AND(AND(OR($EC19=1,$EB19=1),AND($EH19=0,$EF19=0)),SUM($EA19:$EE19,$EK19)>=3),"Ecosystem approach","") | ER19: =IF(AND(AND(AND($EC19=0,$EB19=0),OR($EH19=1,$EF19=1)),SUM($EG19:$EJ19)>=2),"Technology approach","") | ES19: =IF(AND($EC19+$EB19+$EE19+$EA19+$EF19+$EG19=0,$N19="included"),"C neutral forest and HWP assumption","") | ET19: =IF(AND(AND(AND($EC19+$EB19+$EA19+$EG19>=2,$EF19+$EH19+$EI19>=1),$ED19+$EE19>=1),$N19="included"),"All C pools assumption","") | EU19: =IF(AND($ED19+$EE19+$EI19+$EH19+$EF19=0,$N19="included"),"In-situ only assumption","") | EX19: okVB | EY19: =IF(ISNUMBER(BW19),IF(ABS(BW19-[1]QC_indicators!$B$2)>3*[1]QC_indicators!$C$2,"C ratio",IF(ISNUMBER(CA19),IF(ABS(CA19-[1]QC_indicators!$B$1)>3*[1]QC_indicators!$C$1,"DF","no"))),IF(ISNUMBER(CA19),IF(ABS(CA19-[1]QC_indicators!$B$1)>3*[1]QC_indicators!$C$1,"DF","no"))) -> FALSE | FA19: =IF(LEN($CY19)=0,"",IF(AND($CY19<(-0.05),$ES19="C neutral forest and HWP assumption"),"Cneutral paradox",IF(AND($CY19>0.05,$EU19="In-situ only assumption"),"In-situ only paradox","")))
A20: JOURNAL OF FORESTRY | B20: forest management; forest policy; forest carbon dynamics; carbon accounting; carbon offsets; life cycle assessment; building products substitution; bioenergy | C20: SOIL ORGANIC-MATTER; LIFE-CYCLE INVENTORY; MOUNTAIN PINE-BEETLE; UNITED-STATES; CLIMATE-CHANGE; BOREAL FOREST; ENVIRONMENTAL PERFORMANCE; PACIFIC-NORTHWEST; SOFTWOOD LUMBER; OFFSET PROJECTS | D20: Malmsheimer, RW; Bowyer, JL; Fried, JS; Gee, E; Izlar, RL; Miner, RA; Munn, IA; Oneil, E; Stewart, WC | E20: Managing Forests because Carbon Matters: Integrating Energy, Products, and Land Management Policy | F20: The United States needs many different types of forests: some managed for wood products plus other benefits, and some managed for nonconsumptive uses and benefits. The objective of reducing global greenhouse gases (GHG) requires increasing carbon storage in pools other than the atmosphere. Growing more forests and keeping forests as forests are only part of the solution, because focusing solely on the sequestration benefits of the forests misses the important (and substantial) carbon storage and substitution GHG benefits of harvested forest products, as well as other benefits of active forest management. Forests and global climate are closely linked in terms of carbon storage and releases, water fluxes from the soil and into the atmosphere, and solar energy capture. Understanding how carbon dynamics are affected by stand age, density, and management and will evolve with climate change is fundamental to exploiting the capacity for sustainably managed forests to remove carbon dioxide from the atmosphere. For example, even though emperate forests continue to be carbon sinks, in western North America forest fires and tree mortality from insects are converting some forests into net carbon sources. Expanding forest biomass use for biofuels and energy generation will compete with traditional forest products, but it may also produce benefits through competition and market efficiency. Short-rotation woody crops, as well as landowners&apos; preferences-based on investment-return expectations and environmental considerations, both of which will be affected by energy and environmental policies-have the potential to increase biomass supply. Unlike metals, concrete, and plastic, forest products store atmospheric carbon and have low embodied energy (the amount of energy it takes to make products), so there is a substitution effect when wood is used in place of other building materials. Wood used for energy production also provides substitution benefits by reducing the flow of fossil fuel based carbon emissions to the atmosphere. The value of carbon credits generated by forest carbon offset projects differs dramatically, depending on the sets of carbon pods allowed by the protocol and baseline employed. The costs associated with establishing and maintaining offset projects depend largely on the protocols&apos; specific.. Measurement challenges and relatively high transaction costs needed for forest carbon offsets warrant consideration of other policies that promote climate benefits from forests and forest products but do not require project-specific accounting. Policies can foster changes in forest management and product manufacture that reduce carbon emissions over time while maintaining forests for environmental and societal benefits. US policymakers should take to heart the finding of the Intergovernmental Panel on Climate Change in its Fourth Assessment Report when it concluded that In the long term, a sustainable forest management strategy aimed at maintaining or increasing forest carbon stocks, while producing on annual sustained yield of timber, fibre, or energy from the forest, will generate the largest sustained mitigation benefit. A rational energy and environmental policy framework must be based on the premise that atmospheric greenhouse gas levels are increasing primarily because of the addition of geologic fossil fuel-based carbon into the carbon cycle. Forest carbon policy that builds on the scientific information summarized in this article can be a significant and important part of a comprehensive energy policy that provides for energy independence and carbon benefits while simultaneously providing clean water, wildlife habitat, recreation, and other uses and values. | G20: J. For. | H20: Article | I20: 2011 | J20: 108 | K20: 10.1093/jof/109.s1.S7 | M20: =LEFT($D20,FIND(",",$D20)-1)&"_"&I20&L20 -> Malmsheimer_2011 | N20: review | O20: SL | Q20: v5 | CA20: =IFERROR(BZ20/BQ20,"") | CT20: =IF(BI20="Roundwood",$CS20/2,$CS20) -> 0 | CX20: =IFERROR($CW20/$CS20,"") | CZ20: =IFERROR($CW20/$CT20,"") | EP20: =IF(AND(AND(AND(OR($EC20=1,$EB20=1),OR($EH20=1,$EF20=1)),SUM($EA20:$EE20,$EK20)>=3),SUM($EF20:$EJ20)>=2),"Whole sector approach","") | EQ20: =IF(AND(AND(OR($EC20=1,$EB20=1),AND($EH20=0,$EF20=0)),SUM($EA20:$EE20,$EK20)>=3),"Ecosystem approach","") | ER20: =IF(AND(AND(AND($EC20=0,$EB20=0),OR($EH20=1,$EF20=1)),SUM($EG20:$EJ20)>=2),"Technology approach","") | ES20: =IF(AND($EC20+$EB20+$EE20+$EA20+$EF20+$EG20=0,$N20="included"),"C neutral forest and HWP assumption","") | ET20: =IF(AND(AND(AND($EC20+$EB20+$EA20+$EG20>=2,$EF20+$EH20+$EI20>=1),$ED20+$EE20>=1),$N20="included"),"All C pools assumption","") | EU20: =IF(AND($ED20+$EE20+$EI20+$EH20+$EF20=0,$N20="included"),"In-situ only assumption","") | EW20: More an overview than a review, but there are no original results | EX20: changed_to_review | EY20: =IF(ISNUMBER(BW20),IF(ABS(BW20-[1]QC_indicators!$B$2)>3*[1]QC_indicators!$C$2,"C ratio",IF(ISNUMBER(CA20),IF(ABS(CA20-[1]QC_indicators!$B$1)>3*[1]QC_indicators!$C$1,"DF","no"))),IF(ISNUMBER(CA20),IF(ABS(CA20-[1]QC_indicators!$B$1)>3*[1]QC_indicators!$C$1,"DF","no"))) -> FALSE | FA20: =IF(LEN($CY20)=0,"",IF(AND($CY20<(-0.05),$ES20="C neutral forest and HWP assumption"),"Cneutral paradox",IF(AND($CY20>0.05,$EU20="In-situ only assumption"),"In-situ only paradox","")))
A21: FOREST ECOSYSTEMS | C21: CLIMATE-CHANGE MITIGATION; LIFE-CYCLE ASSESSMENT; FOREST SECTOR; ALTERNATIVE MATERIALS; CARBON EMISSIONS; PRODUCTS; IMPACTS; MANAGEMENT; BIOENERGY; BENEFITS | D21: Myllyviita, T; Soimakallio, S; Judl, J; Seppala, J | E21: Wood substitution potential in greenhouse gas emission reduction-review on current state and application of displacement factors | F21: Background Replacing non-renewable materials and energy with wood offers a potential strategy to mitigate climate change if the net emissions of ecosystem and technosystem are reduced in a considered time period. Displacement factors (DFs) describe an emission reduction for a wood-based product or fuel which is used in place of a non-wood alternative. The aims of this review were to map and assess DFs from scientific literature and to provide findings on how to harmonise practices behind them and to support coherent application. Results Most of the reviewed DFs were positive, implying decreasing fossil GHG emissions in the technosystem. The vast majority of the reviewed DFs describe avoided fossil emissions either both in processing and use of wood or only in the latter when wood processing emissions were considered separately. Some of the reviewed DFs included emissions avoided in post-use of harvested wood products (HWPs). Changes in forest and product carbon stocks were not included in DFs except in a few single cases. However, in most of the reviewed studies they were considered separately in a consistent way along with DFs. DFs for wood energy, construction and material substitution were widely available, whereas DFs for packaging products, chemicals and textiles were scarce. More than half of DFs were calculated by the authors of the reviewed articles while the rest of them were adopted from other articles. Conclusions Most of the reviewed DFs describe the avoided fossil GHG emissions. These DFs may provide insights on the wood-based products with a potential to replace emissions intensive alternatives but they do not reveal the actual climate change mitigation effects of wood use. The way DFs should be applied and interpreted depends on what has been included in them. If the aim of DFs is to describe the overall climate effects of wood use, DFs should include all the relevant GHG flows, including changes in forest and HWP carbon stock and post-use of HWPs, however, based on this literature review this is not a common practice. DFs including only fossil emissions should be applied together with a coherent assessment of changes in forest and HWP carbon stocks, as was the case in most of the reviewed studies. To increase robustness and transparency and to decrease misuse, we recommend that system boundaries and other assumptions behind DFs should be clearly documented. | G21: For. Ecosyst. | H21: Review | I21: 2021 | J21: 3 | K21: 10.1186/s40663-021-00326-8 | M21: =LEFT($D21,FIND(",",$D21)-1)&"_"&I21&L21 -> Myllyviita_2021 | N21: review | O21: KN | P21: EC | Q21: v6 | CA21: =IFERROR(BZ21/BQ21,"") | CT21: =IF(BI21="Roundwood",$CS21/2,$CS21) -> 0 | CX21: =IFERROR($CW21/$CS21,"") | CZ21: =IFERROR($CW21/$CT21,"") | EP21: =IF(AND(AND(AND(OR($EC21=1,$EB21=1),OR($EH21=1,$EF21=1)),SUM($EA21:$EE21,$EK21)>=3),SUM($EF21:$EJ21)>=2),"Whole sector approach","") | EQ21: =IF(AND(AND(OR($EC21=1,$EB21=1),AND($EH21=0,$EF21=0)),SUM($EA21:$EE21,$EK21)>=3),"Ecosystem approach","") | ER21: =IF(AND(AND(AND($EC21=0,$EB21=0),OR($EH21=1,$EF21=1)),SUM($EG21:$EJ21)>=2),"Technology approach","") | ES21: =IF(AND($EC21+$EB21+$EE21+$EA21+$EF21+$EG21=0,$N21="included"),"C neutral forest and HWP assumption","") | ET21: =IF(AND(AND(AND($EC21+$EB21+$EA21+$EG21>=2,$EF21+$EH21+$EI21>=1),$ED21+$EE21>=1),$N21="included"),"All C pools assumption","") | EU21: =IF(AND($ED21+$EE21+$EI21+$EH21+$EF21=0,$N21="included"),"In-situ only assumption","") | EY21: =IF(ISNUMBER(BW21),IF(ABS(BW21-[1]QC_indicators!$B$2)>3*[1]QC_indicators!$C$2,"C ratio",IF(ISNUMBER(CA21),IF(ABS(CA21-[1]QC_indicators!$B$1)>3*[1]QC_indicators!$C$1,"DF","no"))),IF(ISNUMBER(CA21),IF(ABS(CA21-[1]QC_indicators!$B$1)>3*[1]QC_indicators!$C$1,"DF","no"))) -> FALSE | FA21: =IF(LEN($CY21)=0,"",IF(AND($CY21<(-0.05),$ES21="C neutral forest and HWP assumption"),"Cneutral paradox",IF(AND($CY21>0.05,$EU21="In-situ only assumption"),"In-situ only paradox","")))
D22: Niles, J. O., & Schwarze, R. | E22: The value of careful carbon accounting in wood products | G22: Climatic change | I22: 2001 | K22: 10.1023/A:1010655806130 | M22: =LEFT($D22,FIND(",",$D22)-1)&"_"&I22&L22 -> Niles_2001 | N22: review | O22: KN | P22: SC | Q22: v6 | AZ22: =COUNTIF(X22:AY22,"<>0") -> 28 | BA22: =COUNTIF(X22:AN22,"<>0") -> 17 | BO22: =IFERROR(BN22/BM22,"") | CA22: =IFERROR(BZ22/BQ22,"") | CT22: =IF(BI22="Roundwood",$CS22/2,$CS22) -> 0 | CX22: =IFERROR($CW22/$CS22,"") | CZ22: =IFERROR($CW22/$CT22,"") | DA22: =IFERROR((CV22-CU22)/ABS(CU22),"") | DN22: =SUM(DI22:DL22) -> 0 | DO22: =IF(DN22=1,INDEX($DI$7:$DL$7,MATCH(1,$DI22:$DL22,0)),"mixedProduct") -> mixedProduct | DP22: =IF(DI22=1,DP$7,0) -> 0 | DQ22: =IF(DJ22=1,DQ$7,0) -> 0 | DR22: =IF(DK22=1,DR$7,0) -> 0 | DS22: =IF(DL22=1,DS$7,0) -> 0 | DZ22: =IF(DT22=1,"self-calculated DF",IF(DU22=1,"external DF used","explicit C balance")) -> explicit C balance | EP22: =IF(AND(AND(AND(OR($EC22=1,$EB22=1),OR($EH22=1,$EF22=1)),SUM($EA22:$EE22,$EK22)>=3),SUM($EF22:$EJ22)>=2),"Whole sector approach","") | EQ22: =IF(AND(AND(OR($EC22=1,$EB22=1),AND($EH22=0,$EF22=0)),SUM($EA22:$EE22,$EK22)>=3),"Ecosystem approach","") | ER22: =IF(AND(AND(AND($EC22=0,$EB22=0),OR($EH22=1,$EF22=1)),SUM($EG22:$EJ22)>=2),"Technology approach","") | ES22: =IF(AND($EC22+$EB22+$EE22+$EA22+$EF22+$EG22=0,$N22="included"),"C neutral forest and HWP assumption","") | ET22: =IF(AND(AND(AND($EC22+$EB22+$EA22+$EG22>=2,$EF22+$EH22+$EI22>=1),$ED22+$EE22>=1),$N22="included"),"All C pools assumption","") | EU22: =IF(AND($ED22+$EE22+$EI22+$EH22+$EF22=0,$N22="included"),"In-situ only assumption","") | EY22: =IF(ISNUMBER(BW22),IF(ABS(BW22-[1]QC_indicators!$B$2)>3*[1]QC_indicators!$C$2,"C ratio",IF(ISNUMBER(CA22),IF(ABS(CA22-[1]QC_indicators!$B$1)>3*[1]QC_indicators!$C$1,"DF","no"))),IF(ISNUMBER(CA22),IF(ABS(CA22-[1]QC_indicators!$B$1)>3*[1]QC_indicators!$C$1,"DF","no"))) -> FALSE | FA22: =IF(LEN($CY22)=0,"",IF(AND($CY22<(-0.05),$ES22="C neutral forest and HWP assumption"),"Cneutral paradox",IF(AND($CY22>0.05,$EU22="In-situ only assumption"),"In-situ only paradox","")))
A23: WILEY INTERDISCIPLINARY REVIEWS-ENERGY AND ENVIRONMENT | B23: biodiversity; climate; soil; stump biomass; water | C23: COARSE WOODY DEBRIS; LOGGING RESIDUE EXTRACTION; SWEDISH FOREST SOILS; CONTROL ROOT-ROT; NORWAY SPRUCE; PICEA-ABIES; SCOTS PINE; ORGANIC-CARBON; METHYL-MERCURY; BOREAL FOREST | D23: Persson, T; Egnell, G | E23: Stump harvesting for bioenergy: A review of climatic and environmental impacts in northern Europe and America | F23: Stump harvesting is defined as an intensification of forest management in comparison with stem-only harvesting and removal of tops and branches. It increases soil mixing and the proportion of bare soil. In contrast to earlier hypotheses, stump harvesting was found to reduce emissions of carbon dioxide (CO2), nitrous oxide, and methane in the short term. In the long term, heterotrophic soil CO2 evolution is reduced. Both model and empirical studies indicate that stump removal can reduce the soil organic carbon (SOC) pool in the short term, but long-term experiments (32-39 years) could not verify any SOC decline. Life cycle assessment studies showed that stumps as fuel resulted in markedly lower emissions of CO2 into the atmosphere, viewed over a whole forest rotation compared to heating by natural gas and coal. Stump removal does not seem to affect timber production in the next forest rotation and often reduces the infection rate of root rot. It increases the natural regeneration of birch and pine, it can increase nitrate leaching at N-rich sites, and it can increase the number of water-filled cavities where methylmercury is formed. Stump extraction decreases the amount of dwarf shrubs in young clear-cuts, but after 1-2 decades, these species are generally recovered. Many species dependent on dead wood are adversely affected by intense stump harvest. Model studies suggest that the risk of species extinction is small when only 10% of the total clear-cut area in the forest landscape is stump harvested, but the risk of extinction rises at increasing extraction intensities. This article is categorized under: Bioenergy > Climate and Environment Energy and Climate > Climate and Environment Energy and Development > Climate and Environment | G23: Wiley Interdiscip. Rev. Energy Environ. | H23: Review | I23: 2018 | J23: 13 | K23: 10.1002/wene.307 | M23: =LEFT($D23,FIND(",",$D23)-1)&"_"&I23&L23 -> Persson_2018 | N23: review | O23: SC | P23: SL | Q23: v6 | CA23: =IFERROR(BZ23/BQ23,"") | CT23: =IF(BI23="Roundwood",$CS23/2,$CS23) -> 0 | CX23: =IFERROR($CW23/$CS23,"") | CZ23: =IFERROR($CW23/$CT23,"") | EP23: =IF(AND(AND(AND(OR($EC23=1,$EB23=1),OR($EH23=1,$EF23=1)),SUM($EA23:$EE23,$EK23)>=3),SUM($EF23:$EJ23)>=2),"Whole sector approach","") | EQ23: =IF(AND(AND(OR($EC23=1,$EB23=1),AND($EH23=0,$EF23=0)),SUM($EA23:$EE23,$EK23)>=3),"Ecosystem approach","") | ER23: =IF(AND(AND(AND($EC23=0,$EB23=0),OR($EH23=1,$EF23=1)),SUM($EG23:$EJ23)>=2),"Technology approach","") | ES23: =IF(AND($EC23+$EB23+$EE23+$EA23+$EF23+$EG23=0,$N23="included"),"C neutral forest and HWP assumption","") | ET23: =IF(AND(AND(AND($EC23+$EB23+$EA23+$EG23>=2,$EF23+$EH23+$EI23>=1),$ED23+$EE23>=1),$N23="included"),"All C pools assumption","") | EU23: =IF(AND($ED23+$EE23+$EI23+$EH23+$EF23=0,$N23="included"),"In-situ only assumption","") | EY23: =IF(ISNUMBER(BW23),IF(ABS(BW23-[1]QC_indicators!$B$2)>3*[1]QC_indicators!$C$2,"C ratio",IF(ISNUMBER(CA23),IF(ABS(CA23-[1]QC_indicators!$B$1)>3*[1]QC_indicators!$C$1,"DF","no"))),IF(ISNUMBER(CA23),IF(ABS(CA23-[1]QC_indicators!$B$1)>3*[1]QC_indicators!$C$1,"DF","no"))) -> FALSE | FA23: =IF(LEN($CY23)=0,"",IF(AND($CY23<(-0.05),$ES23="C neutral forest and HWP assumption"),"Cneutral paradox",IF(AND($CY23>0.05,$EU23="In-situ only assumption"),"In-situ only paradox","")))
A24: FOREST POLICY AND ECONOMICS | B24: life-cycle-assessment (LCA); substitution; cost-effectiveness; economics; wood; steel; concrete | C24: LIFE-CYCLE | D24: Petersen, AK; Solberg, B | E24: Environmental and economic impacts of substitution between wood products and alternative materials: a review of micro-level analyses from Norway and Sweden | F24: This article gives a state of the art overview on quantitative analyses from Norway and Sweden of Life cycle analyses (LCA), which compare the environmental impacts of substitution between wood and alternative materials, with emphasis on greenhouse gas (GHG) emissions, economics and methodological issues. In all studies referred to this overview, wood is a better alternative than other materials with regard to GHG emissions. Furthermore, wood is causing less emissions of SO2 and generates less waste compared to the alternative materials. Preservative treated wood, on the other hand, might have toxicological impacts on human health and ecosystems. Impacts on acidification, eutrofication and creation of photochemical ozone vary in different comparisons. Amount of greenhouse gases avoided due to substitution between wood and steel is in the range of 36-530 kg CO2-equivalents per in 3 input of timber with 4% discount rate; depending on waste management of the materials, and how carbon fixation on forest land is included. This amount is 93-1062 kg CO2-equivalents for substitution between wood and concrete, if the wood is not landfilled after use. Many of the LCAs could be considerably improved, if the analyses were done with several alternative assumptions regarding boundaries of the system used in the LCA. This is important, not least to map what are the main assumptions for the results obtained and to compare with other studies. It is also important to consider the time-profile of the GHG emissions and other impacts over the life-cycle-it is surprising that this is not taken more seriously. Wood as a building material is competitive on price in those studies that include costs. It is a weak point of many LCAs that costs as well as other economic aspects influencing product substitution are not included, and a major research challenge is to combine traditional LCA with economic analysis in order to make both more policy relevant. In particular, one should develop dynamic input/output models where price and income substitutions as well as technological changes and cost components are included endogenously. (c) 2003 Elsevier B.V. All rights reserved. | G24: Forest Policy Econ. | H24: Article | I24: 2005 | J24: 122 | K24: 10.1016/S1389-9341(03)00063-7 | M24: =LEFT($D24,FIND(",",$D24)-1)&"_"&I24&L24 -> Petersen_2005 | N24: review | O24: SC | P24: SL | Q24: v6 | CA24: =IFERROR(BZ24/BQ24,"") | CT24: =IF(BI24="Roundwood",$CS24/2,$CS24) -> 0 | CX24: =IFERROR($CW24/$CS24,"") | CZ24: =IFERROR($CW24/$CT24,"") | EP24: =IF(AND(AND(AND(OR($EC24=1,$EB24=1),OR($EH24=1,$EF24=1)),SUM($EA24:$EE24,$EK24)>=3),SUM($EF24:$EJ24)>=2),"Whole sector approach","") | EQ24: =IF(AND(AND(OR($EC24=1,$EB24=1),AND($EH24=0,$EF24=0)),SUM($EA24:$EE24,$EK24)>=3),"Ecosystem approach","") | ER24: =IF(AND(AND(AND($EC24=0,$EB24=0),OR($EH24=1,$EF24=1)),SUM($EG24:$EJ24)>=2),"Technology approach","") | ES24: =IF(AND($EC24+$EB24+$EE24+$EA24+$EF24+$EG24=0,$N24="included"),"C neutral forest and HWP assumption","") | ET24: =IF(AND(AND(AND($EC24+$EB24+$EA24+$EG24>=2,$EF24+$EH24+$EI24>=1),$ED24+$EE24>=1),$N24="included"),"All C pools assumption","") | EU24: =IF(AND($ED24+$EE24+$EI24+$EH24+$EF24=0,$N24="included"),"In-situ only assumption","") | EY24: =IF(ISNUMBER(BW24),IF(ABS(BW24-[1]QC_indicators!$B$2)>3*[1]QC_indicators!$C$2,"C ratio",IF(ISNUMBER(CA24),IF(ABS(CA24-[1]QC_indicators!$B$1)>3*[1]QC_indicators!$C$1,"DF","no"))),IF(ISNUMBER(CA24),IF(ABS(CA24-[1]QC_indicators!$B$1)>3*[1]QC_indicators!$C$1,"DF","no"))) -> FALSE | FA24: =IF(LEN($CY24)=0,"",IF(AND($CY24<(-0.05),$ES24="C neutral forest and HWP assumption"),"Cneutral paradox",IF(AND($CY24>0.05,$EU24="In-situ only assumption"),"In-situ only paradox","")))
A25: BUILDING AND ENVIRONMENT | B25: Buildings; Life cycle assessment; Embodied emissions; Dynamic; Biogenic; Carbonation | C25: LIFE-CYCLE ASSESSMENT; BIOGENIC CARBON; SENSITIVITY-ANALYSIS; IMPACT ASSESSMENT; LCA; FRAMEWORK; STORAGE; TIME | D25: Resch, E; Andresen, I; Cherubini, F; Brattebo, H | E25: Estimating dynamic climate change effects of material use in buildings-Timing, uncertainty, and emission sources | F25: Material use in buildings affects the climate over centuries, however, temporal aspects are often ignored in Life Cycle Assessment (LCA). Results too often promise uncontested precision of impacts occurring far into the future. Additionally, the validity of building LCAs is being questioned over inadequate scope and inventory. A dynamic LCA method for material use in buildings that addresses those concerns is presented, along with a case study of 20 buildings. In particular, a novel solution to account for delayed emissions is presented, along with future technological improvements. Climate change effects of material use in construction, operation, and end-of-life phases are estimated, from production, transport, construction-waste incineration, biogenic carbon sequestration, and cement carbonation. Building subpart metrics reveal drivers of impacts and are used for generating statistical emission profiles. Application on a bottom-up harmonized dataset produces statistical results for building types (typology, timber/concrete) and building subparts (building elements, material categories). Global warming policy targets requires that the building industry focuses on interventions with short-term effects, such as low-impact materials in the construction phase and reduced construction waste. Uncertainty is estimated, and parameter influence assessed with global sensitivity analysis. Time horizon (TH), building lifetime, and construction waste parameters are found most sensitive. The method reduces uncertainty of postulated future impacts; an important step in the direction of policy-relevant modeling. We recommend that building LCA modeling practice adopts the presented methodological concepts to gain trust and policy-relevance. | G25: Build. Environ. | H25: Article | I25: 2021 | J25: 10 | K25: 10.1016/j.buildenv.2020.107399 | M25: =LEFT($D25,FIND(",",$D25)-1)&"_"&I25&L25 -> Resch_2021 | N25: review | O25: TH | Q25: v5 | CA25: =IFERROR(BZ25/BQ25,"") | CT25: =IF(BI25="Roundwood",$CS25/2,$CS25) -> 0 | CX25: =IFERROR($CW25/$CS25,"") | CZ25: =IFERROR($CW25/$CT25,"") | EP25: =IF(AND(AND(AND(OR($EC25=1,$EB25=1),OR($EH25=1,$EF25=1)),SUM($EA25:$EE25,$EK25)>=3),SUM($EF25:$EJ25)>=2),"Whole sector approach","") | EQ25: =IF(AND(AND(OR($EC25=1,$EB25=1),AND($EH25=0,$EF25=0)),SUM($EA25:$EE25,$EK25)>=3),"Ecosystem approach","") | ER25: =IF(AND(AND(AND($EC25=0,$EB25=0),OR($EH25=1,$EF25=1)),SUM($EG25:$EJ25)>=2),"Technology approach","") | ES25: =IF(AND($EC25+$EB25+$EE25+$EA25+$EF25+$EG25=0,$N25="included"),"C neutral forest and HWP assumption","") | ET25: =IF(AND(AND(AND($EC25+$EB25+$EA25+$EG25>=2,$EF25+$EH25+$EI25>=1),$ED25+$EE25>=1),$N25="included"),"All C pools assumption","") | EU25: =IF(AND($ED25+$EE25+$EI25+$EH25+$EF25=0,$N25="included"),"In-situ only assumption","") | EW25: The review actually retreats LCA data from 20 buildings to incorporate in situ forest emissions/storage, finds that time horizon is key and proposes a distribution of C footprint depending on time horizon -> to be quoted! | EX25: okVB | EY25: =IF(ISNUMBER(BW25),IF(ABS(BW25-[1]QC_indicators!$B$2)>3*[1]QC_indicators!$C$2,"C ratio",IF(ISNUMBER(CA25),IF(ABS(CA25-[1]QC_indicators!$B$1)>3*[1]QC_indicators!$C$1,"DF","no"))),IF(ISNUMBER(CA25),IF(ABS(CA25-[1]QC_indicators!$B$1)>3*[1]QC_indicators!$C$1,"DF","no"))) -> FALSE | FA25: =IF(LEN($CY25)=0,"",IF(AND($CY25<(-0.05),$ES25="C neutral forest and HWP assumption"),"Cneutral paradox",IF(AND($CY25>0.05,$EU25="In-situ only assumption"),"In-situ only paradox","")))
A26: GLOBAL CHANGE BIOLOGY BIOENERGY | B26: climate change mitigation; forest carbon; forest management; life cycle assessment; modelling; scenarios; tree harvest | C26: TRADE-OFFS; MANAGEMENT SCENARIOS; CHANGING CLIMATE; BOREAL FORESTS; WOOD PRODUCTS; TIMBER; SEQUESTRATION; BIODIVERSITY; EMISSIONS; BIOENERGY | D26: Soimakallio, S; Bottcher, H; Niemi, J; Mosley, F; Turunen, S; Hennenberg, KJ; Reise, J; Fehrenbach, H | E26: Closing an open balance: The impact of increased tree harvest on forest carbon | F26: Fossil-based emissions can be avoided by using wood in place of non-renewable raw materials as energy and materials. However, wood harvest influences forest carbon stocks. Increased harvest may reduce the overall climate benefit of wood use significantly, but is widely overlooked. We reviewed selected simulation studies and compared differences in forest carbon and amount of wood harvested between harvest scenarios of different intensities for three different time perspectives: short- (1-30 years), mid- (31-70 years), and long-term (71-100 years). Out of more than 450 reviewed studies 45 provided adequate data. Our results show that increased harvest reduces carbon stocks over 100 years in temperate and boreal forests by about 1.6 (stdev 0.9) t(C) per t(C) harvested (referred to as carbon balance indicator (CBI)). CBI proved to be robust when outliers explicitly influenced by factors other than changes in the harvest rate, such as fertilization or increase in forest area, were removed. The carbon impacts tend to be greatest in the mid-term, but no significant difference in was found for average values between short and long time-horizons. CBI can be interpreted as carbon opportunity costs of wood harvest in forests. Our results indicate that even after 100 years, CBI is significant compared to the typical GHG credits expected in the technosphere by avoiding fossil emissions in substitution and increasing carbon stocks in harvested wood products. Our estimates provide typical values that can directly be included in GHG balances of products or assessments of mitigation policies and measures related to wood use. However, more systematic scenarios with transparent information on influencing factors for forest carbon stocks are required to provide better constrained estimates for specific forest types. | G26: GCB Bioenergy | H26: Review | I26: 2022 | J26: 4 | K26: 10.1111/gcbb.12981 | M26: =LEFT($D26,FIND(",",$D26)-1)&"_"&I26&L26 -> Soimakallio_2022 | N26: review | CA26: =IFERROR(BZ26/BQ26,"") | CT26: =IF(BI26="Roundwood",$CS26/2,$CS26) -> 0 | CX26: =IFERROR($CW26/$CS26,"") | CZ26: =IFERROR($CW26/$CT26,"") | EP26: =IF(AND(AND(AND(OR($EC26=1,$EB26=1),OR($EH26=1,$EF26=1)),SUM($EA26:$EE26,$EK26)>=3),SUM($EF26:$EJ26)>=2),"Whole sector approach","") | EQ26: =IF(AND(AND(OR($EC26=1,$EB26=1),AND($EH26=0,$EF26=0)),SUM($EA26:$EE26,$EK26)>=3),"Ecosystem approach","") | ER26: =IF(AND(AND(AND($EC26=0,$EB26=0),OR($EH26=1,$EF26=1)),SUM($EG26:$EJ26)>=2),"Technology approach","") | ES26: =IF(AND($EC26+$EB26+$EE26+$EA26+$EF26+$EG26=0,$N26="included"),"C neutral forest and HWP assumption","") | ET26: =IF(AND(AND(AND($EC26+$EB26+$EA26+$EG26>=2,$EF26+$EH26+$EI26>=1),$ED26+$EE26>=1),$N26="included"),"All C pools assumption","") | EU26: =IF(AND($ED26+$EE26+$EI26+$EH26+$EF26=0,$N26="included"),"In-situ only assumption","") | EY26: =IF(ISNUMBER(BW26),IF(ABS(BW26-[1]QC_indicators!$B$2)>3*[1]QC_indicators!$C$2,"C ratio",IF(ISNUMBER(CA26),IF(ABS(CA26-[1]QC_indicators!$B$1)>3*[1]QC_indicators!$C$1,"DF","no"))),IF(ISNUMBER(CA26),IF(ABS(CA26-[1]QC_indicators!$B$1)>3*[1]QC_indicators!$C$1,"DF","no"))) -> FALSE | FA26: =IF(LEN($CY26)=0,"",IF(AND($CY26<(-0.05),$ES26="C neutral forest and HWP assumption"),"Cneutral paradox",IF(AND($CY26>0.05,$EU26="In-situ only assumption"),"In-situ only paradox","")))
A27: FORESTS | B27: alternative management; biodiversity; fire hazard abatement; forest residues; mammal habitat; piles and windrows; smoke emissions; woody debris | C27: UNDERSTORY PLANT-COMMUNITIES; GREEN-TREE RETENTION; DOWNED WOOD; POPULATION-DYNAMICS; LOGGING DEBRIS; TIMBER HARVEST; AIR-POLLUTION; RESPONSES; FIRE; BIODIVERSITY | D27: Sullivan, TP; Sullivan, DS; Klenner, W | E27: Fate of Postharvest Woody Debris, Mammal Habitat, and Alternative Management of Forest Residues on Clearcuts: A Synthesis | F27: Coarse woody debris on the forest floor contributes to maintenance of forest biodiversity and long-term ecosystem productivity. Down wood is often dispersed over harvested sites during logging activities, thereby leaving piles of postharvest debris as excess material at landings and roadsides. These wood residues may be burned in most jurisdictions in North America to reduce a perceived fire hazard. The fire hazard debate needs to acknowledge the documented benefits of woody debris retention while striking a balance among biodiversity, bioenergy, and alternative uses for debris, while reducing ignitions by humans. The burning of excess woody debris also creates smoke, causes the release of greenhouse gas (GHG) emissions, and creates human health issues, particularly for vulnerable individuals. The relationship of wildfire smoke to human health problems is well documented. However, there is no scientific evidence showing that postharvest debris piles are ignition points for forest fires, other than those caused by humans. Wood residues from forest harvesting or natural disturbance wood from wildfire and insect outbreaks may be used as renewable biomass feedstocks that could help improve energy supplies and reduce GHG emissions. If not marketable, the management of postharvest debris should seek alternative outlets that do not dispose of debris by burning, but still meet fire hazard abatement requirements. The construction of woody debris structures (e.g., piles and windrows) built at the time of forest harvesting and log processing, or later at the site preparation stages, has positive benefits for wildlife habitat and forest biodiversity. A windrow or series of piles may connect patches and reserves of mature forest and riparian areas on clearcut openings. Piles and windrows have consistently provided habitat on new clearcuts for southern red-backed voles (Myodes gapperi) and Microtus voles, as well as a host of other forest-floor small mammal species, at least up to 12 years postconstruction. Woody debris provides important habitat for foraging and cover attributes for marten (Martes americana), weasels (Mustela spp.), and other furbearers. A list of What to do? and When and Where? with options for construction of woody debris habitats: poorest, good, better, and best are given. In the cases where fire risk from humans is minimized and there are no marketable wood products, eight alternative management scenarios for postharvest woody debris are provided. These include: (1) piles for wildlife habitat; (2) distribution of debris in partial cut forests; (3) machinery to break up and crush debris; (4) protection of riparian zones with barriers for cattle; (5) construction of range fencing; (6) reclamation of landings and skid-trails; (7) soil fertility and reduction in weed competition and drought for planted conifers; and (8) slope stabilization and revegetation. Advantages and disadvantages (if known) are given for each alternative. A flow chart for the fate of excess postharvest woody debris with respect to fire hazard abatement and markets or nonmarkets is given. | G27: Forests | H27: Review | I27: 2021 | J27: 0 | K27: 10.3390/f12050551 | M27: =LEFT($D27,FIND(",",$D27)-1)&"_"&I27&L27 -> Sullivan_2021 | N27: review | O27: VB | Q27: v5 | CA27: =IFERROR(BZ27/BQ27,"") | CT27: =IF(BI27="Roundwood",$CS27/2,$CS27) -> 0 | CX27: =IFERROR($CW27/$CS27,"") | CZ27: =IFERROR($CW27/$CT27,"") | EP27: =IF(AND(AND(AND(OR($EC27=1,$EB27=1),OR($EH27=1,$EF27=1)),SUM($EA27:$EE27,$EK27)>=3),SUM($EF27:$EJ27)>=2),"Whole sector approach","") | EQ27: =IF(AND(AND(OR($EC27=1,$EB27=1),AND($EH27=0,$EF27=0)),SUM($EA27:$EE27,$EK27)>=3),"Ecosystem approach","") | ER27: =IF(AND(AND(AND($EC27=0,$EB27=0),OR($EH27=1,$EF27=1)),SUM($EG27:$EJ27)>=2),"Technology approach","") | ES27: =IF(AND($EC27+$EB27+$EE27+$EA27+$EF27+$EG27=0,$N27="included"),"C neutral forest and HWP assumption","") | ET27: =IF(AND(AND(AND($EC27+$EB27+$EA27+$EG27>=2,$EF27+$EH27+$EI27>=1),$ED27+$EE27>=1),$N27="included"),"All C pools assumption","") | EU27: =IF(AND($ED27+$EE27+$EI27+$EH27+$EF27=0,$N27="included"),"In-situ only assumption","") | EX27: okAV | EY27: =IF(ISNUMBER(BW27),IF(ABS(BW27-[1]QC_indicators!$B$2)>3*[1]QC_indicators!$C$2,"C ratio",IF(ISNUMBER(CA27),IF(ABS(CA27-[1]QC_indicators!$B$1)>3*[1]QC_indicators!$C$1,"DF","no"))),IF(ISNUMBER(CA27),IF(ABS(CA27-[1]QC_indicators!$B$1)>3*[1]QC_indicators!$C$1,"DF","no"))) -> FALSE | FA27: =IF(LEN($CY27)=0,"",IF(AND($CY27<(-0.05),$ES27="C neutral forest and HWP assumption"),"Cneutral paradox",IF(AND($CY27>0.05,$EU27="In-situ only assumption"),"In-situ only paradox","")))
A28: JOURNAL OF BUILDING ENGINEERING | B28: Cross-laminated timber; Carbon footprint; Life cycle assessment; Climate change; Sustainable multi-story construction | C28: CONCRETE; LCA; FUTURE; ENERGY; CARBON; SUSTAINABILITY; ALTERNATIVES; METHODOLOGY; MITIGATION; SCENARIOS | D28: Younis, A; Dodoo, A | E28: Cross-laminated timber for building construction: A life-cycle-assessment overview | F28: The building industry is a large contributor to greenhouse gas (GHG) emissions and a vast con -sumer of natural resources. It is estimated that, in the next 40 years, around 415 Gt of CO2 will be released as a result of global construction activities. Therefore, improvements in construction technologies are essential to reduce GHG emissions and thereby attain national and international goals to mitigate climate change. Cross-laminated timber (CLT) has emerged as an innovative alternative material to steel/concrete in building construction, given its relatively low carbon footprint, not to mention its high strength-to-weight ratio, simple installation, and aesthetic features. CLT is a structural composite panel product developed in the early 1990s, and the contemporary generation of CLT buildings are yet to reach the end of their service life. Accord-ingly, there has been growing interest to understand and optimize the performance of CLT in building construction. In view of that, this paper presents an overview on the feasibility of using CLT in buildings from a life-cycle assessment (LCA) standpoint. The authors performed a brief review on LCA studies conducted in the past decade pertaining to the carbon footprint of CLT buildings. On average, the findings of these studies revealed about 40% reduction in carbon footprint when using CLT in lieu of conventional construction materials (steel/concrete) for multi-story buildings. Furthermore, the paper explores the challenges associated with conducting LCA on CLT buildings, identifies the gaps in knowledge, and outlines directions for future research. | G28: J. Build. Eng. | H28: Article | I28: 2022 | J28: 10 | K28: 10.1016/j.jobe.2022.104482 | M28: =LEFT($D28,FIND(",",$D28)-1)&"_"&I28&L28 -> Younis_2022 | N28: review | O28: AV | Q28: v6 | CA28: =IFERROR(BZ28/BQ28,"") | CT28: =IF(BI28="Roundwood",$CS28/2,$CS28) -> 0 | CX28: =IFERROR($CW28/$CS28,"") | CZ28: =IFERROR($CW28/$CT28,"") | EP28: =IF(AND(AND(AND(OR($EC28=1,$EB28=1),OR($EH28=1,$EF28=1)),SUM($EA28:$EE28,$EK28)>=3),SUM($EF28:$EJ28)>=2),"Whole sector approach","") | EQ28: =IF(AND(AND(OR($EC28=1,$EB28=1),AND($EH28=0,$EF28=0)),SUM($EA28:$EE28,$EK28)>=3),"Ecosystem approach","") | ER28: =IF(AND(AND(AND($EC28=0,$EB28=0),OR($EH28=1,$EF28=1)),SUM($EG28:$EJ28)>=2),"Technology approach","") | ES28: =IF(AND($EC28+$EB28+$EE28+$EA28+$EF28+$EG28=0,$N28="included"),"C neutral forest and HWP assumption","") | ET28: =IF(AND(AND(AND($EC28+$EB28+$EA28+$EG28>=2,$EF28+$EH28+$EI28>=1),$ED28+$EE28>=1),$N28="included"),"All C pools assumption","") | EU28: =IF(AND($ED28+$EE28+$EI28+$EH28+$EF28=0,$N28="included"),"In-situ only assumption","") | EY28: =IF(ISNUMBER(BW28),IF(ABS(BW28-[1]QC_indicators!$B$2)>3*[1]QC_indicators!$C$2,"C ratio",IF(ISNUMBER(CA28),IF(ABS(CA28-[1]QC_indicators!$B$1)>3*[1]QC_indicators!$C$1,"DF","no"))),IF(ISNUMBER(CA28),IF(ABS(CA28-[1]QC_indicators!$B$1)>3*[1]QC_indicators!$C$1,"DF","no"))) -> FALSE | FA28: =IF(LEN($CY28)=0,"",IF(AND($CY28<(-0.05),$ES28="C neutral forest and HWP assumption"),"Cneutral paradox",IF(AND($CY28>0.05,$EU28="In-situ only assumption"),"In-situ only paradox","")))
A29: BIORESOURCES | B29: Reconstituted decorative lumber; Life cycle; Ecological civilization; Sustainable development | C29: WOOD; DESIGN; SUSTAINABILITY; CARBON | D29: Zhou, CM; Shi, ZY; Kaner, J | E29: Life Cycle Analysis for Reconstituted Decorative Lumber from an Ecological Perspective: A Review | F29: In response to global Sustainable Development Goals (SDGs), the Chinese government has pledged to curtail increased carbon dioxide emissions beyond 2030 and to achieve carbon neutrality by 2060, thus achieving a status of an ecological civilization. Reconstituted decorative lumber, with rotary-cut (or planed) veneer from plantation or common species timber as the main raw material, has beneficial development opportunities for forestry from the perspective of an ecological civilization. This paper first discusses China's current state of ecological civilization, then researches the various life cycles of reconstituted decorative lumber using the life cycle theory and provides a reference for the Chinese reconstituted decorative lumber industry's development by analyzing progress in related fields. The eco-friendliness of reconstituted decorative lumber is explained via systematic combing, and proposals for the use and promotion of reconstituted decorative lumber in the new period are presented. Research and analysis findings show that it is necessary to comprehensively regulate the production chain of reconstituted decorative lumber based on life cycle. Research on the development and utilization of reconstituted decorative lumber needs to be strengthened. The promotion and marketing of reconstituted decorative lumber can be promoted by emphasizing its ecological significance. | G29: BioResources | H29: Review | I29: 2022 | J29: 1 | K29: 10.15376/biores.17.3.Zhou | M29: =LEFT($D29,FIND(",",$D29)-1)&"_"&I29&L29 -> Zhou_2022 | N29: review | CA29: =IFERROR(BZ29/BQ29,"") | CT29: =IF(BI29="Roundwood",$CS29/2,$CS29) -> 0 | CX29: =IFERROR($CW29/$CS29,"") | CZ29: =IFERROR($CW29/$CT29,"") | EP29: =IF(AND(AND(AND(OR($EC29=1,$EB29=1),OR($EH29=1,$EF29=1)),SUM($EA29:$EE29,$EK29)>=3),SUM($EF29:$EJ29)>=2),"Whole sector approach","") | EQ29: =IF(AND(AND(OR($EC29=1,$EB29=1),AND($EH29=0,$EF29=0)),SUM($EA29:$EE29,$EK29)>=3),"Ecosystem approach","") | ER29: =IF(AND(AND(AND($EC29=0,$EB29=0),OR($EH29=1,$EF29=1)),SUM($EG29:$EJ29)>=2),"Technology approach","") | ES29: =IF(AND($EC29+$EB29+$EE29+$EA29+$EF29+$EG29=0,$N29="included"),"C neutral forest and HWP assumption","") | ET29: =IF(AND(AND(AND($EC29+$EB29+$EA29+$EG29>=2,$EF29+$EH29+$EI29>=1),$ED29+$EE29>=1),$N29="included"),"All C pools assumption","") | EU29: =IF(AND($ED29+$EE29+$EI29+$EH29+$EF29=0,$N29="included"),"In-situ only assumption","") | EY29: =IF(ISNUMBER(BW29),IF(ABS(BW29-[1]QC_indicators!$B$2)>3*[1]QC_indicators!$C$2,"C ratio",IF(ISNUMBER(CA29),IF(ABS(CA29-[1]QC_indicators!$B$1)>3*[1]QC_indicators!$C$1,"DF","no"))),IF(ISNUMBER(CA29),IF(ABS(CA29-[1]QC_indicators!$B$1)>3*[1]QC_indicators!$C$1,"DF","no"))) -> FALSE | FA29: =IF(LEN($CY29)=0,"",IF(AND($CY29<(-0.05),$ES29="C neutral forest and HWP assumption"),"Cneutral paradox",IF(AND($CY29>0.05,$EU29="In-situ only assumption"),"In-situ only paradox","")))
A30: EKONOMICHESKAYA POLITIKA | B30: Paris Agreement; the role of boreal forests in carbon balance; carbon neutrality; Canada | C30: DYNAMICS | D30: Shvarts, EA; Ptichnikov, AV; Kokorin, AO; Krenke, AN | E30: Cross-Border Carbon Regulation and Forests in Russia: From Expectations and Myth to Realization of Interests | F30: Introduction of the EU Carbon Border Adjustment Mechanism over the period from 2023 to 2026 together with corporate commitments to achieve carbon neutrality and carry out commercial decarbonization have markedly increased interest in assessing the potential of carbon sequestration by Russian forests as a possible way to achieve decarbonization and facilitate Russian exports. The prevailing opinion in business circles is that a signi ficant net positive carbon balance from Russia's forests could circumvent the need for businesses to make costly reductions in their direct CO2 emissions. However, international decarbonization strategies and standards do not concur with that idea. Direct emissions will have to be reduced. Offset mechanisms, whose benefits are calculated as the difference between a baseline and an improved scenario for forest management (the principle of additionality), will compensate for only a part of the emissions. The experience of Canada is indicative, as it consistently implements measures to decarbonize industry without regard to the absorption of CO2 by its forests. Even though Canada has climatic conditions, forest growth, and population density similar to Russia's, its policy is not dependent upon revising estimates of net CO2 absorption by forests upward. Forestry priorities in Russia, including reforestation, should instead be gradually shifted from managing commercial forests for harvesting timber to reducing all forest fires. Leased and non-leased forests should both be included, and reforestation that favors deciduous species and mixed forests should be given a higher priority. It is also necessary to remove barriers to forestry in agricultural forests and to plan for implementation of projects directed at improving both forestry and climate on the land leased out from the holdings of the State Forest Fund as well as on agricultural tracts, including those now overgrown by forests. | G30: EKONOMICHESKAYA POLIT. | H30: Article | I30: 2022 | J30: 0 | K30: 10.18288/1994-5124-2022-5-54-77 | M30: =LEFT($D30,FIND(",",$D30)-1)&"_"&I30&L30 -> Shvarts_2022 | N30: not english | O30: AV | Q30: v6 | CA30: =IFERROR(BZ30/BQ30,"") | CT30: =IF(BI30="Roundwood",$CS30/2,$CS30) -> 0 | CX30: =IFERROR($CW30/$CS30,"") | CZ30: =IFERROR($CW30/$CT30,"") | EP30: =IF(AND(AND(AND(OR($EC30=1,$EB30=1),OR($EH30=1,$EF30=1)),SUM($EA30:$EE30,$EK30)>=3),SUM($EF30:$EJ30)>=2),"Whole sector approach","") | EQ30: =IF(AND(AND(OR($EC30=1,$EB30=1),AND($EH30=0,$EF30=0)),SUM($EA30:$EE30,$EK30)>=3),"Ecosystem approach","") | ER30: =IF(AND(AND(AND($EC30=0,$EB30=0),OR($EH30=1,$EF30=1)),SUM($EG30:$EJ30)>=2),"Technology approach","") | ES30: =IF(AND($EC30+$EB30+$EE30+$EA30+$EF30+$EG30=0,$N30="included"),"C neutral forest and HWP assumption","") | ET30: =IF(AND(AND(AND($EC30+$EB30+$EA30+$EG30>=2,$EF30+$EH30+$EI30>=1),$ED30+$EE30>=1),$N30="included"),"All C pools assumption","") | EU30: =IF(AND($ED30+$EE30+$EI30+$EH30+$EF30=0,$N30="included"),"In-situ only assumption","") | EY30: =IF(ISNUMBER(BW30),IF(ABS(BW30-[1]QC_indicators!$B$2)>3*[1]QC_indicators!$C$2,"C ratio",IF(ISNUMBER(CA30),IF(ABS(CA30-[1]QC_indicators!$B$1)>3*[1]QC_indicators!$C$1,"DF","no"))),IF(ISNUMBER(CA30),IF(ABS(CA30-[1]QC_indicators!$B$1)>3*[1]QC_indicators!$C$1,"DF","no"))) -> FALSE | FA30: =IF(LEN($CY30)=0,"",IF(AND($CY30<(-0.05),$ES30="C neutral forest and HWP assumption"),"Cneutral paradox",IF(AND($CY30>0.05,$EU30="In-situ only assumption"),"In-situ only paradox","")))
A31: PROCEEDINGS OF THE INSTITUTION OF CIVIL ENGINEERS-STRUCTURES AND BUILDINGS | B31: built environment; embodied carbon; embodied energy; energy efficiency; renewable energy; statistical analysis; structural materials; sustainability | D31: Anderson, J; Moncaster, A | E31: Embodied carbon, embodied energy and renewable energy: a review of environmental product declarations | F31: Environmental product declarations (EPD) to EN 15804 provide information about the embodied carbon dioxide of construction products - their life cycle greenhouse gas emissions - alongside reporting the use of renewable and non-renewable primary energy and secondary fuels, among the other environmental indicators. As the number of EPD to EN 15804 increases, they become a useful data resource to consider these impacts. In moving towards a reduction in the embodied carbon of products, it is necessary to use renewable energy resources efficiently to allow the transition to net zero; this is because of the increasing demands on renewable energy to decarbonise industry, transport and domestic energy consumption and the limited capacity to expand renewable generation. This paper reviews published EPD data for structural and reinforcing steels, cement, bricks and structural timber products, and considers, for the cradle to gate 'product' life cycle stage, exploring the relationship of embodied carbon with embodied energy (total energy used), the balance of renewable and non-renewable energy, and the efficient use of energy. It is found, for bricks and timber, that EPD show products that use a greater percentage of renewable energy have higher embodied energy, suggesting a less efficient use of renewable energy for these products. | G31: Proc. Inst. Civil Eng.-Struct. Build. | H31: Review; Early Access | I31: 2022 | J31: 1 | K31: 10.1680/jstbu.21.00160 | M31: =LEFT($D31,FIND(",",$D31)-1)&"_"&I31&L31 -> Anderson_2022 | N31: no journal | O31: AV | CA31: =IFERROR(BZ31/BQ31,"") | CT31: =IF(BI31="Roundwood",$CS31/2,$CS31) -> 0 | CX31: =IFERROR($CW31/$CS31,"") | CZ31: =IFERROR($CW31/$CT31,"") | EP31: =IF(AND(AND(AND(OR($EC31=1,$EB31=1),OR($EH31=1,$EF31=1)),SUM($EA31:$EE31,$EK31)>=3),SUM($EF31:$EJ31)>=2),"Whole sector approach","") | EQ31: =IF(AND(AND(OR($EC31=1,$EB31=1),AND($EH31=0,$EF31=0)),SUM($EA31:$EE31,$EK31)>=3),"Ecosystem approach","") | ER31: =IF(AND(AND(AND($EC31=0,$EB31=0),OR($EH31=1,$EF31=1)),SUM($EG31:$EJ31)>=2),"Technology approach","") | ES31: =IF(AND($EC31+$EB31+$EE31+$EA31+$EF31+$EG31=0,$N31="included"),"C neutral forest and HWP assumption","") | ET31: =IF(AND(AND(AND($EC31+$EB31+$EA31+$EG31>=2,$EF31+$EH31+$EI31>=1),$ED31+$EE31>=1),$N31="included"),"All C pools assumption","") | EU31: =IF(AND($ED31+$EE31+$EI31+$EH31+$EF31=0,$N31="included"),"In-situ only assumption","") | EY31: =IF(ISNUMBER(BW31),IF(ABS(BW31-[1]QC_indicators!$B$2)>3*[1]QC_indicators!$C$2,"C ratio",IF(ISNUMBER(CA31),IF(ABS(CA31-[1]QC_indicators!$B$1)>3*[1]QC_indicators!$C$1,"DF","no"))),IF(ISNUMBER(CA31),IF(ABS(CA31-[1]QC_indicators!$B$1)>3*[1]QC_indicators!$C$1,"DF","no"))) -> FALSE | FA31: =IF(LEN($CY31)=0,"",IF(AND($CY31<(-0.05),$ES31="C neutral forest and HWP assumption"),"Cneutral paradox",IF(AND($CY31>0.05,$EU31="In-situ only assumption"),"In-situ only paradox","")))
A32: NAFTA-GAZ | B32: biohydrogen; biofuel; reforming; gasification; GHG emissions | C32: HYDROGEN-PRODUCTION; GASIFICATION; BIOMASS | D32: Berdechowski, K | E32: Analysis of biohydrogen production methods in terms of GHG emission value | F32: One of the fuels which will be used in the future to a much greater extent than currently is hydrogen. Many of the implemented technologies will allow this kind of fuel to drive motor vehicles without major obstacles. However, hydrogen has long been an indispensable raw material for many installations for the production of traditional fuels and used primarily for the so-called hydrogen catalytic processes (including hydrocracking, hydrotreating). Traditional hydrogen production based on natural gas steam reforming, generates high GHG emissions over the life cycle. The reason for this is the use of fossil raw material, from which CO2 is generated at the production stage (treated as emission from fossil fuel and included in the GHG emission balance). The second reason is the high energy consumption of the process, which translates into additional greenhouse gas emissions generated in the life cycle. Given this aspect, it is advisable to use alternative methods of obtaining hydrogen and known processes, but using waste biomass as the starting raw material. Such processes lead to obtaining hydrogen, which due to the origin of the raw material from which it was created, is treated as a biofuel. Current legislation allows the possibility to qualify the biohydrogen used in the abovementioned refinery processes as a biogenic component of traditional fuel. However, according to the current regulations, each biofuel must meet the sustainability criteria. One of them is the minimum level of greenhouse gas emission reduction calculated in the whole life cycle. Therefore, as part of this work, three production paths have been analyzed. The following pathways were analyzed: biohydrogen from biogas, biohydrogen from wood residues and biohydrogen from raw glycerine. Of the three, the most advantageous variant turned out to be biogas reforming, which showed a GEG emission reduction of around 77%. In addition, only this production path met the requirements for biofuels obtained on new installations. | G32: Naft.-Gaz | H32: Article | I32: 2019 | J32: 1 | K32: 10.18668/NG.2019.04.05 | M32: =LEFT($D32,FIND(",",$D32)-1)&"_"&I32&L32 -> Berdechowski_2019 | N32: no journal | O32: AV | Q32: v5 | CA32: =IFERROR(BZ32/BQ32,"") | CT32: =IF(BI32="Roundwood",$CS32/2,$CS32) -> 0 | CX32: =IFERROR($CW32/$CS32,"") | CZ32: =IFERROR($CW32/$CT32,"") | EP32: =IF(AND(AND(AND(OR($EC32=1,$EB32=1),OR($EH32=1,$EF32=1)),SUM($EA32:$EE32,$EK32)>=3),SUM($EF32:$EJ32)>=2),"Whole sector approach","") | EQ32: =IF(AND(AND(OR($EC32=1,$EB32=1),AND($EH32=0,$EF32=0)),SUM($EA32:$EE32,$EK32)>=3),"Ecosystem approach","") | ER32: =IF(AND(AND(AND($EC32=0,$EB32=0),OR($EH32=1,$EF32=1)),SUM($EG32:$EJ32)>=2),"Technology approach","") | ES32: =IF(AND($EC32+$EB32+$EE32+$EA32+$EF32+$EG32=0,$N32="included"),"C neutral forest and HWP assumption","") | ET32: =IF(AND(AND(AND($EC32+$EB32+$EA32+$EG32>=2,$EF32+$EH32+$EI32>=1),$ED32+$EE32>=1),$N32="included"),"All C pools assumption","") | EU32: =IF(AND($ED32+$EE32+$EI32+$EH32+$EF32=0,$N32="included"),"In-situ only assumption","") | EW32: excluded because written in polish | EX32: okVB | EY32: =IF(ISNUMBER(BW32),IF(ABS(BW32-[1]QC_indicators!$B$2)>3*[1]QC_indicators!$C$2,"C ratio",IF(ISNUMBER(CA32),IF(ABS(CA32-[1]QC_indicators!$B$1)>3*[1]QC_indicators!$C$1,"DF","no"))),IF(ISNUMBER(CA32),IF(ABS(CA32-[1]QC_indicators!$B$1)>3*[1]QC_indicators!$C$1,"DF","no"))) -> FALSE | FA32: =IF(LEN($CY32)=0,"",IF(AND($CY32<(-0.05),$ES32="C neutral forest and HWP assumption"),"Cneutral paradox",IF(AND($CY32>0.05,$EU32="In-situ only assumption"),"In-situ only paradox","")))
A33: NAFTA-GAZ | B33: biohydrogen; biofuel; reforming; gasification; GHG emissions | C33: HYDROGEN-PRODUCTION; GASIFICATION; BIOMASS | D33: Berdechowski, K | E33: Analysis of biohydrogen production methods in terms of GHG emission value | F33: One of the fuels which will be used in the future to a much greater extent than currently is hydrogen. Many of the implemented technologies will allow this kind of fuel to drive motor vehicles without major obstacles. However, hydrogen has long been an indispensable raw material for many installations for the production of traditional fuels and used primarily for the so-called hydrogen catalytic processes (including hydrocracking, hydrotreating). Traditional hydrogen production based on natural gas steam reforming, generates high GHG emissions over the life cycle. The reason for this is the use of fossil raw material, from which CO2 is generated at the production stage (treated as emission from fossil fuel and included in the GHG emission balance). The second reason is the high energy consumption of the process, which translates into additional greenhouse gas emissions generated in the life cycle. Given this aspect, it is advisable to use alternative methods of obtaining hydrogen and known processes, but using waste biomass as the starting raw material. Such processes lead to obtaining hydrogen, which due to the origin of the raw material from which it was created, is treated as a biofuel. Current legislation allows the possibility to qualify the biohydrogen used in the abovementioned refinery processes as a biogenic component of traditional fuel. However, according to the current regulations, each biofuel must meet the sustainability criteria. One of them is the minimum level of greenhouse gas emission reduction calculated in the whole life cycle. Therefore, as part of this work, three production paths have been analyzed. The following pathways were analyzed: biohydrogen from biogas, biohydrogen from wood residues and biohydrogen from raw glycerine. Of the three, the most advantageous variant turned out to be biogas reforming, which showed a GEG emission reduction of around 77%. In addition, only this production path met the requirements for biofuels obtained on new installations. | G33: Naft.-Gaz | H33: Article | I33: 2019 | J33: 1 | K33: 10.18668/NG.2019.04.05 | M33: =LEFT($D33,FIND(",",$D33)-1)&"_"&I33&L33 -> Berdechowski_2019 | N33: no journal | O33: AV | Q33: v5 | CA33: =IFERROR(BZ33/BQ33,"") | CT33: =IF(BI33="Roundwood",$CS33/2,$CS33) -> 0 | CX33: =IFERROR($CW33/$CS33,"") | CZ33: =IFERROR($CW33/$CT33,"") | EP33: =IF(AND(AND(AND(OR($EC33=1,$EB33=1),OR($EH33=1,$EF33=1)),SUM($EA33:$EE33,$EK33)>=3),SUM($EF33:$EJ33)>=2),"Whole sector approach","") | EQ33: =IF(AND(AND(OR($EC33=1,$EB33=1),AND($EH33=0,$EF33=0)),SUM($EA33:$EE33,$EK33)>=3),"Ecosystem approach","") | ER33: =IF(AND(AND(AND($EC33=0,$EB33=0),OR($EH33=1,$EF33=1)),SUM($EG33:$EJ33)>=2),"Technology approach","") | ES33: =IF(AND($EC33+$EB33+$EE33+$EA33+$EF33+$EG33=0,$N33="included"),"C neutral forest and HWP assumption","") | ET33: =IF(AND(AND(AND($EC33+$EB33+$EA33+$EG33>=2,$EF33+$EH33+$EI33>=1),$ED33+$EE33>=1),$N33="included"),"All C pools assumption","") | EU33: =IF(AND($ED33+$EE33+$EI33+$EH33+$EF33=0,$N33="included"),"In-situ only assumption","") | EW33: excluded because written in polish | EY33: =IF(ISNUMBER(BW33),IF(ABS(BW33-[1]QC_indicators!$B$2)>3*[1]QC_indicators!$C$2,"C ratio",IF(ISNUMBER(CA33),IF(ABS(CA33-[1]QC_indicators!$B$1)>3*[1]QC_indicators!$C$1,"DF","no"))),IF(ISNUMBER(CA33),IF(ABS(CA33-[1]QC_indicators!$B$1)>3*[1]QC_indicators!$C$1,"DF","no"))) -> FALSE | FA33: =IF(LEN($CY33)=0,"",IF(AND($CY33<(-0.05),$ES33="C neutral forest and HWP assumption"),"Cneutral paradox",IF(AND($CY33>0.05,$EU33="In-situ only assumption"),"In-situ only paradox","")))
A34: CARBON MANAGEMENT, TECHNOLOGIES, AND TRENDS IN MEDITERRANEAN ECOSYSTEMS | B34: Climate change; Mitigation; Cost-benefit analysis; Kyoto Protocol; LULUCF | D34: Bouyer, O; Serengil, Y | E34: Cost-Benefit Assessment of Implementing LULUCF Accounting Rules in Turkey | F34: Turkey is an Annex 1 Party with Specific circumstances because it has the fastest population growth rate among the Organization for Economic Cooperation and Development (OECD) countries and lowest per capita energy-related CO2 emissions among the International Energy Agency (IEA) countries. In addition, all national indicators show that Turkey is in fact a developing country. It was deleted from Annex 2 of the United Nations Framework Convention on Climate Change (UNFCCC) and not included in the Annex B of the first term of the Kyoto Protocol (KP1). In the context of preparation of a 2015 multilateral treaty on climate change, which would enter into force in 2020, differentiation between Annex 1 and non-Annex 1 Parties may be revisited, and it seems useful to explore the possible consequences of such a reclassification. Accordingly, this study aims at providing a neutral cost/benefit assessment of implementing Land Use, Land Use Change and Forestry (LULUCF) accounting rules in Turkey in the future, as one possible scenario. The rationale for this assessment is based on a technical and objective deduction and does not in any way pre-empt the national positions put forward by Turkey in the climate negotiations or any possible COP decision that may determine its future classification, considering its specific circumstances. Turkey started reporting LULUCF under the Climate Convention in 2006. Presently, the LULUCF sink (made of a forest sink for its bigger part) is estimated to offset 12 % of Turkey's total greenhouse emissions. For afforestation/reforestation (A/R) (Article 3.3), the objectives of the 2014-2017 OGM (General Directorate of Forestry Turkish abbreviation) Strategic Plan were considered. For forest management (FM) (Article 3.4), two alternative scenarios were considered: 90 Mm3 of roundwood harvest between 2013 and 2017 (intensive harvest) and 25 Mm3/year of felling (industrial round wood) harvest by 2020 (extensive harvest). The corresponding volumes of firewood, felling and total round wood were forecast accordingly from 2013 to 2020. The carbon credits or Removal Units (RMUs) for Article 3.3 ARD and Article 3.4 FM (including the carbon storage in harvested wood products) were estimated using the guidelines from the intergovernmental panel of experts on climate change and taking into account the upgraded LULUCF rules. For Article 3.3, it was estimated that 119.4 million RMUs could be generated between 2013 and 2020, which is more than twice the maximum amount of RMUs to be generated under Article 3.4 FM. The total economic values (TEVs) of Turkey's forests have been estimated based on recent studies and then used to calculate benefits. Taking into account the recent European Union (EU) market price (Kyoto market) or the recent forest carbon price (Kyoto and voluntary markets), carbon benefits are reduced in all scenarios compared with other values included in the TEV of the forest. If we consider the carbon shadow price (i.e. the recommended carbon price from 2011 to 2050, to achieve the EU target of reducing GHG emissions fourfold by 2050), it is worth noting that the situation is quite different: for the 3.4 FM areas and mainly for 3.3 ARD areas, the carbon benefits are substantial. However, this price level is still far from attainable as negotiations stand now, unless the international community is able to adopt a strong political commitment in coming years. | H34: Article; Book Chapter | I34: 2017 | J34: 1 | K34: 10.1007/978-3-319-45035-3_8 | M34: =LEFT($D34,FIND(",",$D34)-1)&"_"&I34&L34 -> Bouyer_2017 | N34: no journal | O34: VB | Q34: v6 | R34: AV | S34: Increased harvest | T34: extensive | U34: intensive | X34: 0 | Y34: 0 | Z34: 0 | AA34: 1 | AB34: 0 | AC34: 0 | AD34: 0 | AE34: 0 | AF34: 0 | AG34: 0 | AH34: 0 | AI34: 0 | AJ34: 0 | AK34: 0 | AL34: 0 | AM34: 0 | AN34: 0 | AO34: 0 | AP34: 0 | AQ34: 0 | AR34: 0 | AS34: 0 | AT34: 0 | AU34: 0 | AV34: 0 | AW34: 0 | AX34: 0 | AY34: 0 | AZ34: =COUNTIF(X34:AY34,"<>0") -> 1 | BA34: =COUNTIF(X34:AN34,"<>0") -> 1 | BB34: =COUNTIF(X34:AE34,"<>0") -> 1 | BC34: =COUNTIF(AF34:AK34,"<>0") -> 0 | BD34: =COUNTIF(AL34:AN34,"<>0") -> 0 | BE34: =COUNTIF(AU34:AY34,"<>0") -> 0 | BF34: =COUNTIF(AO34:AT34,"<>0") -> 0 | BG34: {=IF(BA34=1,INDEX($X$7:$AN$7,MATCH(TRUE,INDEX($X34:$AY34<>0,),0)),IF(BA34=0,INDEX($AO$7:$AY$7,MATCH(1,$AO34:$AY34,0)),IF(BH34="Multiple strategies","mixed drivers",IF(BH34="Supply chain","multiple supply","multiple silviculture"))))} -> cutting intensity | BH34: {=IF(COUNTIF(BB34:BD34,"<>0")=1,INDEX($X$4:$AY$4,MATCH(TRUE,INDEX($X34:$AY34<>0,),0)),IF(COUNTIF(BB34:BD34,"<>0")=0,INDEX($AO$4:$AY$4,MATCH(1,$AO34:$AY34,0)),"Multiple strategies"))} -> Silviculture for removals | BI34: Roundwood | BJ34: harvested volume | BK34: Text and figure 8.16 & 8.17 | BL34: Mm3/yr | BM34: 21.542969 | BN34: 24.02587 | BO34: =BN34/BM34 -> 1.1152534 | BP34: =BN34-BM34 -> 2.4829012 | BQ34: =BP34*1000000 -> 2482901.2 | BR34: Sequestration positive | BS34: Figure 8,18 | BT34: MtCO2/yr | BU34: 15.160763 | BV34: 11.996176 | BW34: =BV34/BU34 -> 0.79126463 | BX34: =BV34-BU34 -> -3.1645876 | BZ34: =BX34*1000000 -> -3164587.6 | CA34: =IFERROR(BZ34/BQ34,"") -> -1.2745524 | CB34: 0 | CC34: 0 | CD34: 0 | CE34: 0 | CF34: 0 | CG34: 0 | CH34: 0 | CI34: 0 | CJ34: 0 | CK34: 0 | CL34: 0 | CM34: 0 | CN34: 0 | CO34: 0 | CP34: =IF($BN34<$BM34,"refNeedCorrection","refOK") -> refOK | CQ34: =IF($CP34="refOK",$BM34,$BN34) -> 21.542969 | CR34: =IF($CP34="refOK",$BN34,$BM34) -> 24.02587 | CS34: =IF($CP34="refOK",$BQ34,-$BQ34) -> 2482901.2 | CT34: =IF(BI34="Roundwood",$CS34/2,$CS34) -> 1241450.6 | CU34: =IF($CP34="refOK",$BU34,$BV34)*IF($BR34="Emissions positive",-1,1) -> 15.160763 | CV34: =IF($CP34="refOK",$BV34,$BU34)*IF($BR34="Emissions positive",-1,1) -> 11.996176 | CW34: =IF($CP34="refNeedCorrection",-BZ34,BZ34)*IF($BR34="Emissions positive",-1,1) -> -3164587.6 | CX34: =IFERROR($CW34/$CS34,"") -> -1.2745524 | CY34: =IFERROR($CW34/$CS34,"") -> -1.2745524 | CZ34: =IFERROR($CW34/$CT34,"") -> -2.5491047 | DA34: =IFERROR((CV34-CU34)/ABS(CU34),"") -> -0.20873537 | DB34: coy | DC34: =IF(OR($DB34="prd",$DB34="std",$DB34="cit"),"loc",IF(OR($DB34="eur",$DB34="reg",$DB34="coy"),"reg",$DB34)) -> reg | DD34: Turkey | DE34: 2013 | DF34: 2020 | DG34: =DF34-DE34 -> 7 | DH34: =IF(DG34=0,"0",IF(AND(DG34>=1,DG34<=30),"1-30",IF(AND(DG34>30,DG34<=70),"31-70",IF(AND(DG34>70,DG34<=100),"71-100",IF(DG34>100,"+100"))))) -> 1-30 | DI34: 1 | DJ34: 0 | DK34: 0 | DL34: 0 | DM34: 0 | DN34: =SUM(DI34:DL34) -> 1 | DO34: =IF(DN34=1,INDEX($DI$7:$DL$7,MATCH(1,$DI34:$DL34,0)),"mixedProduct") -> UpstreamInput | DP34: =IF(DI34=1,DP$7,0) -> Upstream | DQ34: =IF(DJ34=1,DQ$7,0) -> 0 | DR34: =IF(DK34=1,DR$7,0) -> 0 | DS34: =IF(DL34=1,DS$7,0) -> 0 | DT34: 0 | DU34: 0 | DV34: 0 | DW34: 0 | DX34: 0 | EA34: 0 | EB34: 0 | EC34: 1 | ED34: 1 | EE34: 0 | EF34: 0 | EG34: 0 | EH34: 0 | EI34: 0 | EJ34: 0 | EK34: 1 | EL34: 0 | EM34: 0 | EN34: 0 | EP34: =IF(AND(AND(AND(OR($EC34=1,$EB34=1),OR($EH34=1,$EF34=1)),SUM($EA34:$EE34,$EK34)>=3),SUM($EF34:$EJ34)>=2),"Whole sector approach","") | EQ34: =IF(AND(AND(OR($EC34=1,$EB34=1),AND($EH34=0,$EF34=0)),SUM($EA34:$EE34,$EK34)>=4),"Ecosystem approach","") | ER34: =IF(AND(AND(AND($EC34=0,$EB34=0),OR($EH34=1,$EF34=1)),SUM($EG34:$EJ34)>=2),"Technology approach","") | ES34: =IF(AND($EC34+$EB34+$EE34+$EA34+$EF34+$EG34=0,$N34="included"),"C neutral forest and HWP assumption","") | ET34: =IF(AND(AND(AND($EC34+$EB34+$EA34+$EG34>=2,$EF34+$EH34+$EI34>=1),$ED34+$EE34>=1),$N34="included"),"All C pools assumption","") | EU34: =IF(AND($ED34+$EE34+$EI34+$EH34+$EF34=0,$N34="included"),"In-situ only assumption","") | EY34: =IF(ISNUMBER(BW34),IF(ABS(BW34-[2]QC_indicators!$B$2)>3*[2]QC_indicators!$C$2,"C ratio",IF(ISNUMBER(CA34),IF(ABS(CA34-[2]QC_indicators!$B$1)>3*[2]QC_indicators!$C$1,"DF","no"))),IF(ISNUMBER(CA34),IF(ABS(CA34-[2]QC_indicators!$B$1)>3*[2]QC_indicators!$C$1,"DF","no"))) -> no | FA34: =IF(LEN($CY34)=0,"",IF(AND($CY34<(-0.05),$ES34="C neutral forest and HWP assumption"),"Cneutral paradox",IF(AND($CY34>0.05,$EU34="In-situ only assumption"),"In-situ only paradox",""))) | FD34: no journal ,exclusion
A35: 18TH WORLD IMACS CONGRESS AND MODSIM09 INTERNATIONAL CONGRESS ON MODELLING AND SIMULATION: INTERFACING MODELLING AND SIMULATION WITH MATHEMATICAL AND COMPUTATIONAL SCIENCES | B35: Climate change; plantation species selection; probability of fire; carbon sequestration | D35: Buchanan, G; Kennedy, J | E35: Optimal selection of plantation tree species accounting for climate change | F35: The Australian plantation forestry industry, including the manufacture of forest products will be affected directly by climate change, since changes in weather variables such as temperature and rainfall directly impact timber yields. Furthermore, increased CO(2) concentrations and risk of fire are also likely to directly result in altered yields from forested land. This analysis aims to examine the future viability and profitability of the two most widely planted and financially important plantation species in Australia, Pinus Radiata and Eucalyptus Globulus. These two species of plantation tree have proved successful in the environment of Australia; however whether this continues to be the case in a changing climate is unclear. Examination of this question is facilitated through the use of a Central Victorian case study. The most recent National Plantation Inventory (1996) of the Bureau of Rural Sciences (BRS) defines Central Victoria as the region located immediately west of Melbourne, stretching from the Otway Ranges, north to Castlemaine, and to just west of the Grampians. The main areas of significance for plantation centre on Ballarat, Beaufort, Colac and Geelong which are also major centres for timber processing (and shipping in Geelong). Central Victoria has a reported total plantation area of 57,185 hectares, of which the two most planted species are Pinus Radiata which comprise 53.7 % of plantation land, and Eucalyptus Globulus which constitutes 43.2 %. Australia wide the two most widely planted plantation species are also Pinus Radiata which accounts for 42.6 % of the total land in Australia under plantation, and Eucalyptus Globulus which accounts for 21.6 % of total plantings in Australia. The data used in this study concentrates on these two species since they are central to the plantation industry in the region and in the country as a whole. The expected long-run value of the two species, Pinus Radiata and Eucalyptus Globulus, are estimated, in two ways: first assuming current growing conditions continue indefinitely; and secondly assuming changing growing conditions as a result of projected climate change. The plantation region considered is Central Victoria, split into three productivity areas based on historical seasonal rainfall. Estimates of the effect of climate change, represented by changes in atmospheric carbon dioxide concentration, ambient temperature and rainfall, on timber yields for the two species are used in the second part of the study. Maximum net present values of plantation returns with respect to rotation length are determined in the first part based on the Faustmann formula for infinite rotations with no changes in growth parameters. In the second part, maximum net present values are calculated with respect to rotation length the same for each rotation, over 20 rotations, allowing for changing growth parameters. For the base rate of discount of 3 per cent per annum the net present values over a planning horizon of 20 rotations closely approximate the present values over infinite rotations. Plantation returns include payments from carbon sequestration calculated for a range of carbon prices. Allowance is made for the changing probability of fire destroying a plantation in any year by adding a suitable element to the rate of discount. It is concluded that for the base case climate-change scenario, Eucalyptus Globulus dominates Pinus Radiata as the preferred species, but this is subject to a number of caveats. The modelling of how the net present value (NPV) of each species changes under climate change provides insight for management practices (including selection of plantation species) to better anticipate the challenges of climate change. | H35: Proceedings Paper | I35: 2009 | J35: 0 | M35: =LEFT($D35,FIND(",",$D35)-1)&"_"&I35&L35 -> Buchanan_2009 | N35: no journal | O35: AV | CA35: =IFERROR(BZ35/BQ35,"") | CT35: =IF(BI35="Roundwood",$CS35/2,$CS35) -> 0 | CX35: =IFERROR($CW35/$CS35,"") | CZ35: =IFERROR($CW35/$CT35,"") | EP35: =IF(AND(AND(AND(OR($EC35=1,$EB35=1),OR($EH35=1,$EF35=1)),SUM($EA35:$EE35,$EK35)>=3),SUM($EF35:$EJ35)>=2),"Whole sector approach","") | EQ35: =IF(AND(AND(OR($EC35=1,$EB35=1),AND($EH35=0,$EF35=0)),SUM($EA35:$EE35,$EK35)>=3),"Ecosystem approach","") | ER35: =IF(AND(AND(AND($EC35=0,$EB35=0),OR($EH35=1,$EF35=1)),SUM($EG35:$EJ35)>=2),"Technology approach","") | ES35: =IF(AND($EC35+$EB35+$EE35+$EA35+$EF35+$EG35=0,$N35="included"),"C neutral forest and HWP assumption","") | ET35: =IF(AND(AND(AND($EC35+$EB35+$EA35+$EG35>=2,$EF35+$EH35+$EI35>=1),$ED35+$EE35>=1),$N35="included"),"All C pools assumption","") | EU35: =IF(AND($ED35+$EE35+$EI35+$EH35+$EF35=0,$N35="included"),"In-situ only assumption","") | EY35: =IF(ISNUMBER(BW35),IF(ABS(BW35-[1]QC_indicators!$B$2)>3*[1]QC_indicators!$C$2,"C ratio",IF(ISNUMBER(CA35),IF(ABS(CA35-[1]QC_indicators!$B$1)>3*[1]QC_indicators!$C$1,"DF","no"))),IF(ISNUMBER(CA35),IF(ABS(CA35-[1]QC_indicators!$B$1)>3*[1]QC_indicators!$C$1,"DF","no"))) -> FALSE | FA35: =IF(LEN($CY35)=0,"",IF(AND($CY35<(-0.05),$ES35="C neutral forest and HWP assumption"),"Cneutral paradox",IF(AND($CY35>0.05,$EU35="In-situ only assumption"),"In-situ only paradox","")))
A36: EXPANDING BOUNDARIES: SYSTEMS THINKING IN THE BUILT ENVIRONMENT | B36: Life-cycle assessment; Post-tensioned timber; Reinforced concrete; Costs; Construction time; Greenhouse gas emissions | D36: Cattarinussi, L; Hofstetter, K; Ryffel, R; Zumstein, K; Ioannidou, D; Klippel, M | E36: LIFE CYCLE ASSESSMENT OF A POST-TENSIONED TIMBER FRAME IN COMPARISON TO A REINFORCED CONCRETE FRAME FOR TALL BUILDINGS | F36: This paper summarises a recently conducted project to investigate the sustainability of high-rise timber buildings. In particular, an innovative post-tensioned timber frame structure using glued laminated timber was compared to a functionally equivalent traditional reinforced concrete frame by means of a cradle-to-gate Life Cycle Assessment (LCA). Further, the two structures were compared with regard to costs and time for the construction. The assessment showed that the post-tensioned timber frame structure contributes about 44% less on greenhouse gas emissions compared to the traditional reinforced concrete structure. Additional performed analysis estimating the construction costs and construction time showed the great potential when using timber in comparison to reinforced concrete. | H36: Proceedings Paper | I36: 2016 | J36: 3 | M36: =LEFT($D36,FIND(",",$D36)-1)&"_"&I36&L36 -> Cattarinussi_2016 | N36: no journal | O36: AV | Q36: v5 | CA36: =IFERROR(BZ36/BQ36,"") | CT36: =IF(BI36="Roundwood",$CS36/2,$CS36) -> 0 | CX36: =IFERROR($CW36/$CS36,"") | CZ36: =IFERROR($CW36/$CT36,"") | EP36: =IF(AND(AND(AND(OR($EC36=1,$EB36=1),OR($EH36=1,$EF36=1)),SUM($EA36:$EE36,$EK36)>=3),SUM($EF36:$EJ36)>=2),"Whole sector approach","") | EQ36: =IF(AND(AND(OR($EC36=1,$EB36=1),AND($EH36=0,$EF36=0)),SUM($EA36:$EE36,$EK36)>=3),"Ecosystem approach","") | ER36: =IF(AND(AND(AND($EC36=0,$EB36=0),OR($EH36=1,$EF36=1)),SUM($EG36:$EJ36)>=2),"Technology approach","") | ES36: =IF(AND($EC36+$EB36+$EE36+$EA36+$EF36+$EG36=0,$N36="included"),"C neutral forest and HWP assumption","") | ET36: =IF(AND(AND(AND($EC36+$EB36+$EA36+$EG36>=2,$EF36+$EH36+$EI36>=1),$ED36+$EE36>=1),$N36="included"),"All C pools assumption","") | EU36: =IF(AND($ED36+$EE36+$EI36+$EH36+$EF36=0,$N36="included"),"In-situ only assumption","") | EX36: okVB | EY36: =IF(ISNUMBER(BW36),IF(ABS(BW36-[1]QC_indicators!$B$2)>3*[1]QC_indicators!$C$2,"C ratio",IF(ISNUMBER(CA36),IF(ABS(CA36-[1]QC_indicators!$B$1)>3*[1]QC_indicators!$C$1,"DF","no"))),IF(ISNUMBER(CA36),IF(ABS(CA36-[1]QC_indicators!$B$1)>3*[1]QC_indicators!$C$1,"DF","no"))) -> FALSE | FA36: =IF(LEN($CY36)=0,"",IF(AND($CY36<(-0.05),$ES36="C neutral forest and HWP assumption"),"Cneutral paradox",IF(AND($CY36>0.05,$EU36="In-situ only assumption"),"In-situ only paradox","")))
A37: EXPANDING BOUNDARIES: SYSTEMS THINKING IN THE BUILT ENVIRONMENT | B37: Life-cycle assessment; Post-tensioned timber; Reinforced concrete; Costs; Construction time; Greenhouse gas emissions | D37: Cattarinussi, L; Hofstetter, K; Ryffel, R; Zumstein, K; Ioannidou, D; Klippel, M | E37: LIFE CYCLE ASSESSMENT OF A POST-TENSIONED TIMBER FRAME IN COMPARISON TO A REINFORCED CONCRETE FRAME FOR TALL BUILDINGS | F37: This paper summarises a recently conducted project to investigate the sustainability of high-rise timber buildings. In particular, an innovative post-tensioned timber frame structure using glued laminated timber was compared to a functionally equivalent traditional reinforced concrete frame by means of a cradle-to-gate Life Cycle Assessment (LCA). Further, the two structures were compared with regard to costs and time for the construction. The assessment showed that the post-tensioned timber frame structure contributes about 44% less on greenhouse gas emissions compared to the traditional reinforced concrete structure. Additional performed analysis estimating the construction costs and construction time showed the great potential when using timber in comparison to reinforced concrete. | H37: Proceedings Paper | I37: 2016 | J37: 3 | M37: =LEFT($D37,FIND(",",$D37)-1)&"_"&I37&L37 -> Cattarinussi_2016 | N37: no journal | O37: AV | Q37: v5 | CA37: =IFERROR(BZ37/BQ37,"") | CT37: =IF(BI37="Roundwood",$CS37/2,$CS37) -> 0 | CX37: =IFERROR($CW37/$CS37,"") | CZ37: =IFERROR($CW37/$CT37,"") | EP37: =IF(AND(AND(AND(OR($EC37=1,$EB37=1),OR($EH37=1,$EF37=1)),SUM($EA37:$EE37,$EK37)>=3),SUM($EF37:$EJ37)>=2),"Whole sector approach","") | EQ37: =IF(AND(AND(OR($EC37=1,$EB37=1),AND($EH37=0,$EF37=0)),SUM($EA37:$EE37,$EK37)>=3),"Ecosystem approach","") | ER37: =IF(AND(AND(AND($EC37=0,$EB37=0),OR($EH37=1,$EF37=1)),SUM($EG37:$EJ37)>=2),"Technology approach","") | ES37: =IF(AND($EC37+$EB37+$EE37+$EA37+$EF37+$EG37=0,$N37="included"),"C neutral forest and HWP assumption","") | ET37: =IF(AND(AND(AND($EC37+$EB37+$EA37+$EG37>=2,$EF37+$EH37+$EI37>=1),$ED37+$EE37>=1),$N37="included"),"All C pools assumption","") | EU37: =IF(AND($ED37+$EE37+$EI37+$EH37+$EF37=0,$N37="included"),"In-situ only assumption","") | EY37: =IF(ISNUMBER(BW37),IF(ABS(BW37-[1]QC_indicators!$B$2)>3*[1]QC_indicators!$C$2,"C ratio",IF(ISNUMBER(CA37),IF(ABS(CA37-[1]QC_indicators!$B$1)>3*[1]QC_indicators!$C$1,"DF","no"))),IF(ISNUMBER(CA37),IF(ABS(CA37-[1]QC_indicators!$B$1)>3*[1]QC_indicators!$C$1,"DF","no"))) -> FALSE | FA37: =IF(LEN($CY37)=0,"",IF(AND($CY37<(-0.05),$ES37="C neutral forest and HWP assumption"),"Cneutral paradox",IF(AND($CY37>0.05,$EU37="In-situ only assumption"),"In-situ only paradox","")))
A38: WORLD HERITAGE AND LEGACY: CULTURE, CREATIVITY, CONTAMINATION | B38: LCA; FEM analysis; reinforced concrete structures; timber structures; thermal analysis | C38: CARBON | D38: Chiaia, B; Fantilli, AP; Mancinelli, O | E38: Comparison between the environmental performance of buildings made of reinforced concrete and timber | F38: In order to reduce the environmental impact of the construction industry, the case of natural material (such as timber) is pursued. However, is the use of low-impact materials sufficient to decrease the overall environmental impact of a building? The answer is not trivial, because there are many parameters that affect sustainability, in addition to the unitary environmental impact of the building materials. Through this article, an evaluation of the total CO2 emission in buildings made of reinforced concrete and CLT panels is carried out. The entire life cycle (LCA) of the materials is considered, as well as the CO2 emissions derived from heating and chilling. The relationship between CO2 emissions and building height is also taken into account along with weather conditions. The structures and envelopes of a three - storey family house and of a multi-storey residential building are designed from a structural and thermal point of view, respectively. In order to consider the climatic effects, three locations with very different weather conditions are assumed (i.e. Catania, Turin, Oslo). The carbon footprint of three different structures is considered, namely RC frame made with cast-in-situ structural elements, precast RC panels and timber CLT structure. The quantification of the carbon footprint allows to notice how the overall structural and thermal performances, including the thermal mass, affect the environment performance. | H38: Proceedings Paper | I38: 2019 | J38: 0 | M38: =LEFT($D38,FIND(",",$D38)-1)&"_"&I38&L38 -> Chiaia_2019 | N38: no journal | O38: AV | Q38: v5 | CA38: =IFERROR(BZ38/BQ38,"") | CT38: =IF(BI38="Roundwood",$CS38/2,$CS38) -> 0 | CX38: =IFERROR($CW38/$CS38,"") | CZ38: =IFERROR($CW38/$CT38,"") | EP38: =IF(AND(AND(AND(OR($EC38=1,$EB38=1),OR($EH38=1,$EF38=1)),SUM($EA38:$EE38,$EK38)>=3),SUM($EF38:$EJ38)>=2),"Whole sector approach","") | EQ38: =IF(AND(AND(OR($EC38=1,$EB38=1),AND($EH38=0,$EF38=0)),SUM($EA38:$EE38,$EK38)>=3),"Ecosystem approach","") | ER38: =IF(AND(AND(AND($EC38=0,$EB38=0),OR($EH38=1,$EF38=1)),SUM($EG38:$EJ38)>=2),"Technology approach","") | ES38: =IF(AND($EC38+$EB38+$EE38+$EA38+$EF38+$EG38=0,$N38="included"),"C neutral forest and HWP assumption","") | ET38: =IF(AND(AND(AND($EC38+$EB38+$EA38+$EG38>=2,$EF38+$EH38+$EI38>=1),$ED38+$EE38>=1),$N38="included"),"All C pools assumption","") | EU38: =IF(AND($ED38+$EE38+$EI38+$EH38+$EF38=0,$N38="included"),"In-situ only assumption","") | EX38: okVB | EY38: =IF(ISNUMBER(BW38),IF(ABS(BW38-[1]QC_indicators!$B$2)>3*[1]QC_indicators!$C$2,"C ratio",IF(ISNUMBER(CA38),IF(ABS(CA38-[1]QC_indicators!$B$1)>3*[1]QC_indicators!$C$1,"DF","no"))),IF(ISNUMBER(CA38),IF(ABS(CA38-[1]QC_indicators!$B$1)>3*[1]QC_indicators!$C$1,"DF","no"))) -> FALSE | FA38: =IF(LEN($CY38)=0,"",IF(AND($CY38<(-0.05),$ES38="C neutral forest and HWP assumption"),"Cneutral paradox",IF(AND($CY38>0.05,$EU38="In-situ only assumption"),"In-situ only paradox","")))
A39: WORLD HERITAGE AND LEGACY: CULTURE, CREATIVITY, CONTAMINATION | B39: LCA; FEM analysis; reinforced concrete structures; timber structures; thermal analysis | C39: CARBON | D39: Chiaia, B; Fantilli, AP; Mancinelli, O | E39: Comparison between the environmental performance of buildings made of reinforced concrete and timber | F39: In order to reduce the environmental impact of the construction industry, the case of natural material (such as timber) is pursued. However, is the use of low-impact materials sufficient to decrease the overall environmental impact of a building? The answer is not trivial, because there are many parameters that affect sustainability, in addition to the unitary environmental impact of the building materials. Through this article, an evaluation of the total CO2 emission in buildings made of reinforced concrete and CLT panels is carried out. The entire life cycle (LCA) of the materials is considered, as well as the CO2 emissions derived from heating and chilling. The relationship between CO2 emissions and building height is also taken into account along with weather conditions. The structures and envelopes of a three - storey family house and of a multi-storey residential building are designed from a structural and thermal point of view, respectively. In order to consider the climatic effects, three locations with very different weather conditions are assumed (i.e. Catania, Turin, Oslo). The carbon footprint of three different structures is considered, namely RC frame made with cast-in-situ structural elements, precast RC panels and timber CLT structure. The quantification of the carbon footprint allows to notice how the overall structural and thermal performances, including the thermal mass, affect the environment performance. | H39: Proceedings Paper | I39: 2019 | J39: 0 | M39: =LEFT($D39,FIND(",",$D39)-1)&"_"&I39&L39 -> Chiaia_2019 | N39: no journal | O39: AV | Q39: v5 | CA39: =IFERROR(BZ39/BQ39,"") | CT39: =IF(BI39="Roundwood",$CS39/2,$CS39) -> 0 | CX39: =IFERROR($CW39/$CS39,"") | CZ39: =IFERROR($CW39/$CT39,"") | EP39: =IF(AND(AND(AND(OR($EC39=1,$EB39=1),OR($EH39=1,$EF39=1)),SUM($EA39:$EE39,$EK39)>=3),SUM($EF39:$EJ39)>=2),"Whole sector approach","") | EQ39: =IF(AND(AND(OR($EC39=1,$EB39=1),AND($EH39=0,$EF39=0)),SUM($EA39:$EE39,$EK39)>=3),"Ecosystem approach","") | ER39: =IF(AND(AND(AND($EC39=0,$EB39=0),OR($EH39=1,$EF39=1)),SUM($EG39:$EJ39)>=2),"Technology approach","") | ES39: =IF(AND($EC39+$EB39+$EE39+$EA39+$EF39+$EG39=0,$N39="included"),"C neutral forest and HWP assumption","") | ET39: =IF(AND(AND(AND($EC39+$EB39+$EA39+$EG39>=2,$EF39+$EH39+$EI39>=1),$ED39+$EE39>=1),$N39="included"),"All C pools assumption","") | EU39: =IF(AND($ED39+$EE39+$EI39+$EH39+$EF39=0,$N39="included"),"In-situ only assumption","") | EY39: =IF(ISNUMBER(BW39),IF(ABS(BW39-[1]QC_indicators!$B$2)>3*[1]QC_indicators!$C$2,"C ratio",IF(ISNUMBER(CA39),IF(ABS(CA39-[1]QC_indicators!$B$1)>3*[1]QC_indicators!$C$1,"DF","no"))),IF(ISNUMBER(CA39),IF(ABS(CA39-[1]QC_indicators!$B$1)>3*[1]QC_indicators!$C$1,"DF","no"))) -> FALSE | FA39: =IF(LEN($CY39)=0,"",IF(AND($CY39<(-0.05),$ES39="C neutral forest and HWP assumption"),"Cneutral paradox",IF(AND($CY39>0.05,$EU39="In-situ only assumption"),"In-situ only paradox","")))
A40: LIFE-CYCLE ANALYSIS AND ASSESSMENT IN CIVIL ENGINEERING: TOWARDS AN INTEGRATED VISION | D40: De Wolf, C; Davies, D | E40: Benchmarking embodied carbon in structural materials | F40: To inspire structural engineers to contribute towards the vision of zero carbon buildings by 2050, this paper discusses the Structural Engineers 2050 Commitment. To participate, structural engineers are encouraged to share their progress with data on material quantities and embodied carbon in their structures within the database of embodied Quantity outputs (deQo). The literature reviews the variations in carbon emissions (Embodied Carbon Coefficients expressed in kg of CO2 equivalent or CO(2)e per kg of material) for common structural materials. These variations illustrate why it is necessary to collect data on material quantities in buildings rather than the end result in terms of carbon emissions of building structures: once the ECCs of materials become more accurate, the collected material quantities can be used to update the Global Warming Potential (expressed in kg of CO(2)e per m(2) of floor area or another functional unit) of the building structure. This is needed to create benchmarks of embodied carbon in building structures. To align methodologies for evaluating embodied carbon in industry practice and in deQo, an LCA specification guide is being published by the Carbon Leadership Forum. From the presented benchmarking efforts, strategies to lower embodied carbon are derived: structural optimization and low-carbon material choices. Compared to conventional practices in concrete, steel and timber structures, these strategies are applied to project case studies provided by Magnusson Klemencic Associates. In particular, new lower carbon construction materials under development are explored to illustrate the potential reductions toward the goal of zero carbon buildings by 2050. | H40: Proceedings Paper | I40: 2019 | J40: 0 | M40: =LEFT($D40,FIND(",",$D40)-1)&"_"&I40&L40 -> De Wolf_2019 | N40: no journal | O40: AV | Q40: v5 | CA40: =IFERROR(BZ40/BQ40,"") | CT40: =IF(BI40="Roundwood",$CS40/2,$CS40) -> 0 | CX40: =IFERROR($CW40/$CS40,"") | CZ40: =IFERROR($CW40/$CT40,"") | EP40: =IF(AND(AND(AND(OR($EC40=1,$EB40=1),OR($EH40=1,$EF40=1)),SUM($EA40:$EE40,$EK40)>=3),SUM($EF40:$EJ40)>=2),"Whole sector approach","") | EQ40: =IF(AND(AND(OR($EC40=1,$EB40=1),AND($EH40=0,$EF40=0)),SUM($EA40:$EE40,$EK40)>=3),"Ecosystem approach","") | ER40: =IF(AND(AND(AND($EC40=0,$EB40=0),OR($EH40=1,$EF40=1)),SUM($EG40:$EJ40)>=2),"Technology approach","") | ES40: =IF(AND($EC40+$EB40+$EE40+$EA40+$EF40+$EG40=0,$N40="included"),"C neutral forest and HWP assumption","") | ET40: =IF(AND(AND(AND($EC40+$EB40+$EA40+$EG40>=2,$EF40+$EH40+$EI40>=1),$ED40+$EE40>=1),$N40="included"),"All C pools assumption","") | EU40: =IF(AND($ED40+$EE40+$EI40+$EH40+$EF40=0,$N40="included"),"In-situ only assumption","") | EX40: okVB | EY40: =IF(ISNUMBER(BW40),IF(ABS(BW40-[1]QC_indicators!$B$2)>3*[1]QC_indicators!$C$2,"C ratio",IF(ISNUMBER(CA40),IF(ABS(CA40-[1]QC_indicators!$B$1)>3*[1]QC_indicators!$C$1,"DF","no"))),IF(ISNUMBER(CA40),IF(ABS(CA40-[1]QC_indicators!$B$1)>3*[1]QC_indicators!$C$1,"DF","no"))) -> FALSE | FA40: =IF(LEN($CY40)=0,"",IF(AND($CY40<(-0.05),$ES40="C neutral forest and HWP assumption"),"Cneutral paradox",IF(AND($CY40>0.05,$EU40="In-situ only assumption"),"In-situ only paradox","")))
A41: LIFE-CYCLE ANALYSIS AND ASSESSMENT IN CIVIL ENGINEERING: TOWARDS AN INTEGRATED VISION | D41: De Wolf, C; Davies, D | E41: Benchmarking embodied carbon in structural materials | F41: To inspire structural engineers to contribute towards the vision of zero carbon buildings by 2050, this paper discusses the Structural Engineers 2050 Commitment. To participate, structural engineers are encouraged to share their progress with data on material quantities and embodied carbon in their structures within the database of embodied Quantity outputs (deQo). The literature reviews the variations in carbon emissions (Embodied Carbon Coefficients expressed in kg of CO2 equivalent or CO(2)e per kg of material) for common structural materials. These variations illustrate why it is necessary to collect data on material quantities in buildings rather than the end result in terms of carbon emissions of building structures: once the ECCs of materials become more accurate, the collected material quantities can be used to update the Global Warming Potential (expressed in kg of CO(2)e per m(2) of floor area or another functional unit) of the building structure. This is needed to create benchmarks of embodied carbon in building structures. To align methodologies for evaluating embodied carbon in industry practice and in deQo, an LCA specification guide is being published by the Carbon Leadership Forum. From the presented benchmarking efforts, strategies to lower embodied carbon are derived: structural optimization and low-carbon material choices. Compared to conventional practices in concrete, steel and timber structures, these strategies are applied to project case studies provided by Magnusson Klemencic Associates. In particular, new lower carbon construction materials under development are explored to illustrate the potential reductions toward the goal of zero carbon buildings by 2050. | H41: Proceedings Paper | I41: 2019 | J41: 0 | M41: =LEFT($D41,FIND(",",$D41)-1)&"_"&I41&L41 -> De Wolf_2019 | N41: no journal | O41: AV | Q41: v5 | CA41: =IFERROR(BZ41/BQ41,"") | CT41: =IF(BI41="Roundwood",$CS41/2,$CS41) -> 0 | CX41: =IFERROR($CW41/$CS41,"") | CZ41: =IFERROR($CW41/$CT41,"") | EP41: =IF(AND(AND(AND(OR($EC41=1,$EB41=1),OR($EH41=1,$EF41=1)),SUM($EA41:$EE41,$EK41)>=3),SUM($EF41:$EJ41)>=2),"Whole sector approach","") | EQ41: =IF(AND(AND(OR($EC41=1,$EB41=1),AND($EH41=0,$EF41=0)),SUM($EA41:$EE41,$EK41)>=3),"Ecosystem approach","") | ER41: =IF(AND(AND(AND($EC41=0,$EB41=0),OR($EH41=1,$EF41=1)),SUM($EG41:$EJ41)>=2),"Technology approach","") | ES41: =IF(AND($EC41+$EB41+$EE41+$EA41+$EF41+$EG41=0,$N41="included"),"C neutral forest and HWP assumption","") | ET41: =IF(AND(AND(AND($EC41+$EB41+$EA41+$EG41>=2,$EF41+$EH41+$EI41>=1),$ED41+$EE41>=1),$N41="included"),"All C pools assumption","") | EU41: =IF(AND($ED41+$EE41+$EI41+$EH41+$EF41=0,$N41="included"),"In-situ only assumption","") | EY41: =IF(ISNUMBER(BW41),IF(ABS(BW41-[1]QC_indicators!$B$2)>3*[1]QC_indicators!$C$2,"C ratio",IF(ISNUMBER(CA41),IF(ABS(CA41-[1]QC_indicators!$B$1)>3*[1]QC_indicators!$C$1,"DF","no"))),IF(ISNUMBER(CA41),IF(ABS(CA41-[1]QC_indicators!$B$1)>3*[1]QC_indicators!$C$1,"DF","no"))) -> FALSE | FA41: =IF(LEN($CY41)=0,"",IF(AND($CY41<(-0.05),$ES41="C neutral forest and HWP assumption"),"Cneutral paradox",IF(AND($CY41>0.05,$EU41="In-situ only assumption"),"In-situ only paradox","")))
A42: INNOVATIVE SOLUTIONS FOR ENERGY TRANSITIONS | B42: Post-use building material; end-of-life; primary energy; carbon dioxide emissions; recyclig | C42: CYCLE ASSESSMENT; WOOD; CONCRETE; CONSTRUCTION; IMPACTS | D42: Dodoo, A; Gustaysson, L; Tettey, UYA | E42: Effects of end-of-life management options for materials on primary energy and greenhouse gas balances of building systems | F42: In this study we have analysed the life cycle primary energy and greenhouse gas (GHG) balances of concrete-frame and timber frame multi-storey building alternatives, designed to meet the current Swedish building code, considering different end-of-life scenarios. The scenarios include recycling of concrete and steel, cascading by recycling of wood into particle board and energy recovery at the end-of-life of the board, energy recovery of wood by combustion, and landfilling of wood with and without landfill gas (LFG) recovery. The energy recovered is assumed to replace fossil coal or gas. Our analysis accounts for energy and GHG flows in the production and end-of-life phases. We estimate the GHG emission changes achieved per unit of difference in finished wood in buildings or in harvest forest biomass between the timber buildings and the concrete building. The results show that the timber building systems give significantly lower life cycle primary energy balances than the concrete building system for all the end-of-life options. The concrete building system gives higher life cycle GHG balances than the timber alternatives for all the end-of-life options, except when wood is landfill without LFG recovery. The end-of-life primary energy and GHG benefit of wood materials is most significant for energy recovery while the benefit of cascading is low. However, replacing fossil gas instead of fossil coal significantly reduce the carbon benefits of the timber alternatives. The benefits of recycling steel and concrete are small. This study shows that end-of-life options for building materials can offer opportunities to reduce energy use and GHG emissions in the built environment. (C) 2019 The Authors. Published by Elsevier Ltd. | H42: Proceedings Paper | I42: 2019 | J42: 1 | K42: 10.1016/j.egypro.2019.01.802 | M42: =LEFT($D42,FIND(",",$D42)-1)&"_"&I42&L42 -> Dodoo_2019 | N42: no journal | O42: AV | Q42: v5 | CA42: =IFERROR(BZ42/BQ42,"") | CT42: =IF(BI42="Roundwood",$CS42/2,$CS42) -> 0 | CX42: =IFERROR($CW42/$CS42,"") | CZ42: =IFERROR($CW42/$CT42,"") | EP42: =IF(AND(AND(AND(OR($EC42=1,$EB42=1),OR($EH42=1,$EF42=1)),SUM($EA42:$EE42,$EK42)>=3),SUM($EF42:$EJ42)>=2),"Whole sector approach","") | EQ42: =IF(AND(AND(OR($EC42=1,$EB42=1),AND($EH42=0,$EF42=0)),SUM($EA42:$EE42,$EK42)>=3),"Ecosystem approach","") | ER42: =IF(AND(AND(AND($EC42=0,$EB42=0),OR($EH42=1,$EF42=1)),SUM($EG42:$EJ42)>=2),"Technology approach","") | ES42: =IF(AND($EC42+$EB42+$EE42+$EA42+$EF42+$EG42=0,$N42="included"),"C neutral forest and HWP assumption","") | ET42: =IF(AND(AND(AND($EC42+$EB42+$EA42+$EG42>=2,$EF42+$EH42+$EI42>=1),$ED42+$EE42>=1),$N42="included"),"All C pools assumption","") | EU42: =IF(AND($ED42+$EE42+$EI42+$EH42+$EF42=0,$N42="included"),"In-situ only assumption","") | EX42: okVB | EY42: =IF(ISNUMBER(BW42),IF(ABS(BW42-[1]QC_indicators!$B$2)>3*[1]QC_indicators!$C$2,"C ratio",IF(ISNUMBER(CA42),IF(ABS(CA42-[1]QC_indicators!$B$1)>3*[1]QC_indicators!$C$1,"DF","no"))),IF(ISNUMBER(CA42),IF(ABS(CA42-[1]QC_indicators!$B$1)>3*[1]QC_indicators!$C$1,"DF","no"))) -> FALSE | FA42: =IF(LEN($CY42)=0,"",IF(AND($CY42<(-0.05),$ES42="C neutral forest and HWP assumption"),"Cneutral paradox",IF(AND($CY42>0.05,$EU42="In-situ only assumption"),"In-situ only paradox","")))
A43: INNOVATIVE SOLUTIONS FOR ENERGY TRANSITIONS | B43: Post-use building material; end-of-life; primary energy; carbon dioxide emissions; recyclig | C43: CYCLE ASSESSMENT; WOOD; CONCRETE; CONSTRUCTION; IMPACTS | D43: Dodoo, A; Gustaysson, L; Tettey, UYA | E43: Effects of end-of-life management options for materials on primary energy and greenhouse gas balances of building systems | F43: In this study we have analysed the life cycle primary energy and greenhouse gas (GHG) balances of concrete-frame and timber frame multi-storey building alternatives, designed to meet the current Swedish building code, considering different end-of-life scenarios. The scenarios include recycling of concrete and steel, cascading by recycling of wood into particle board and energy recovery at the end-of-life of the board, energy recovery of wood by combustion, and landfilling of wood with and without landfill gas (LFG) recovery. The energy recovered is assumed to replace fossil coal or gas. Our analysis accounts for energy and GHG flows in the production and end-of-life phases. We estimate the GHG emission changes achieved per unit of difference in finished wood in buildings or in harvest forest biomass between the timber buildings and the concrete building. The results show that the timber building systems give significantly lower life cycle primary energy balances than the concrete building system for all the end-of-life options. The concrete building system gives higher life cycle GHG balances than the timber alternatives for all the end-of-life options, except when wood is landfill without LFG recovery. The end-of-life primary energy and GHG benefit of wood materials is most significant for energy recovery while the benefit of cascading is low. However, replacing fossil gas instead of fossil coal significantly reduce the carbon benefits of the timber alternatives. The benefits of recycling steel and concrete are small. This study shows that end-of-life options for building materials can offer opportunities to reduce energy use and GHG emissions in the built environment. (C) 2019 The Authors. Published by Elsevier Ltd. | H43: Proceedings Paper | I43: 2019 | J43: 1 | K43: 10.1016/j.egypro.2019.01.802 | M43: =LEFT($D43,FIND(",",$D43)-1)&"_"&I43&L43 -> Dodoo_2019 | N43: no journal | O43: AV | Q43: v5 | CA43: =IFERROR(BZ43/BQ43,"") | CT43: =IF(BI43="Roundwood",$CS43/2,$CS43) -> 0 | CX43: =IFERROR($CW43/$CS43,"") | CZ43: =IFERROR($CW43/$CT43,"") | EP43: =IF(AND(AND(AND(OR($EC43=1,$EB43=1),OR($EH43=1,$EF43=1)),SUM($EA43:$EE43,$EK43)>=3),SUM($EF43:$EJ43)>=2),"Whole sector approach","") | EQ43: =IF(AND(AND(OR($EC43=1,$EB43=1),AND($EH43=0,$EF43=0)),SUM($EA43:$EE43,$EK43)>=3),"Ecosystem approach","") | ER43: =IF(AND(AND(AND($EC43=0,$EB43=0),OR($EH43=1,$EF43=1)),SUM($EG43:$EJ43)>=2),"Technology approach","") | ES43: =IF(AND($EC43+$EB43+$EE43+$EA43+$EF43+$EG43=0,$N43="included"),"C neutral forest and HWP assumption","") | ET43: =IF(AND(AND(AND($EC43+$EB43+$EA43+$EG43>=2,$EF43+$EH43+$EI43>=1),$ED43+$EE43>=1),$N43="included"),"All C pools assumption","") | EU43: =IF(AND($ED43+$EE43+$EI43+$EH43+$EF43=0,$N43="included"),"In-situ only assumption","") | EY43: =IF(ISNUMBER(BW43),IF(ABS(BW43-[1]QC_indicators!$B$2)>3*[1]QC_indicators!$C$2,"C ratio",IF(ISNUMBER(CA43),IF(ABS(CA43-[1]QC_indicators!$B$1)>3*[1]QC_indicators!$C$1,"DF","no"))),IF(ISNUMBER(CA43),IF(ABS(CA43-[1]QC_indicators!$B$1)>3*[1]QC_indicators!$C$1,"DF","no"))) -> FALSE | FA43: =IF(LEN($CY43)=0,"",IF(AND($CY43<(-0.05),$ES43="C neutral forest and HWP assumption"),"Cneutral paradox",IF(AND($CY43>0.05,$EU43="In-situ only assumption"),"In-situ only paradox","")))
A44: SUSTAINABLE BUILT ENVIRONMENT D-A-CH CONFERENCE 2019 (SBE19 GRAZ) | D44: Forster, EJ; Healey, JR; Dymond, CC; Newman, G; Davies, G; Styles, D | E44: Linking construction timber carbon storage with land use and forestry management practices | F44: Consequential life cycle assessment was applied to forestry systems to evaluate the environmental balance of expanding forestry onto marginal agricultural land to supply more timber for the built environment, accounting for land use effects and product substitution. Forestry expansion to supply timber buildings could mitigate UK greenhouse gas (GHG) emissions by 2.4 Gg CO2 eq. per ha of forest over 100 years, though net mitigation could be halved if beef production were displaced to Brazil. Forest thinning increases wood yields and percentage conversion of harvested wood to construction sawnwood, resulting in 5% greater net GHG mitigation compared with unthinned systems. Optimising the environmental sustainability of construction timber value chains in a circular, bio-based economy will require holistic accounting of land use (change), forestry management and complex flows of wood. | G44: IOP Conf. Ser. Earth Envir. Sci. | H44: Proceedings Paper | I44: 2019 | J44: 2 | K44: 10.1088/1755-1315/323/1/012142 | M44: =LEFT($D44,FIND(",",$D44)-1)&"_"&I44&L44 -> Forster_2019 | N44: no journal | O44: SC | P44: AV | Q44: v6 | CA44: =IFERROR(BZ44/BQ44,"") | CT44: =IF(BI44="Roundwood",$CS44/2,$CS44) -> 0 | CX44: =IFERROR($CW44/$CS44,"") | CZ44: =IFERROR($CW44/$CT44,"") | EP44: =IF(AND(AND(AND(OR($EC44=1,$EB44=1),OR($EH44=1,$EF44=1)),SUM($EA44:$EE44,$EK44)>=3),SUM($EF44:$EJ44)>=2),"Whole sector approach","") | EQ44: =IF(AND(AND(OR($EC44=1,$EB44=1),AND($EH44=0,$EF44=0)),SUM($EA44:$EE44,$EK44)>=3),"Ecosystem approach","") | ER44: =IF(AND(AND(AND($EC44=0,$EB44=0),OR($EH44=1,$EF44=1)),SUM($EG44:$EJ44)>=2),"Technology approach","") | ES44: =IF(AND($EC44+$EB44+$EE44+$EA44+$EF44+$EG44=0,$N44="included"),"C neutral forest and HWP assumption","") | ET44: =IF(AND(AND(AND($EC44+$EB44+$EA44+$EG44>=2,$EF44+$EH44+$EI44>=1),$ED44+$EE44>=1),$N44="included"),"All C pools assumption","") | EU44: =IF(AND($ED44+$EE44+$EI44+$EH44+$EF44=0,$N44="included"),"In-situ only assumption","") | EY44: =IF(ISNUMBER(BW44),IF(ABS(BW44-[1]QC_indicators!$B$2)>3*[1]QC_indicators!$C$2,"C ratio",IF(ISNUMBER(CA44),IF(ABS(CA44-[1]QC_indicators!$B$1)>3*[1]QC_indicators!$C$1,"DF","no"))),IF(ISNUMBER(CA44),IF(ABS(CA44-[1]QC_indicators!$B$1)>3*[1]QC_indicators!$C$1,"DF","no"))) -> FALSE | FA44: =IF(LEN($CY44)=0,"",IF(AND($CY44<(-0.05),$ES44="C neutral forest and HWP assumption"),"Cneutral paradox",IF(AND($CY44>0.05,$EU44="In-situ only assumption"),"In-situ only paradox","")))
A45: PAPERS OF THE 25TH EUROPEAN BIOMASS CONFERENCE | B45: life cycle assessment; wood-based bioeconomy; integrated industrial production networks; lignocellulosic biorefineries | D45: Hildebrandt, J; Budzinski, M; Thran, D; Bezama, A | E45: ASSESSING A BIOECONOMY NETWORK FROM AN INTEGRATED LIFE CYCLE PERSPECTIVE | F45: The production of wood fibres, bio-based polymers and engineered wood products within integrated industrial production networks can be organized by industrial decision makers in future production planning with a varying degree in the integration of cross company supply and conversion chains. For instance, the supply with wood fibres in future composite and wood panel production lines can rely on individual or cooperative operation of refinery plants. Also, the feedstock of lignocellulosic biorefineries can primarily be mobilized from raw wood resources or can be sourced from saw mill by-products and/or secondary wood resources. Finally, a major option for coupled use and integration of value added chains between biorefineries and wood manufacturing industries is the production of intermediary and auxiliary materials such as bio-based resins and adhesives for glue-laminated and cross-laminated timber products. Considering these scenarios of varying intensity in coupled use and cascade use of wood resources a baseline scenario was developed and assessed in this study, which serves as a basis for further LCA studies on extended scenarios. If these horizontal and vertical integration options really contribute to favourable reduction of environmental impacts along the bio-based value chains in bioeconomy regions, thereby remains a major question for further in-depth assessments. A life cycle-based approach has been used to model and evaluate the technological processes that take part in wood-based bio-polymer and wood processing supply chains. This work analyses the negative environmental impacts of a future wood-based bioeconomy network and compares its impacts with those of a traditional fossil-based production system. Results show that for the future bioeconomy system for seven out of 11 impact categories a relative advantage between 25 % to 130% of the initial impacts of fossil-based counterparts is attainable. As expected the global warming potential and the abiotic depletion potentials are building the top group with 130 % and 70 % respectively. The inventory analysis shows that the integration of regional and cross company supply chains and the minimization of fossil-based additives and auxiliaries and utility service installations offer further options for leveraging optimization scenarios. | H45: Proceedings Paper | I45: 2017 | J45: 1 | L45: b | M45: =LEFT($D45,FIND(",",$D45)-1)&"_"&I45&L45 -> Hildebrandt_2017b | N45: no journal | O45: SC | Q45: v5 | CA45: =IFERROR(BZ45/BQ45,"") | CT45: =IF(BI45="Roundwood",$CS45/2,$CS45) -> 0 | CX45: =IFERROR($CW45/$CS45,"") | CZ45: =IFERROR($CW45/$CT45,"") | EP45: =IF(AND(AND(AND(OR($EC45=1,$EB45=1),OR($EH45=1,$EF45=1)),SUM($EA45:$EE45,$EK45)>=3),SUM($EF45:$EJ45)>=2),"Whole sector approach","") | EQ45: =IF(AND(AND(OR($EC45=1,$EB45=1),AND($EH45=0,$EF45=0)),SUM($EA45:$EE45,$EK45)>=3),"Ecosystem approach","") | ER45: =IF(AND(AND(AND($EC45=0,$EB45=0),OR($EH45=1,$EF45=1)),SUM($EG45:$EJ45)>=2),"Technology approach","") | ES45: =IF(AND($EC45+$EB45+$EE45+$EA45+$EF45+$EG45=0,$N45="included"),"C neutral forest and HWP assumption","") | ET45: =IF(AND(AND(AND($EC45+$EB45+$EA45+$EG45>=2,$EF45+$EH45+$EI45>=1),$ED45+$EE45>=1),$N45="included"),"All C pools assumption","") | EU45: =IF(AND($ED45+$EE45+$EI45+$EH45+$EF45=0,$N45="included"),"In-situ only assumption","") | EX45: okVB | EY45: =IF(ISNUMBER(BW45),IF(ABS(BW45-[1]QC_indicators!$B$2)>3*[1]QC_indicators!$C$2,"C ratio",IF(ISNUMBER(CA45),IF(ABS(CA45-[1]QC_indicators!$B$1)>3*[1]QC_indicators!$C$1,"DF","no"))),IF(ISNUMBER(CA45),IF(ABS(CA45-[1]QC_indicators!$B$1)>3*[1]QC_indicators!$C$1,"DF","no"))) -> FALSE | FA45: =IF(LEN($CY45)=0,"",IF(AND($CY45<(-0.05),$ES45="C neutral forest and HWP assumption"),"Cneutral paradox",IF(AND($CY45>0.05,$EU45="In-situ only assumption"),"In-situ only paradox","")))
A46: 27TH EUROPEAN SYMPOSIUM ON COMPUTER AIDED PROCESS ENGINEERING, PT B | B46: Biomass; Bioenergy; Cogeneration; Multigeneration; Renewable resources | D46: Kanematsu, Y; Oosawa, K; Okubo, T; Kikuchi, Y | E46: A design of rural energy system by industrial symbiosis considering availability of regional resources | F46: This paper performed the design of rural energy system by industrial symbiosis considering long-term availability of forest resources, As for the case examples, alternatives of energy system in Tanegashima, a remote island in Japan, were examined, where two types of combined heating and power (CHP) were designed. In the first option, bagasse-based CHP at the cane sugar mill was enhanced to use woody biomass as additional fuel and generate energy for district heating and cooling (DHC). In another option, small scale biomass-CHP was designed for DHC in city center. Both options were mathematically modeled and simulated for examining the resource requirements and life cycle greenhouse gas emission. A constraint on total availability of woody biomass was taken into account, which was calculated through a simulation on forestry. The effect of total timber availability and allocation to the two CHP systems was quantified. A design of rural energy system by industrial symbiosis can be facilitated by simulation-based analysis to visualize the impacts of such energy networks among involved multiple players such as industry, residential, and commercial sectors, | H46: Proceedings Paper | I46: 2017 | J46: 1 | K46: 10.1016/B978-0-444-63965-3.50333-0 | M46: =LEFT($D46,FIND(",",$D46)-1)&"_"&I46&L46 -> Kanematsu_2017 | N46: no journal | O46: SC | Q46: v5 | CA46: =IFERROR(BZ46/BQ46,"") | CT46: =IF(BI46="Roundwood",$CS46/2,$CS46) -> 0 | CX46: =IFERROR($CW46/$CS46,"") | CZ46: =IFERROR($CW46/$CT46,"") | EP46: =IF(AND(AND(AND(OR($EC46=1,$EB46=1),OR($EH46=1,$EF46=1)),SUM($EA46:$EE46,$EK46)>=3),SUM($EF46:$EJ46)>=2),"Whole sector approach","") | EQ46: =IF(AND(AND(OR($EC46=1,$EB46=1),AND($EH46=0,$EF46=0)),SUM($EA46:$EE46,$EK46)>=3),"Ecosystem approach","") | ER46: =IF(AND(AND(AND($EC46=0,$EB46=0),OR($EH46=1,$EF46=1)),SUM($EG46:$EJ46)>=2),"Technology approach","") | ES46: =IF(AND($EC46+$EB46+$EE46+$EA46+$EF46+$EG46=0,$N46="included"),"C neutral forest and HWP assumption","") | ET46: =IF(AND(AND(AND($EC46+$EB46+$EA46+$EG46>=2,$EF46+$EH46+$EI46>=1),$ED46+$EE46>=1),$N46="included"),"All C pools assumption","") | EU46: =IF(AND($ED46+$EE46+$EI46+$EH46+$EF46=0,$N46="included"),"In-situ only assumption","") | EX46: changed_to_nojournal | EY46: =IF(ISNUMBER(BW46),IF(ABS(BW46-[1]QC_indicators!$B$2)>3*[1]QC_indicators!$C$2,"C ratio",IF(ISNUMBER(CA46),IF(ABS(CA46-[1]QC_indicators!$B$1)>3*[1]QC_indicators!$C$1,"DF","no"))),IF(ISNUMBER(CA46),IF(ABS(CA46-[1]QC_indicators!$B$1)>3*[1]QC_indicators!$C$1,"DF","no"))) -> FALSE | FA46: =IF(LEN($CY46)=0,"",IF(AND($CY46<(-0.05),$ES46="C neutral forest and HWP assumption"),"Cneutral paradox",IF(AND($CY46>0.05,$EU46="In-situ only assumption"),"In-situ only paradox","")))
A47: 4TH WORLD MULTIDISCIPLINARY CIVIL ENGINEERING-ARCHITECTURE-URBAN PLANNING SYMPOSIUM - WMCAUS | D47: Karas, A; Idem, R | E47: The Dilemmas of Choosing a Suitable Technology for Low Energy and Passive Houses in the Context of their Overheating Issues | F47: In compliance with European Union directives, numerous countries are introducing increasingly stricter legal limits on the estimated energy consumption of newly designed residential buildings. However, the fact, that regulations and designers' efforts are focused on decreasing energy consumption (and consequently carbon dioxide emissions) only at the post-occupancy stage, may lead to a significant increase in the carbon footprint of the buildings during their entire life cycle. A frequent criticism levelled at low-energy and passive buildings is that they are susceptible to the phenomenon of overheating. The reduction of overheating through the choice of massive technologies, materials with high thermal capacity as well as a high heat dispersion coefficient, stands in opposition to the requirement to choose the technologies that ensure a low ecological footprint (i.e. timber frame technologies). The development of a tool facilitating decision making in this issue seems to be a challenge. Life Cycle Assessment (LCA) is a well-known, optimal method for forecasting buildings' carbon footprint, however, it is an expensive and time-consuming method. Life Cycle Assessment is a method dedicated to large investments. In practice, such analysis are not carried out for residential buildings. The purpose of this paper is to analyse the foregoing problem on the example of detached single-family houses and to propose a method and tool that can assist architectural design in this regard. | H47: Proceedings Paper | I47: 2019 | J47: 0 | K47: 10.1088/1757-899X/603/4/042024 | M47: =LEFT($D47,FIND(",",$D47)-1)&"_"&I47&L47 -> Karas_2019 | N47: no journal | O47: SC | P47: AV | Q47: v6 | CA47: =IFERROR(BZ47/BQ47,"") | CT47: =IF(BI47="Roundwood",$CS47/2,$CS47) -> 0 | CX47: =IFERROR($CW47/$CS47,"") | CZ47: =IFERROR($CW47/$CT47,"") | EP47: =IF(AND(AND(AND(OR($EC47=1,$EB47=1),OR($EH47=1,$EF47=1)),SUM($EA47:$EE47,$EK47)>=3),SUM($EF47:$EJ47)>=2),"Whole sector approach","") | EQ47: =IF(AND(AND(OR($EC47=1,$EB47=1),AND($EH47=0,$EF47=0)),SUM($EA47:$EE47,$EK47)>=3),"Ecosystem approach","") | ER47: =IF(AND(AND(AND($EC47=0,$EB47=0),OR($EH47=1,$EF47=1)),SUM($EG47:$EJ47)>=2),"Technology approach","") | ES47: =IF(AND($EC47+$EB47+$EE47+$EA47+$EF47+$EG47=0,$N47="included"),"C neutral forest and HWP assumption","") | ET47: =IF(AND(AND(AND($EC47+$EB47+$EA47+$EG47>=2,$EF47+$EH47+$EI47>=1),$ED47+$EE47>=1),$N47="included"),"All C pools assumption","") | EU47: =IF(AND($ED47+$EE47+$EI47+$EH47+$EF47=0,$N47="included"),"In-situ only assumption","") | EY47: =IF(ISNUMBER(BW47),IF(ABS(BW47-[1]QC_indicators!$B$2)>3*[1]QC_indicators!$C$2,"C ratio",IF(ISNUMBER(CA47),IF(ABS(CA47-[1]QC_indicators!$B$1)>3*[1]QC_indicators!$C$1,"DF","no"))),IF(ISNUMBER(CA47),IF(ABS(CA47-[1]QC_indicators!$B$1)>3*[1]QC_indicators!$C$1,"DF","no"))) -> FALSE | FA47: =IF(LEN($CY47)=0,"",IF(AND($CY47<(-0.05),$ES47="C neutral forest and HWP assumption"),"Cneutral paradox",IF(AND($CY47>0.05,$EU47="In-situ only assumption"),"In-situ only paradox","")))
A48: 19TH INTERNATIONAL CONGRESS ON MODELLING AND SIMULATION (MODSIM2011) | B48: Intertemporal general equilibrium; optimal forest management; mixed complementarity | D48: Lennox, JA; Turner, JA; Daigneault, A; Jhunjhnuwala, K | E48: Global forestry and land use change dynamics in intertemporal general equilibrium | F48: Management of forests for timber and other values, deforestation and afforestation are subjects of major policy interest, with important implications for climate change and food security inter alia. To robustly quantify impacts of policies on forests and on land use generally requires accounting for economic interactions not only between agricultural and forestry, but also energy and other sectors. At larger scales, these interactions may include linkages via international trade. General equilibrium models are well suited to capture such interactions; however, adequate representation of land use change and forestry in these models remains challenging. We present a dynamic bottom-up representation of forestry within a top-down intertemporal general equilibrium model that is formulated as a mixed complementarity problem (Mathiesen, 1985; Lau et al., 2002). Intertemporally optimal management of forests and optimal harvest ages are determined endogenously within the model, bringing into an intertemporal general equilibrium farmework features hitherto limited to partial equilibrium models (e. g. the Global Timber Model Sedjo and Lyon, 1990; Sohngen et al., 1999) or recursive dynamic general equilibrium models (Pant, H. M. 2010). Planted or naturally regenerating production forests are represented by a set of multiperiod production functions corresponding to a discrete set of harvest ages. Complementarity between negative profits and output allow for the endogenous selection of the optimal age(s) at any time under conditions of perfect foresight. A comparable bottom-up treatment of timber production from and clearance of primary forests is the subject of ongoing research. These dynamic representations of forestry in a general equilibrium framework will allow for more robust assessments of policies such as domestic greenhouse gas emissions trading schemes or Reducing Emissions from Degradation and Deforestation (REDD) Plus in developed and developing countries. Computational limitations on direct bottom-up integration may be prohibited for models with more sectoral or regional detail. However, larger models should be tractable with the aid of decomposition techniques, which allow for tight and theoretically consistent linking of a top-down general equilibrium model with bottom-up partial equilibrium sub-models. This is also the subject of our own-going research An illustrative scenario using a four-region version of our CliMAT-DGE model with bottom-up forestry showed the effects of carbon credits for HWPs in the US, within a wider context of CO2 emissions pricing by developed countries. We showed not only a significant expansion of forestland and output in the US, but changes in age composition of the forest estate and harvest ages during a six decade transition. Marginal flow-on effects of the US HWP credits were small, but larger effects could be expected for policies affecting a larger share of global forest production, or in regions where forestry is economically more important. Computational considerations limit the number of regions and the level of bottom-up detail achievable through direct bottom-up integration. However, larger models should be solvable with the aid of decomposition techniques, which allow tight and theoretically consistent linking of a top-down model with bottom-up sub-models. This is another focus of our own-going research. | H48: Proceedings Paper | I48: 2011 | J48: 0 | M48: =LEFT($D48,FIND(",",$D48)-1)&"_"&I48&L48 -> Lennox_2011 | N48: no journal | O48: SL | Q48: v5 | CA48: =IFERROR(BZ48/BQ48,"") | CT48: =IF(BI48="Roundwood",$CS48/2,$CS48) -> 0 | CX48: =IFERROR($CW48/$CS48,"") | CZ48: =IFERROR($CW48/$CT48,"") | EP48: =IF(AND(AND(AND(OR($EC48=1,$EB48=1),OR($EH48=1,$EF48=1)),SUM($EA48:$EE48,$EK48)>=3),SUM($EF48:$EJ48)>=2),"Whole sector approach","") | EQ48: =IF(AND(AND(OR($EC48=1,$EB48=1),AND($EH48=0,$EF48=0)),SUM($EA48:$EE48,$EK48)>=3),"Ecosystem approach","") | ER48: =IF(AND(AND(AND($EC48=0,$EB48=0),OR($EH48=1,$EF48=1)),SUM($EG48:$EJ48)>=2),"Technology approach","") | ES48: =IF(AND($EC48+$EB48+$EE48+$EA48+$EF48+$EG48=0,$N48="included"),"C neutral forest and HWP assumption","") | ET48: =IF(AND(AND(AND($EC48+$EB48+$EA48+$EG48>=2,$EF48+$EH48+$EI48>=1),$ED48+$EE48>=1),$N48="included"),"All C pools assumption","") | EU48: =IF(AND($ED48+$EE48+$EI48+$EH48+$EF48=0,$N48="included"),"In-situ only assumption","") | EX48: changed_to_no_journal | EY48: =IF(ISNUMBER(BW48),IF(ABS(BW48-[1]QC_indicators!$B$2)>3*[1]QC_indicators!$C$2,"C ratio",IF(ISNUMBER(CA48),IF(ABS(CA48-[1]QC_indicators!$B$1)>3*[1]QC_indicators!$C$1,"DF","no"))),IF(ISNUMBER(CA48),IF(ABS(CA48-[1]QC_indicators!$B$1)>3*[1]QC_indicators!$C$1,"DF","no"))) -> FALSE | FA48: =IF(LEN($CY48)=0,"",IF(AND($CY48<(-0.05),$ES48="C neutral forest and HWP assumption"),"Cneutral paradox",IF(AND($CY48>0.05,$EU48="In-situ only assumption"),"In-situ only paradox","")))
A49: PROCEEDINGS OF AICCE&apos;19: TRANSFORMING THE NATION FOR A SUSTAINABLE TOMORROW | B49: Carbon footprint; Industrialised building system; Life cycle assessment | C49: EMISSIONS | D49: Lip, YY; Teo, FY; Tang, IYH | E49: Carbon Footprint Analysis of Industrialised Building System in Malaysia | F49: The topic on sustainability of Industrialised Building System (IBS) in the construction industry of Malaysia is always debatable and questionable. This study is carried out to determine the carbon footprint of a typical commercial project with the application of IBS. In this paper, IBS is classified to aluminium formwork system and fully precast concrete structure. The carbon footprint is quantified with life cycle assessment (LCA) of the building dividing into production phase of materials, transportation phase and construction phase. Whereas the study adopted data of embodied carbon of materials and carbon emission factor from reliable external source to estimate the total carbon emission of the project with the application of IBS. The outcome of carbon footprint is compared with conventional building method to identify the sustainability of each building method. Based on the data analysis, the application of precast concrete has the lowest carbon footprint as compared to cast-in situ with aluminium formwork and timber formwork. Although the carbon emission from the transportation of precast concrete elements is relatively high, but the overall carbon footprint is still the lowest among the other building method. The amount of carbon emission of the commercial project with IBS construction is 0.342 tonnes CO2 per meter square. The production of construction materials that contributed the most to the carbon footprint is concrete, followed by steel rebar and formwork. The findings in this study is very useful for future research on carbon footprint of construction in Malaysia. The study also helps to raise awareness towards sustainable construction with the application of IBS in Malaysia. | H49: Proceedings Paper | I49: 2020 | J49: 0 | K49: 10.1007/978-3-030-32816-0_59 | M49: =LEFT($D49,FIND(",",$D49)-1)&"_"&I49&L49 -> Lip_2020 | N49: no journal | O49: SL | Q49: v5 | CA49: =IFERROR(BZ49/BQ49,"") | CT49: =IF(BI49="Roundwood",$CS49/2,$CS49) -> 0 | CX49: =IFERROR($CW49/$CS49,"") | CZ49: =IFERROR($CW49/$CT49,"") | EP49: =IF(AND(AND(AND(OR($EC49=1,$EB49=1),OR($EH49=1,$EF49=1)),SUM($EA49:$EE49,$EK49)>=3),SUM($EF49:$EJ49)>=2),"Whole sector approach","") | EQ49: =IF(AND(AND(OR($EC49=1,$EB49=1),AND($EH49=0,$EF49=0)),SUM($EA49:$EE49,$EK49)>=3),"Ecosystem approach","") | ER49: =IF(AND(AND(AND($EC49=0,$EB49=0),OR($EH49=1,$EF49=1)),SUM($EG49:$EJ49)>=2),"Technology approach","") | ES49: =IF(AND($EC49+$EB49+$EE49+$EA49+$EF49+$EG49=0,$N49="included"),"C neutral forest and HWP assumption","") | ET49: =IF(AND(AND(AND($EC49+$EB49+$EA49+$EG49>=2,$EF49+$EH49+$EI49>=1),$ED49+$EE49>=1),$N49="included"),"All C pools assumption","") | EU49: =IF(AND($ED49+$EE49+$EI49+$EH49+$EF49=0,$N49="included"),"In-situ only assumption","") | EW49: The Study deals with an LCA of prefab aluminum components. The word "wood" or "forest" were not mentioned in the manuscript. | EX49: changed_to_nojournal | EY49: =IF(ISNUMBER(BW49),IF(ABS(BW49-[1]QC_indicators!$B$2)>3*[1]QC_indicators!$C$2,"C ratio",IF(ISNUMBER(CA49),IF(ABS(CA49-[1]QC_indicators!$B$1)>3*[1]QC_indicators!$C$1,"DF","no"))),IF(ISNUMBER(CA49),IF(ABS(CA49-[1]QC_indicators!$B$1)>3*[1]QC_indicators!$C$1,"DF","no"))) -> FALSE | FA49: =IF(LEN($CY49)=0,"",IF(AND($CY49<(-0.05),$ES49="C neutral forest and HWP assumption"),"Cneutral paradox",IF(AND($CY49>0.05,$EU49="In-situ only assumption"),"In-situ only paradox","")))
A50: LESNOY ZHURNAL-FORESTRY JOURNAL | B50: boiler; wood pellet fuel; harmful substances; numerical modeling; heat losses; efficiency | C50: COMBUSTION; GRATE | D50: Lyubov, VK; Vladimirov, AM | E50: COMPLEX EFFICIENCY OF USING WOOD PELLETS IN POWER PLANTS | F50: In advanced countries, the dramatic impact of greenhouse gases on the global climate is reduced by replacing fossil fuels with biofuels. This method is being actively encouraged. However, by-products of logging, processing and conversion of wood are classified as difficult to burn fuels due to their high moisture content, low energy density and extremely heterogeneous granulometric composition. A promising direction to increase the energy density and transportability of the timber industry by-products is their granulation. Wood pellet fuel burning in heat-generating plants results in significant increase in their energy and environmental performance. The purpose of the paper is an experimental and calculation study of the energy and environmental performance of 4 MW hot water boilers produced by Polytechnik Luft- und Feuerungstechnik GmbH in the process of burning pine and spruce wood pellets obtained from by-products woodworking. When performing studies, the components of the boiler&apos;s heat balance, gas release, and particulate emissions were determined. Numerical modeling of thermochemical and aerodynamic processes taking place in the boiler combustion chamber was carried out by using the Ansys Fluent three-dimensional simulation software. Together with industrial-operational tests it showed the possibility to reduce the total share of flue gas recirculation into combustion chambers of boiler units to values not exceeding 0.45, in providing an acceptable temperature of combustion products at the combustion chamber outlet and maintaining minimum emissions of carbon and nitrogen monoxides. At the same time, the share of gases fed by recirculation smoke exhausters to the over-bed area of the burner should have higher values than under the reciprocating grates of boilers. Guidelines for comprehensive improvement of wood pellet combustion efficiency in combustion chamber of 4 MW hot water boilers have been developed and implemented. The priorities are: using the air passed through the cooling channels of the setting as secondary air; reducing the rarefaction in the combustion chambers to 30-70 Pa; optimizing the ratio of primary and secondary air, herewith, the share of primary air in the total flow should be 0.26-0.35. Implementation of the developed guidelines allowed to increase the boiler gross efficiency by 0.5-1.8 %, to reduce the aerodynamic resistance of the gas path by 15-20 % and to ensure consistently low emissions of carbon and nitrogen monoxides and soot particles. When designing boiler units for burning wood pellet fuel it is advisable to place heating surfaces in the combustion chamber, included in the circulation circuit of the boiler. This will increase the efficiency and life cycle of the boiler unit. | G50: Lesnoy Zh. | H50: Article | I50: 2021 | J50: 0 | K50: 10.37482/0536-1036-2021-1-159-172 | M50: =LEFT($D50,FIND(",",$D50)-1)&"_"&I50&L50 -> Lyubov_2021 | N50: no journal | O50: SL | Q50: v5 | CA50: =IFERROR(BZ50/BQ50,"") | CT50: =IF(BI50="Roundwood",$CS50/2,$CS50) -> 0 | CX50: =IFERROR($CW50/$CS50,"") | CZ50: =IFERROR($CW50/$CT50,"") | EP50: =IF(AND(AND(AND(OR($EC50=1,$EB50=1),OR($EH50=1,$EF50=1)),SUM($EA50:$EE50,$EK50)>=3),SUM($EF50:$EJ50)>=2),"Whole sector approach","") | EQ50: =IF(AND(AND(OR($EC50=1,$EB50=1),AND($EH50=0,$EF50=0)),SUM($EA50:$EE50,$EK50)>=3),"Ecosystem approach","") | ER50: =IF(AND(AND(AND($EC50=0,$EB50=0),OR($EH50=1,$EF50=1)),SUM($EG50:$EJ50)>=2),"Technology approach","") | ES50: =IF(AND($EC50+$EB50+$EE50+$EA50+$EF50+$EG50=0,$N50="included"),"C neutral forest and HWP assumption","") | ET50: =IF(AND(AND(AND($EC50+$EB50+$EA50+$EG50>=2,$EF50+$EH50+$EI50>=1),$ED50+$EE50>=1),$N50="included"),"All C pools assumption","") | EU50: =IF(AND($ED50+$EE50+$EI50+$EH50+$EF50=0,$N50="included"),"In-situ only assumption","") | EW50: It is written in Russian. | EX50: okVB | EY50: =IF(ISNUMBER(BW50),IF(ABS(BW50-[1]QC_indicators!$B$2)>3*[1]QC_indicators!$C$2,"C ratio",IF(ISNUMBER(CA50),IF(ABS(CA50-[1]QC_indicators!$B$1)>3*[1]QC_indicators!$C$1,"DF","no"))),IF(ISNUMBER(CA50),IF(ABS(CA50-[1]QC_indicators!$B$1)>3*[1]QC_indicators!$C$1,"DF","no"))) -> FALSE | FA50: =IF(LEN($CY50)=0,"",IF(AND($CY50<(-0.05),$ES50="C neutral forest and HWP assumption"),"Cneutral paradox",IF(AND($CY50>0.05,$EU50="In-situ only assumption"),"In-situ only paradox","")))
A51: GREENHOUSE GAS CONTROL TECHNOLOGIES, VOLS I AND II, PROCEEDINGS | D51: Read, P; Lermit, J; Kathirgamanathan, P | E51: Modelling bio-energy with carbon storage (BECS) in a multi-region version of flames | F51: Global FLAMES [1,2] demonstrates the potential of the combined evolution of the stock and flow effects from temporary sequestration and subsequent fossil fuel displacement due to plantation based bio-energy, in reducing greenhouse gas levels below those widely thought to be feasible [3]. This surprising effectiveness can be further enhanced by linking plantation bio-energy to carbon capture and storage [4]. Such 'BECS' technology yields, potentially, a negative emissions energy system and control of CO2 levels on a few decade time-scale. The effect of BECS is illustrated using global FLAMES. To provide relevance to country level scenario building and decision taking, FLAMES has been developed [5] into a multi-region dynamic market model simulating trade in fossil fuel, biofuel, and timber products. Results are illustrated in the case of three notional regions, 'rich', 'landed' and 'popet' (populous with petroleum) - broadly equivalent to the 'North', South Sahara Africa with Southern America, and Asia plus OPEC. | H51: Proceedings Paper | I51: 2003 | J51: 0 | M51: =LEFT($D51,FIND(",",$D51)-1)&"_"&I51&L51 -> Read_2003 | N51: no journal | O51: TH | Q51: v5 | CA51: =IFERROR(BZ51/BQ51,"") | CT51: =IF(BI51="Roundwood",$CS51/2,$CS51) -> 0 | CX51: =IFERROR($CW51/$CS51,"") | CZ51: =IFERROR($CW51/$CT51,"") | EP51: =IF(AND(AND(AND(OR($EC51=1,$EB51=1),OR($EH51=1,$EF51=1)),SUM($EA51:$EE51,$EK51)>=3),SUM($EF51:$EJ51)>=2),"Whole sector approach","") | EQ51: =IF(AND(AND(OR($EC51=1,$EB51=1),AND($EH51=0,$EF51=0)),SUM($EA51:$EE51,$EK51)>=3),"Ecosystem approach","") | ER51: =IF(AND(AND(AND($EC51=0,$EB51=0),OR($EH51=1,$EF51=1)),SUM($EG51:$EJ51)>=2),"Technology approach","") | ES51: =IF(AND($EC51+$EB51+$EE51+$EA51+$EF51+$EG51=0,$N51="included"),"C neutral forest and HWP assumption","") | ET51: =IF(AND(AND(AND($EC51+$EB51+$EA51+$EG51>=2,$EF51+$EH51+$EI51>=1),$ED51+$EE51>=1),$N51="included"),"All C pools assumption","") | EU51: =IF(AND($ED51+$EE51+$EI51+$EH51+$EF51=0,$N51="included"),"In-situ only assumption","") | EX51: okVB | EY51: =IF(ISNUMBER(BW51),IF(ABS(BW51-[1]QC_indicators!$B$2)>3*[1]QC_indicators!$C$2,"C ratio",IF(ISNUMBER(CA51),IF(ABS(CA51-[1]QC_indicators!$B$1)>3*[1]QC_indicators!$C$1,"DF","no"))),IF(ISNUMBER(CA51),IF(ABS(CA51-[1]QC_indicators!$B$1)>3*[1]QC_indicators!$C$1,"DF","no"))) -> FALSE | FA51: =IF(LEN($CY51)=0,"",IF(AND($CY51<(-0.05),$ES51="C neutral forest and HWP assumption"),"Cneutral paradox",IF(AND($CY51>0.05,$EU51="In-situ only assumption"),"In-situ only paradox","")))
A52: FARM MACHINERY AND PROCESSES MANAGEMENT IN SUSTAINABLE AGRICULTURE | B52: greenhouse gas emissions; bioenergy; short rotation coppice; willow | D52: Rodzkin, A; Kostukevich, S; Tanas, W; Szymanek, M; Kassar, FH | E52: ASSESSMENT OF THE BALANCE OF GREENHOUSE GASES IN THE PRODUCTION OF RENEWABLE BIOMASS FROM SHORT-CYCLE ENERGY PLANTATIONS OF WILLOW | F52: Greenhouse gas control it is the key aspect for climate protection. As climate regulation became inevitable, companies started adopting more proactive strategies. One of the effective methods for greenhouse gas emission calculation is based on life cycle analysis. A carbon footprint is defined as the sum of greenhouse gas emissions caused by an organization, event, or product and is expressed in terms of CO2 equivalents. The investigations were devoted to greenhouse emission assessment during life cycle of willow wood production from short rotation coppice plantations. In accordance with results about 48% of carbon dioxide gas from all life cycle of willow was emitted during wood harvesting and transportation to energy plants. | H52: Proceedings Paper | I52: 2017 | J52: 0 | K52: 10.24326/fmpmsa.2017.60 | M52: =LEFT($D52,FIND(",",$D52)-1)&"_"&I52&L52 -> Rodzkin_2017 | N52: no journal | O52: TH | Q52: v5 | CA52: =IFERROR(BZ52/BQ52,"") | CT52: =IF(BI52="Roundwood",$CS52/2,$CS52) -> 0 | CX52: =IFERROR($CW52/$CS52,"") | CZ52: =IFERROR($CW52/$CT52,"") | EP52: =IF(AND(AND(AND(OR($EC52=1,$EB52=1),OR($EH52=1,$EF52=1)),SUM($EA52:$EE52,$EK52)>=3),SUM($EF52:$EJ52)>=2),"Whole sector approach","") | EQ52: =IF(AND(AND(OR($EC52=1,$EB52=1),AND($EH52=0,$EF52=0)),SUM($EA52:$EE52,$EK52)>=3),"Ecosystem approach","") | ER52: =IF(AND(AND(AND($EC52=0,$EB52=0),OR($EH52=1,$EF52=1)),SUM($EG52:$EJ52)>=2),"Technology approach","") | ES52: =IF(AND($EC52+$EB52+$EE52+$EA52+$EF52+$EG52=0,$N52="included"),"C neutral forest and HWP assumption","") | ET52: =IF(AND(AND(AND($EC52+$EB52+$EA52+$EG52>=2,$EF52+$EH52+$EI52>=1),$ED52+$EE52>=1),$N52="included"),"All C pools assumption","") | EU52: =IF(AND($ED52+$EE52+$EI52+$EH52+$EF52=0,$N52="included"),"In-situ only assumption","") | EX52: okVB | EY52: =IF(ISNUMBER(BW52),IF(ABS(BW52-[1]QC_indicators!$B$2)>3*[1]QC_indicators!$C$2,"C ratio",IF(ISNUMBER(CA52),IF(ABS(CA52-[1]QC_indicators!$B$1)>3*[1]QC_indicators!$C$1,"DF","no"))),IF(ISNUMBER(CA52),IF(ABS(CA52-[1]QC_indicators!$B$1)>3*[1]QC_indicators!$C$1,"DF","no"))) -> FALSE | FA52: =IF(LEN($CY52)=0,"",IF(AND($CY52<(-0.05),$ES52="C neutral forest and HWP assumption"),"Cneutral paradox",IF(AND($CY52>0.05,$EU52="In-situ only assumption"),"In-situ only paradox","")))
A53: PAPERS OF THE 22ND EUROPEAN BIOMASS CONFERENCE: SETTING THE COURSE FOR A BIOBASED ECONOMY | B53: Canada; managed forest; harvested wood product (HWP); wood pellets; life cycle analysis; cascade | D53: Sikkema, R; Junginger, HM; Faaij, APC; McFarlane, P | E53: THE CASCADED USE OF HARVESTED WOOD PRODUCTS COMPARED WITH THE USE OF WOOD FOR ENERGY - A GHG INVENTORY ON AVAILABLE FOREST RESOURCES IN CANADA | F53: Some Parties (Countries) to the UNFCCC decided to include the carbon uptake by harvested wood products (HWP) in a new general accounting framework after 2012 (post Kyoto). We combine the new HWP framework with an assumed increased 5 0 million m(3) harvest level in Canada and evaluate the impact of the GHG emissions over a 100 year period. Our reference case assumes all harvested wood is an immediate CO2 emission (IPCC default) and no substitution effects, i.e. annual GHG emissions of 41 million tonnes CO2eq. In our wood utilisation scenarios, harvested trees are allocated to three end-products: construction wood, paper products and pellets for power production. In comparison with our base case, a combination of fossil fuel substitution, material substitution and temporary carbon uptake by HWP leads to significant decreases in GHG emissions. A similar approach is intended for future EU-28 harvesting. | H53: Proceedings Paper | I53: 2014 | J53: 0 | M53: =LEFT($D53,FIND(",",$D53)-1)&"_"&I53&L53 -> Sikkema_2014 | N53: no journal | O53: TH | Q53: v5 | CA53: =IFERROR(BZ53/BQ53,"") | CT53: =IF(BI53="Roundwood",$CS53/2,$CS53) -> 0 | CX53: =IFERROR($CW53/$CS53,"") | CZ53: =IFERROR($CW53/$CT53,"") | EP53: =IF(AND(AND(AND(OR($EC53=1,$EB53=1),OR($EH53=1,$EF53=1)),SUM($EA53:$EE53,$EK53)>=3),SUM($EF53:$EJ53)>=2),"Whole sector approach","") | EQ53: =IF(AND(AND(OR($EC53=1,$EB53=1),AND($EH53=0,$EF53=0)),SUM($EA53:$EE53,$EK53)>=3),"Ecosystem approach","") | ER53: =IF(AND(AND(AND($EC53=0,$EB53=0),OR($EH53=1,$EF53=1)),SUM($EG53:$EJ53)>=2),"Technology approach","") | ES53: =IF(AND($EC53+$EB53+$EE53+$EA53+$EF53+$EG53=0,$N53="included"),"C neutral forest and HWP assumption","") | ET53: =IF(AND(AND(AND($EC53+$EB53+$EA53+$EG53>=2,$EF53+$EH53+$EI53>=1),$ED53+$EE53>=1),$N53="included"),"All C pools assumption","") | EU53: =IF(AND($ED53+$EE53+$EI53+$EH53+$EF53=0,$N53="included"),"In-situ only assumption","") | EX53: okVB | EY53: =IF(ISNUMBER(BW53),IF(ABS(BW53-[1]QC_indicators!$B$2)>3*[1]QC_indicators!$C$2,"C ratio",IF(ISNUMBER(CA53),IF(ABS(CA53-[1]QC_indicators!$B$1)>3*[1]QC_indicators!$C$1,"DF","no"))),IF(ISNUMBER(CA53),IF(ABS(CA53-[1]QC_indicators!$B$1)>3*[1]QC_indicators!$C$1,"DF","no"))) -> FALSE | FA53: =IF(LEN($CY53)=0,"",IF(AND($CY53<(-0.05),$ES53="C neutral forest and HWP assumption"),"Cneutral paradox",IF(AND($CY53>0.05,$EU53="In-situ only assumption"),"In-situ only paradox","")))
A54: STRUCTURES AND ARCHITECTURE: CONCEPTS: APPLICATIONS AND CHALLENGES | D54: Spinelli, A | E54: Convertible city: light wood prefab systems in the extension of built environment | F54: The research work proposes a reflection about transforming existing city. The paper focus about transformation projects which considering the addition of part and volumes an opportunity to redefine performance and architectural appeal of existent building and renovate the whole city functioning. The research refers to urban living context and housing quality, by using timber technology as method to read the change towards new smart urban environment. This topic becomes the driving force at the center of development actions in many European medium cities, promoting a new research approach against soil consumption. Thus represent an opportunity to experiment new forms of living and search further directions for the building sector. Wood can be seen as the most suitable material for these interventions, it offers the opportunity to reduce energy consumption and CO2 emissions during the entire construction process and the building life cycle. | H54: Proceedings Paper | I54: 2013 | J54: 0 | M54: =LEFT($D54,FIND(",",$D54)-1)&"_"&I54&L54 -> Spinelli_2013 | N54: no journal | O54: TH | Q54: v5 | CA54: =IFERROR(BZ54/BQ54,"") | CT54: =IF(BI54="Roundwood",$CS54/2,$CS54) -> 0 | CX54: =IFERROR($CW54/$CS54,"") | CZ54: =IFERROR($CW54/$CT54,"") | EP54: =IF(AND(AND(AND(OR($EC54=1,$EB54=1),OR($EH54=1,$EF54=1)),SUM($EA54:$EE54,$EK54)>=3),SUM($EF54:$EJ54)>=2),"Whole sector approach","") | EQ54: =IF(AND(AND(OR($EC54=1,$EB54=1),AND($EH54=0,$EF54=0)),SUM($EA54:$EE54,$EK54)>=3),"Ecosystem approach","") | ER54: =IF(AND(AND(AND($EC54=0,$EB54=0),OR($EH54=1,$EF54=1)),SUM($EG54:$EJ54)>=2),"Technology approach","") | ES54: =IF(AND($EC54+$EB54+$EE54+$EA54+$EF54+$EG54=0,$N54="included"),"C neutral forest and HWP assumption","") | ET54: =IF(AND(AND(AND($EC54+$EB54+$EA54+$EG54>=2,$EF54+$EH54+$EI54>=1),$ED54+$EE54>=1),$N54="included"),"All C pools assumption","") | EU54: =IF(AND($ED54+$EE54+$EI54+$EH54+$EF54=0,$N54="included"),"In-situ only assumption","") | EX54: okVB | EY54: =IF(ISNUMBER(BW54),IF(ABS(BW54-[1]QC_indicators!$B$2)>3*[1]QC_indicators!$C$2,"C ratio",IF(ISNUMBER(CA54),IF(ABS(CA54-[1]QC_indicators!$B$1)>3*[1]QC_indicators!$C$1,"DF","no"))),IF(ISNUMBER(CA54),IF(ABS(CA54-[1]QC_indicators!$B$1)>3*[1]QC_indicators!$C$1,"DF","no"))) -> FALSE | FA54: =IF(LEN($CY54)=0,"",IF(AND($CY54<(-0.05),$ES54="C neutral forest and HWP assumption"),"Cneutral paradox",IF(AND($CY54>0.05,$EU54="In-situ only assumption"),"In-situ only paradox","")))
A55: STAHLBAU | B55: sustainability; embodied emissions; resource efficiency; lightweight structures; circular construction; life cycle expansion; material use; infra-lightweight-concrete | D55: Stockhusen, K; Erichsen, J | E55: The net zero as a target: examples for building in line with the reduce-reuse-recycle principle | F55: The building sector is currently facing an unprecedented challenge: How can we drastically reduce emissions of climate-damaging greenhouse gases and still meet the growing global demand for a built environment? It is certain that sustainability can only be achieved through a holistic architectural approach. Just as important as taking into account operational emissions are the emissions generated during construction itself. After all, the amount of these embodied emissions produced by 2050 is crucial to achieving the United Nations' climate goals. The three R's of Reduce - Reuse - Recycle are essential for the building industry to be able to meet these objectives. In the following, projects are presented that are guided by these three R's and successfully demonstrate how innovative approaches and concepts can drive the change to net-zero. Among these are the roof of the Olympic Stadium in Munich as a pioneering model for all light-weight structures, the hanging timber canopy for the 2024 Olympic Aquatics Center in Paris as an example of materials-based design, the free-form steel and glass domes of the Moynihan Train Hall in New York City, as well as the modular container stadium serving as examples for preserving and extending the life cycle of structures or entire building components, the City of Dream Pavilion Cast & Place made of recycled aluminum, and the youth facility Betonoase in Berlin, whose exterior walls and porches are made of the particularly recycling-friendly infra-light concrete (ILC). | G55: Stahlbau | H55: Article | I55: 2022 | J55: 1 | K55: 10.1002/stab.202200006 | M55: =LEFT($D55,FIND(",",$D55)-1)&"_"&I55&L55 -> Stockhusen_2022 | N55: no journal | CA55: =IFERROR(BZ55/BQ55,"") | CT55: =IF(BI55="Roundwood",$CS55/2,$CS55) -> 0 | CX55: =IFERROR($CW55/$CS55,"") | CZ55: =IFERROR($CW55/$CT55,"") | EP55: =IF(AND(AND(AND(OR($EC55=1,$EB55=1),OR($EH55=1,$EF55=1)),SUM($EA55:$EE55,$EK55)>=3),SUM($EF55:$EJ55)>=2),"Whole sector approach","") | EQ55: =IF(AND(AND(OR($EC55=1,$EB55=1),AND($EH55=0,$EF55=0)),SUM($EA55:$EE55,$EK55)>=3),"Ecosystem approach","") | ER55: =IF(AND(AND(AND($EC55=0,$EB55=0),OR($EH55=1,$EF55=1)),SUM($EG55:$EJ55)>=2),"Technology approach","") | ES55: =IF(AND($EC55+$EB55+$EE55+$EA55+$EF55+$EG55=0,$N55="included"),"C neutral forest and HWP assumption","") | ET55: =IF(AND(AND(AND($EC55+$EB55+$EA55+$EG55>=2,$EF55+$EH55+$EI55>=1),$ED55+$EE55>=1),$N55="included"),"All C pools assumption","") | EU55: =IF(AND($ED55+$EE55+$EI55+$EH55+$EF55=0,$N55="included"),"In-situ only assumption","") | EY55: =IF(ISNUMBER(BW55),IF(ABS(BW55-[1]QC_indicators!$B$2)>3*[1]QC_indicators!$C$2,"C ratio",IF(ISNUMBER(CA55),IF(ABS(CA55-[1]QC_indicators!$B$1)>3*[1]QC_indicators!$C$1,"DF","no"))),IF(ISNUMBER(CA55),IF(ABS(CA55-[1]QC_indicators!$B$1)>3*[1]QC_indicators!$C$1,"DF","no"))) -> FALSE | FA55: =IF(LEN($CY55)=0,"",IF(AND($CY55<(-0.05),$ES55="C neutral forest and HWP assumption"),"Cneutral paradox",IF(AND($CY55>0.05,$EU55="In-situ only assumption"),"In-situ only paradox","")))
A56: ECOLOGY, ECONOMICS, EDUCATION AND LEGISLATION, VOL I | B56: civil engineering; timber products; sustainable; GFRP; LCA | D56: Taranu, N; Maxineasa, SG; Entuc, IS; Oprisan, G; Secu, A | E56: Assessing the environmental impact of a glass fibre reinforced polymer strengthening solution for timber beams | F56: It is common knowledge that forests represent the most proficient tool of the planet Earth for improving air quality, by sequestering and replacing a significant volume of carbon dioxide (CO2) with oxygen (O-2). Moreover, wood plantations are known to provide a natural habitat for animals, making them an important element in the global efforts of protecting the fauna. Due to the crucial influence of trees in ensuring such life conditions, during the latest years, international debates concerning the protection of old-growth forests by reducing the consumption of trees as a material in different economic industries have intensified. World-wide, a significant amount of wood is processed in order to be utilised in the civil engineering sector. Even if the utilization of trees from certified forests is encouraged, at the moment, only a small part of the amount of timber products used in this sector is fabricated by processing materials originated from sustainable wood plantations. Therefore, besides increasing the volume of the processed certified trees, the construction field should also implement new solutions in order to minimize the environmental load resulted from using uncertified timber solutions. The reusing of existing timber structures by applying different fibre reinforced polymer (FRP) composites strengthening solutions can represent an efficient approach for achieving this goal. The present paper evaluates the environmental impact of a glass fibre reinforced polymer (GFRP) strengthening technique utilized on a timber beam by using the Life Cycle Assessment (LCA) methodology and the GaBi 6 software. The resulted values point to the fact that despite their negative influence, FRP materials can have an important role in protecting and improving the condition of the natural environment by reducing the quantity of timber used in this sector. | H56: Proceedings Paper | I56: 2015 | J56: 2 | M56: =LEFT($D56,FIND(",",$D56)-1)&"_"&I56&L56 -> Taranu_2015 | N56: no journal | O56: VB | Q56: v5 | CA56: =IFERROR(BZ56/BQ56,"") | CT56: =IF(BI56="Roundwood",$CS56/2,$CS56) -> 0 | CX56: =IFERROR($CW56/$CS56,"") | CZ56: =IFERROR($CW56/$CT56,"") | EP56: =IF(AND(AND(AND(OR($EC56=1,$EB56=1),OR($EH56=1,$EF56=1)),SUM($EA56:$EE56,$EK56)>=3),SUM($EF56:$EJ56)>=2),"Whole sector approach","") | EQ56: =IF(AND(AND(OR($EC56=1,$EB56=1),AND($EH56=0,$EF56=0)),SUM($EA56:$EE56,$EK56)>=3),"Ecosystem approach","") | ER56: =IF(AND(AND(AND($EC56=0,$EB56=0),OR($EH56=1,$EF56=1)),SUM($EG56:$EJ56)>=2),"Technology approach","") | ES56: =IF(AND($EC56+$EB56+$EE56+$EA56+$EF56+$EG56=0,$N56="included"),"C neutral forest and HWP assumption","") | ET56: =IF(AND(AND(AND($EC56+$EB56+$EA56+$EG56>=2,$EF56+$EH56+$EI56>=1),$ED56+$EE56>=1),$N56="included"),"All C pools assumption","") | EU56: =IF(AND($ED56+$EE56+$EI56+$EH56+$EF56=0,$N56="included"),"In-situ only assumption","") | EX56: okAV | EY56: =IF(ISNUMBER(BW56),IF(ABS(BW56-[1]QC_indicators!$B$2)>3*[1]QC_indicators!$C$2,"C ratio",IF(ISNUMBER(CA56),IF(ABS(CA56-[1]QC_indicators!$B$1)>3*[1]QC_indicators!$C$1,"DF","no"))),IF(ISNUMBER(CA56),IF(ABS(CA56-[1]QC_indicators!$B$1)>3*[1]QC_indicators!$C$1,"DF","no"))) -> FALSE | FA56: =IF(LEN($CY56)=0,"",IF(AND($CY56<(-0.05),$ES56="C neutral forest and HWP assumption"),"Cneutral paradox",IF(AND($CY56>0.05,$EU56="In-situ only assumption"),"In-situ only paradox","")))
